Workbook

Sheet Scenario
B2: Financial KPI and scenario model
B4: Case Selected: | C4: 1 | D4: =IF(C4=1,"Base",IF(C4=2,"Downside",IF(C4=3,"Upside","Invalid case"))) -> Base | G4: 1 Base 2 Downside 3 Upside
B5: Hypothetical next own fiscal year after FY2025. Not guidance, budget or actual FY2026.
B7: Selected result | C7: Visa | D7: Mastercard
B8: FY2025 baseline end | C8: ='Historical KPIs'!G10 -> 45930 | D8: ='Historical KPIs'!G48 -> 46022 | G8: Issuer | H8: FY2025 actual | I8: Selected scenario
B9: Hypothetical period end | C9: =DATE(YEAR(C8)+1,MONTH(C8),DAY(C8)) -> 46295 | D9: =DATE(YEAR(D8)+1,MONTH(D8),DAY(D8)) -> 46387 | G9: Visa | H9: =C31 -> 23994 | I9: =C37 -> 26400
B10: Scenario revenue (USDm) | C10: =C35 -> 44000 | D10: =D35 -> 36725.92 | G10: Mastercard | H10: =D31 -> 18897 | I10: =D37 -> 21301.034
B11: Scenario operating income (USDm) | C11: =C37 -> 26400 | D11: =D37 -> 21301.034
B12: Scenario operating margin | C12: =C38 -> 0.6 | D12: =D38 -> 0.58
B13: Op income change vs FY25 (USDm) | C13: =C39 -> 2406 | D13: =D39 -> 2404.0336
B14: Revenue change vs FY25 (USDm) | C14: =C40 -> 4000 | D14: =D40 -> 3934.92
B17: Editable assumptions
G18: Amber cells: edit assumptions.
B19: Revenue growth: Active Selection | C19: =IF(AND(ISNUMBER($C$4),OR($C$4=1,$C$4=2,$C$4=3)),IF(CHOOSE($C$4,ISNUMBER(C20),ISNUMBER(C21),ISNUMBER(C22)),IF(CHOOSE($C$4,C20,C21,C22)>=-1,CHOOSE($C$4,C20,C21,C22),"n.a."),"n.a."),"n.a.") -> 0.1 | D19: =IF(AND(ISNUMBER($C$4),OR($C$4=1,$C$4=2,$C$4=3)),IF(CHOOSE($C$4,ISNUMBER(D20),ISNUMBER(D21),ISNUMBER(D22)),IF(CHOOSE($C$4,D20,D21,D22)>=-1,CHOOSE($C$4,D20,D21,D22),"n.a."),"n.a."),"n.a.") -> 0.12 | G19: Active rows select one case.
B20: Base growth | C20: 0.1 | D20: 0.12 | G20: Costs are implied by revenue and margin.
B21: Downside growth | C21: 0.04 | D21: 0.06
B22: Upside growth | C22: 0.14 | D22: 0.16 | G22: Visa operating income (USDm)
G23: Growth across; margin down
B24: Operating margin: Active Selection | C24: =IF(AND(ISNUMBER($C$4),OR($C$4=1,$C$4=2,$C$4=3)),IF(CHOOSE($C$4,ISNUMBER(C25),ISNUMBER(C26),ISNUMBER(C27)),IF(AND(CHOOSE($C$4,C25,C26,C27)>=-1,CHOOSE($C$4,C25,C26,C27)<=1),CHOOSE($C$4,C25,C26,C27),"n.a."),"n.a."),"n.a.") -> 0.6 | D24: =IF(AND(ISNUMBER($C$4),OR($C$4=1,$C$4=2,$C$4=3)),IF(CHOOSE($C$4,ISNUMBER(D25),ISNUMBER(D26),ISNUMBER(D27)),IF(AND(CHOOSE($C$4,D25,D26,D27)>=-1,CHOOSE($C$4,D25,D26,D27)<=1),CHOOSE($C$4,D25,D26,D27),"n.a."),"n.a."),"n.a.") -> 0.58 | G24: =C37 -> 26400 | H24: =C21 -> 0.04 | I24: =C20 -> 0.1 | J24: =C22 -> 0.14
B25: Base margin | C25: 0.6 | D25: 0.58 | G25: =C26 -> 0.56 | H25: 23296 | I25: 24640 | J25: 25536
B26: Downside margin | C26: 0.56 | D26: 0.54 | G26: =C25 -> 0.6 | H26: 24960 | I26: 26400 | J26: 27360
B27: Upside margin | C27: 0.62 | D27: 0.6 | G27: =C27 -> 0.62 | H27: 25792 | I27: 27280 | J27: 28272
B29: Calculation (USD million)
B30: FY2025 net revenue | C30: ='Historical KPIs'!G12 -> 40000 | D30: ='Historical KPIs'!G50 -> 32791
B31: FY2025 operating income | C31: ='Historical KPIs'!G14 -> 23994 | D31: ='Historical KPIs'!G52 -> 18897
B32: FY2025 operating expenses | C32: ='Historical KPIs'!G13 -> 16006 | D32: ='Historical KPIs'!G51 -> 13894 | G32: Mastercard operating income (USDm)
B33: Revenue growth input | C33: =C19 -> 0.1 | D33: =D19 -> 0.12 | G33: Growth across; margin down
B34: Operating margin input | C34: =C24 -> 0.6 | D34: =D24 -> 0.58 | G34: =D37 -> 21301.034 | H34: =D21 -> 0.06 | I34: =D20 -> 0.12 | J34: =D22 -> 0.16
B35: Scenario revenue | C35: =IF(AND(ISNUMBER(C30),ISNUMBER(C33)),C30*(1+C33),"n.a.") -> 44000 | D35: =IF(AND(ISNUMBER(D30),ISNUMBER(D33)),D30*(1+D33),"n.a.") -> 36725.92 | G35: =D26 -> 0.54 | H35: 18769.568 | I35: 19831.997 | J35: 20540.282
B36: Scenario operating expenses | C36: =IF(AND(ISNUMBER(C35),ISNUMBER(C37)),C35-C37,"n.a.") -> 17600 | D36: =IF(AND(ISNUMBER(D35),ISNUMBER(D37)),D35-D37,"n.a.") -> 15424.886 | G36: =D25 -> 0.58 | H36: 20159.907 | I36: 21301.034 | J36: 22061.785
B37: Scenario operating income | C37: =IF(AND(ISNUMBER(C35),ISNUMBER(C34)),C35*C34,"n.a.") -> 26400 | D37: =IF(AND(ISNUMBER(D35),ISNUMBER(D34)),D35*D34,"n.a.") -> 21301.034 | G37: =D27 -> 0.6 | H37: 20855.076 | I37: 22035.552 | J37: 22822.536
B38: Scenario operating margin | C38: =IF(AND(ISNUMBER(C37),ISNUMBER(C35),C35>0),C37/C35,"n.a.") -> 0.6 | D38: =IF(AND(ISNUMBER(D37),ISNUMBER(D35),D35>0),D37/D35,"n.a.") -> 0.58
B39: Operating income change vs FY25 | C39: =IF(AND(ISNUMBER(C37),ISNUMBER(C31)),C37-C31,"n.a.") -> 2406 | D39: =IF(AND(ISNUMBER(D37),ISNUMBER(D31)),D37-D31,"n.a.") -> 2404.0336
B40: Revenue change vs FY25 | C40: =IF(AND(ISNUMBER(C35),ISNUMBER(C30)),C35-C30,"n.a.") -> 4000 | D40: =IF(AND(ISNUMBER(D35),ISNUMBER(D30)),D35-D30,"n.a.") -> 3934.92
B41: Operating income change (%) | C41: =IF(AND(ISNUMBER(C37),ISNUMBER(C31),C31>0),C37/C31-1,"n.a.") -> 0.10027507 | D41: =IF(AND(ISNUMBER(D37),ISNUMBER(D31),D31>0),D37/D31-1,"n.a.") -> 0.12721774
B42: Implied operating expense change (%) | C42: =IF(AND(ISNUMBER(C36),ISNUMBER(C32),C32>0),C36/C32-1,"n.a.") -> 0.099587655 | D42: =IF(AND(ISNUMBER(D36),ISNUMBER(D32),D32>0),D36/D32-1,"n.a.") -> 0.11018327 | G42: No scenario net income or cash flow is modeled.
G43: Changes compare a scenario with FY2025 actuals.
B44: Revenue - opex - op income | C44: =IF(AND(ISNUMBER(C35),ISNUMBER(C36),ISNUMBER(C37)),C35-C36-C37,"n.a.") -> 0 | D44: =IF(AND(ISNUMBER(D35),ISNUMBER(D36),ISNUMBER(D37)),D35-D36-D37,"n.a.") -> 0 | G44: They are not actual budget variances.
B45: Reconciliation tolerance (USDm) | C45: 0.01 | D45: 0.01

Sheet Historical KPIs
B2: Historical financial KPIs
B3: Reported fiscal years. Amounts in USD million; ratios are unscaled.
B5: Case Selected: | C5: ='Scenario'!D4 -> Base
B7: Visa reported fiscal years
B8: Fiscal year | C8: 2021 | D8: 2022 | E8: 2023 | F8: 2024 | G8: 2025
B9: Period start | C9: 2020-10-01T00:00:00.000Z | D9: 2021-10-01T00:00:00.000Z | E9: 2022-10-01T00:00:00.000Z | F9: 2023-10-01T00:00:00.000Z | G9: 2024-10-01T00:00:00.000Z
B10: Period end | C10: 2021-09-30T00:00:00.000Z | D10: 2022-09-30T00:00:00.000Z | E10: 2023-09-30T00:00:00.000Z | F10: 2024-09-30T00:00:00.000Z | G10: 2025-09-30T00:00:00.000Z
B12: Reported net revenue | C12: =IF(COUNTIFS('Actuals'!$K$6:$K$163,"visa|"&C$8&"|net_revenue")=1,IF(AND(COUNTIFS('Actuals'!$K$6:$K$163,"visa|"&C$8&"|net_revenue",'Actuals'!$F$6:$F$163,"<>")=1,ISNUMBER(_xlfn.XLOOKUP("visa|"&C$8&"|net_revenue",'Actuals'!$K$6:$K$163,'Actuals'!$F$6:$F$163,"n.a.",0)),_xlfn.XLOOKUP("visa|"&C$8&"|net_revenue",'Actuals'!$K$6:$K$163,'Actuals'!$G$6:$G$163,"n.a.",0)="USD"),_xlfn.XLOOKUP("visa|"&C$8&"|net_revenue",'Actuals'!$K$6:$K$163,'Actuals'!$F$6:$F$163,"n.a.",0)/1000000,"n.a."),"n.a.") -> 24105 | D12: =IF(COUNTIFS('Actuals'!$K$6:$K$163,"visa|"&D$8&"|net_revenue")=1,IF(AND(COUNTIFS('Actuals'!$K$6:$K$163,"visa|"&D$8&"|net_revenue",'Actuals'!$F$6:$F$163,"<>")=1,ISNUMBER(_xlfn.XLOOKUP("visa|"&D$8&"|net_revenue",'Actuals'!$K$6:$K$163,'Actuals'!$F$6:$F$163,"n.a.",0)),_xlfn.XLOOKUP("visa|"&D$8&"|net_revenue",'Actuals'!$K$6:$K$163,'Actuals'!$G$6:$G$163,"n.a.",0)="USD"),_xlfn.XLOOKUP("visa|"&D$8&"|net_revenue",'Actuals'!$K$6:$K$163,'Actuals'!$F$6:$F$163,"n.a.",0)/1000000,"n.a."),"n.a.") -> 29310 | E12: =IF(COUNTIFS('Actuals'!$K$6:$K$163,"visa|"&E$8&"|net_revenue")=1,IF(AND(COUNTIFS('Actuals'!$K$6:$K$163,"visa|"&E$8&"|net_revenue",'Actuals'!$F$6:$F$163,"<>")=1,ISNUMBER(_xlfn.XLOOKUP("visa|"&E$8&"|net_revenue",'Actuals'!$K$6:$K$163,'Actuals'!$F$6:$F$163,"n.a.",0)),_xlfn.XLOOKUP("visa|"&E$8&"|net_revenue",'Actuals'!$K$6:$K$163,'Actuals'!$G$6:$G$163,"n.a.",0)="USD"),_xlfn.XLOOKUP("visa|"&E$8&"|net_revenue",'Actuals'!$K$6:$K$163,'Actuals'!$F$6:$F$163,"n.a.",0)/1000000,"n.a."),"n.a.") -> 32653 | F12: =IF(COUNTIFS('Actuals'!$K$6:$K$163,"visa|"&F$8&"|net_revenue")=1,IF(AND(COUNTIFS('Actuals'!$K$6:$K$163,"visa|"&F$8&"|net_revenue",'Actuals'!$F$6:$F$163,"<>")=1,ISNUMBER(_xlfn.XLOOKUP("visa|"&F$8&"|net_revenue",'Actuals'!$K$6:$K$163,'Actuals'!$F$6:$F$163,"n.a.",0)),_xlfn.XLOOKUP("visa|"&F$8&"|net_revenue",'Actuals'!$K$6:$K$163,'Actuals'!$G$6:$G$163,"n.a.",0)="USD"),_xlfn.XLOOKUP("visa|"&F$8&"|net_revenue",'Actuals'!$K$6:$K$163,'Actuals'!$F$6:$F$163,"n.a.",0)/1000000,"n.a."),"n.a.") -> 35926 | G12: =IF(COUNTIFS('Actuals'!$K$6:$K$163,"visa|"&G$8&"|net_revenue")=1,IF(AND(COUNTIFS('Actuals'!$K$6:$K$163,"visa|"&G$8&"|net_revenue",'Actuals'!$F$6:$F$163,"<>")=1,ISNUMBER(_xlfn.XLOOKUP("visa|"&G$8&"|net_revenue",'Actuals'!$K$6:$K$163,'Actuals'!$F$6:$F$163,"n.a.",0)),_xlfn.XLOOKUP("visa|"&G$8&"|net_revenue",'Actuals'!$K$6:$K$163,'Actuals'!$G$6:$G$163,"n.a.",0)="USD"),_xlfn.XLOOKUP("visa|"&G$8&"|net_revenue",'Actuals'!$K$6:$K$163,'Actuals'!$F$6:$F$163,"n.a.",0)/1000000,"n.a."),"n.a.") -> 40000
B13: Reported operating expenses | C13: =IF(COUNTIFS('Actuals'!$K$6:$K$163,"visa|"&C$8&"|operating_expenses")=1,IF(AND(COUNTIFS('Actuals'!$K$6:$K$163,"visa|"&C$8&"|operating_expenses",'Actuals'!$F$6:$F$163,"<>")=1,ISNUMBER(_xlfn.XLOOKUP("visa|"&C$8&"|operating_expenses",'Actuals'!$K$6:$K$163,'Actuals'!$F$6:$F$163,"n.a.",0)),_xlfn.XLOOKUP("visa|"&C$8&"|operating_expenses",'Actuals'!$K$6:$K$163,'Actuals'!$G$6:$G$163,"n.a.",0)="USD"),_xlfn.XLOOKUP("visa|"&C$8&"|operating_expenses",'Actuals'!$K$6:$K$163,'Actuals'!$F$6:$F$163,"n.a.",0)/1000000,"n.a."),"n.a.") -> 8301 | D13: =IF(COUNTIFS('Actuals'!$K$6:$K$163,"visa|"&D$8&"|operating_expenses")=1,IF(AND(COUNTIFS('Actuals'!$K$6:$K$163,"visa|"&D$8&"|operating_expenses",'Actuals'!$F$6:$F$163,"<>")=1,ISNUMBER(_xlfn.XLOOKUP("visa|"&D$8&"|operating_expenses",'Actuals'!$K$6:$K$163,'Actuals'!$F$6:$F$163,"n.a.",0)),_xlfn.XLOOKUP("visa|"&D$8&"|operating_expenses",'Actuals'!$K$6:$K$163,'Actuals'!$G$6:$G$163,"n.a.",0)="USD"),_xlfn.XLOOKUP("visa|"&D$8&"|operating_expenses",'Actuals'!$K$6:$K$163,'Actuals'!$F$6:$F$163,"n.a.",0)/1000000,"n.a."),"n.a.") -> 10497 | E13: =IF(COUNTIFS('Actuals'!$K$6:$K$163,"visa|"&E$8&"|operating_expenses")=1,IF(AND(COUNTIFS('Actuals'!$K$6:$K$163,"visa|"&E$8&"|operating_expenses",'Actuals'!$F$6:$F$163,"<>")=1,ISNUMBER(_xlfn.XLOOKUP("visa|"&E$8&"|operating_expenses",'Actuals'!$K$6:$K$163,'Actuals'!$F$6:$F$163,"n.a.",0)),_xlfn.XLOOKUP("visa|"&E$8&"|operating_expenses",'Actuals'!$K$6:$K$163,'Actuals'!$G$6:$G$163,"n.a.",0)="USD"),_xlfn.XLOOKUP("visa|"&E$8&"|operating_expenses",'Actuals'!$K$6:$K$163,'Actuals'!$F$6:$F$163,"n.a.",0)/1000000,"n.a."),"n.a.") -> 11653 | F13: =IF(COUNTIFS('Actuals'!$K$6:$K$163,"visa|"&F$8&"|operating_expenses")=1,IF(AND(COUNTIFS('Actuals'!$K$6:$K$163,"visa|"&F$8&"|operating_expenses",'Actuals'!$F$6:$F$163,"<>")=1,ISNUMBER(_xlfn.XLOOKUP("visa|"&F$8&"|operating_expenses",'Actuals'!$K$6:$K$163,'Actuals'!$F$6:$F$163,"n.a.",0)),_xlfn.XLOOKUP("visa|"&F$8&"|operating_expenses",'Actuals'!$K$6:$K$163,'Actuals'!$G$6:$G$163,"n.a.",0)="USD"),_xlfn.XLOOKUP("visa|"&F$8&"|operating_expenses",'Actuals'!$K$6:$K$163,'Actuals'!$F$6:$F$163,"n.a.",0)/1000000,"n.a."),"n.a.") -> 12331 | G13: =IF(COUNTIFS('Actuals'!$K$6:$K$163,"visa|"&G$8&"|operating_expenses")=1,IF(AND(COUNTIFS('Actuals'!$K$6:$K$163,"visa|"&G$8&"|operating_expenses",'Actuals'!$F$6:$F$163,"<>")=1,ISNUMBER(_xlfn.XLOOKUP("visa|"&G$8&"|operating_expenses",'Actuals'!$K$6:$K$163,'Actuals'!$F$6:$F$163,"n.a.",0)),_xlfn.XLOOKUP("visa|"&G$8&"|operating_expenses",'Actuals'!$K$6:$K$163,'Actuals'!$G$6:$G$163,"n.a.",0)="USD"),_xlfn.XLOOKUP("visa|"&G$8&"|operating_expenses",'Actuals'!$K$6:$K$163,'Actuals'!$F$6:$F$163,"n.a.",0)/1000000,"n.a."),"n.a.") -> 16006
B14: Reported operating income | C14: =IF(COUNTIFS('Actuals'!$K$6:$K$163,"visa|"&C$8&"|operating_income")=1,IF(AND(COUNTIFS('Actuals'!$K$6:$K$163,"visa|"&C$8&"|operating_income",'Actuals'!$F$6:$F$163,"<>")=1,ISNUMBER(_xlfn.XLOOKUP("visa|"&C$8&"|operating_income",'Actuals'!$K$6:$K$163,'Actuals'!$F$6:$F$163,"n.a.",0)),_xlfn.XLOOKUP("visa|"&C$8&"|operating_income",'Actuals'!$K$6:$K$163,'Actuals'!$G$6:$G$163,"n.a.",0)="USD"),_xlfn.XLOOKUP("visa|"&C$8&"|operating_income",'Actuals'!$K$6:$K$163,'Actuals'!$F$6:$F$163,"n.a.",0)/1000000,"n.a."),"n.a.") -> 15804 | D14: =IF(COUNTIFS('Actuals'!$K$6:$K$163,"visa|"&D$8&"|operating_income")=1,IF(AND(COUNTIFS('Actuals'!$K$6:$K$163,"visa|"&D$8&"|operating_income",'Actuals'!$F$6:$F$163,"<>")=1,ISNUMBER(_xlfn.XLOOKUP("visa|"&D$8&"|operating_income",'Actuals'!$K$6:$K$163,'Actuals'!$F$6:$F$163,"n.a.",0)),_xlfn.XLOOKUP("visa|"&D$8&"|operating_income",'Actuals'!$K$6:$K$163,'Actuals'!$G$6:$G$163,"n.a.",0)="USD"),_xlfn.XLOOKUP("visa|"&D$8&"|operating_income",'Actuals'!$K$6:$K$163,'Actuals'!$F$6:$F$163,"n.a.",0)/1000000,"n.a."),"n.a.") -> 18813 | E14: =IF(COUNTIFS('Actuals'!$K$6:$K$163,"visa|"&E$8&"|operating_income")=1,IF(AND(COUNTIFS('Actuals'!$K$6:$K$163,"visa|"&E$8&"|operating_income",'Actuals'!$F$6:$F$163,"<>")=1,ISNUMBER(_xlfn.XLOOKUP("visa|"&E$8&"|operating_income",'Actuals'!$K$6:$K$163,'Actuals'!$F$6:$F$163,"n.a.",0)),_xlfn.XLOOKUP("visa|"&E$8&"|operating_income",'Actuals'!$K$6:$K$163,'Actuals'!$G$6:$G$163,"n.a.",0)="USD"),_xlfn.XLOOKUP("visa|"&E$8&"|operating_income",'Actuals'!$K$6:$K$163,'Actuals'!$F$6:$F$163,"n.a.",0)/1000000,"n.a."),"n.a.") -> 21000 | F14: =IF(COUNTIFS('Actuals'!$K$6:$K$163,"visa|"&F$8&"|operating_income")=1,IF(AND(COUNTIFS('Actuals'!$K$6:$K$163,"visa|"&F$8&"|operating_income",'Actuals'!$F$6:$F$163,"<>")=1,ISNUMBER(_xlfn.XLOOKUP("visa|"&F$8&"|operating_income",'Actuals'!$K$6:$K$163,'Actuals'!$F$6:$F$163,"n.a.",0)),_xlfn.XLOOKUP("visa|"&F$8&"|operating_income",'Actuals'!$K$6:$K$163,'Actuals'!$G$6:$G$163,"n.a.",0)="USD"),_xlfn.XLOOKUP("visa|"&F$8&"|operating_income",'Actuals'!$K$6:$K$163,'Actuals'!$F$6:$F$163,"n.a.",0)/1000000,"n.a."),"n.a.") -> 23595 | G14: =IF(COUNTIFS('Actuals'!$K$6:$K$163,"visa|"&G$8&"|operating_income")=1,IF(AND(COUNTIFS('Actuals'!$K$6:$K$163,"visa|"&G$8&"|operating_income",'Actuals'!$F$6:$F$163,"<>")=1,ISNUMBER(_xlfn.XLOOKUP("visa|"&G$8&"|operating_income",'Actuals'!$K$6:$K$163,'Actuals'!$F$6:$F$163,"n.a.",0)),_xlfn.XLOOKUP("visa|"&G$8&"|operating_income",'Actuals'!$K$6:$K$163,'Actuals'!$G$6:$G$163,"n.a.",0)="USD"),_xlfn.XLOOKUP("visa|"&G$8&"|operating_income",'Actuals'!$K$6:$K$163,'Actuals'!$F$6:$F$163,"n.a.",0)/1000000,"n.a."),"n.a.") -> 23994
B15: Reported consolidated net income | C15: =IF(COUNTIFS('Actuals'!$K$6:$K$163,"visa|"&C$8&"|net_income")=1,IF(AND(COUNTIFS('Actuals'!$K$6:$K$163,"visa|"&C$8&"|net_income",'Actuals'!$F$6:$F$163,"<>")=1,ISNUMBER(_xlfn.XLOOKUP("visa|"&C$8&"|net_income",'Actuals'!$K$6:$K$163,'Actuals'!$F$6:$F$163,"n.a.",0)),_xlfn.XLOOKUP("visa|"&C$8&"|net_income",'Actuals'!$K$6:$K$163,'Actuals'!$G$6:$G$163,"n.a.",0)="USD"),_xlfn.XLOOKUP("visa|"&C$8&"|net_income",'Actuals'!$K$6:$K$163,'Actuals'!$F$6:$F$163,"n.a.",0)/1000000,"n.a."),"n.a.") -> 12311 | D15: =IF(COUNTIFS('Actuals'!$K$6:$K$163,"visa|"&D$8&"|net_income")=1,IF(AND(COUNTIFS('Actuals'!$K$6:$K$163,"visa|"&D$8&"|net_income",'Actuals'!$F$6:$F$163,"<>")=1,ISNUMBER(_xlfn.XLOOKUP("visa|"&D$8&"|net_income",'Actuals'!$K$6:$K$163,'Actuals'!$F$6:$F$163,"n.a.",0)),_xlfn.XLOOKUP("visa|"&D$8&"|net_income",'Actuals'!$K$6:$K$163,'Actuals'!$G$6:$G$163,"n.a.",0)="USD"),_xlfn.XLOOKUP("visa|"&D$8&"|net_income",'Actuals'!$K$6:$K$163,'Actuals'!$F$6:$F$163,"n.a.",0)/1000000,"n.a."),"n.a.") -> 14957 | E15: =IF(COUNTIFS('Actuals'!$K$6:$K$163,"visa|"&E$8&"|net_income")=1,IF(AND(COUNTIFS('Actuals'!$K$6:$K$163,"visa|"&E$8&"|net_income",'Actuals'!$F$6:$F$163,"<>")=1,ISNUMBER(_xlfn.XLOOKUP("visa|"&E$8&"|net_income",'Actuals'!$K$6:$K$163,'Actuals'!$F$6:$F$163,"n.a.",0)),_xlfn.XLOOKUP("visa|"&E$8&"|net_income",'Actuals'!$K$6:$K$163,'Actuals'!$G$6:$G$163,"n.a.",0)="USD"),_xlfn.XLOOKUP("visa|"&E$8&"|net_income",'Actuals'!$K$6:$K$163,'Actuals'!$F$6:$F$163,"n.a.",0)/1000000,"n.a."),"n.a.") -> 17273 | F15: =IF(COUNTIFS('Actuals'!$K$6:$K$163,"visa|"&F$8&"|net_income")=1,IF(AND(COUNTIFS('Actuals'!$K$6:$K$163,"visa|"&F$8&"|net_income",'Actuals'!$F$6:$F$163,"<>")=1,ISNUMBER(_xlfn.XLOOKUP("visa|"&F$8&"|net_income",'Actuals'!$K$6:$K$163,'Actuals'!$F$6:$F$163,"n.a.",0)),_xlfn.XLOOKUP("visa|"&F$8&"|net_income",'Actuals'!$K$6:$K$163,'Actuals'!$G$6:$G$163,"n.a.",0)="USD"),_xlfn.XLOOKUP("visa|"&F$8&"|net_income",'Actuals'!$K$6:$K$163,'Actuals'!$F$6:$F$163,"n.a.",0)/1000000,"n.a."),"n.a.") -> 19743 | G15: =IF(COUNTIFS('Actuals'!$K$6:$K$163,"visa|"&G$8&"|net_income")=1,IF(AND(COUNTIFS('Actuals'!$K$6:$K$163,"visa|"&G$8&"|net_income",'Actuals'!$F$6:$F$163,"<>")=1,ISNUMBER(_xlfn.XLOOKUP("visa|"&G$8&"|net_income",'Actuals'!$K$6:$K$163,'Actuals'!$F$6:$F$163,"n.a.",0)),_xlfn.XLOOKUP("visa|"&G$8&"|net_income",'Actuals'!$K$6:$K$163,'Actuals'!$G$6:$G$163,"n.a.",0)="USD"),_xlfn.XLOOKUP("visa|"&G$8&"|net_income",'Actuals'!$K$6:$K$163,'Actuals'!$F$6:$F$163,"n.a.",0)/1000000,"n.a."),"n.a.") -> 20058
B16: Reported operating cash flow | C16: =IF(COUNTIFS('Actuals'!$K$6:$K$163,"visa|"&C$8&"|operating_cash_flow")=1,IF(AND(COUNTIFS('Actuals'!$K$6:$K$163,"visa|"&C$8&"|operating_cash_flow",'Actuals'!$F$6:$F$163,"<>")=1,ISNUMBER(_xlfn.XLOOKUP("visa|"&C$8&"|operating_cash_flow",'Actuals'!$K$6:$K$163,'Actuals'!$F$6:$F$163,"n.a.",0)),_xlfn.XLOOKUP("visa|"&C$8&"|operating_cash_flow",'Actuals'!$K$6:$K$163,'Actuals'!$G$6:$G$163,"n.a.",0)="USD"),_xlfn.XLOOKUP("visa|"&C$8&"|operating_cash_flow",'Actuals'!$K$6:$K$163,'Actuals'!$F$6:$F$163,"n.a.",0)/1000000,"n.a."),"n.a.") -> 15227 | D16: =IF(COUNTIFS('Actuals'!$K$6:$K$163,"visa|"&D$8&"|operating_cash_flow")=1,IF(AND(COUNTIFS('Actuals'!$K$6:$K$163,"visa|"&D$8&"|operating_cash_flow",'Actuals'!$F$6:$F$163,"<>")=1,ISNUMBER(_xlfn.XLOOKUP("visa|"&D$8&"|operating_cash_flow",'Actuals'!$K$6:$K$163,'Actuals'!$F$6:$F$163,"n.a.",0)),_xlfn.XLOOKUP("visa|"&D$8&"|operating_cash_flow",'Actuals'!$K$6:$K$163,'Actuals'!$G$6:$G$163,"n.a.",0)="USD"),_xlfn.XLOOKUP("visa|"&D$8&"|operating_cash_flow",'Actuals'!$K$6:$K$163,'Actuals'!$F$6:$F$163,"n.a.",0)/1000000,"n.a."),"n.a.") -> 18849 | E16: =IF(COUNTIFS('Actuals'!$K$6:$K$163,"visa|"&E$8&"|operating_cash_flow")=1,IF(AND(COUNTIFS('Actuals'!$K$6:$K$163,"visa|"&E$8&"|operating_cash_flow",'Actuals'!$F$6:$F$163,"<>")=1,ISNUMBER(_xlfn.XLOOKUP("visa|"&E$8&"|operating_cash_flow",'Actuals'!$K$6:$K$163,'Actuals'!$F$6:$F$163,"n.a.",0)),_xlfn.XLOOKUP("visa|"&E$8&"|operating_cash_flow",'Actuals'!$K$6:$K$163,'Actuals'!$G$6:$G$163,"n.a.",0)="USD"),_xlfn.XLOOKUP("visa|"&E$8&"|operating_cash_flow",'Actuals'!$K$6:$K$163,'Actuals'!$F$6:$F$163,"n.a.",0)/1000000,"n.a."),"n.a.") -> 20755 | F16: =IF(COUNTIFS('Actuals'!$K$6:$K$163,"visa|"&F$8&"|operating_cash_flow")=1,IF(AND(COUNTIFS('Actuals'!$K$6:$K$163,"visa|"&F$8&"|operating_cash_flow",'Actuals'!$F$6:$F$163,"<>")=1,ISNUMBER(_xlfn.XLOOKUP("visa|"&F$8&"|operating_cash_flow",'Actuals'!$K$6:$K$163,'Actuals'!$F$6:$F$163,"n.a.",0)),_xlfn.XLOOKUP("visa|"&F$8&"|operating_cash_flow",'Actuals'!$K$6:$K$163,'Actuals'!$G$6:$G$163,"n.a.",0)="USD"),_xlfn.XLOOKUP("visa|"&F$8&"|operating_cash_flow",'Actuals'!$K$6:$K$163,'Actuals'!$F$6:$F$163,"n.a.",0)/1000000,"n.a."),"n.a.") -> 19950 | G16: =IF(COUNTIFS('Actuals'!$K$6:$K$163,"visa|"&G$8&"|operating_cash_flow")=1,IF(AND(COUNTIFS('Actuals'!$K$6:$K$163,"visa|"&G$8&"|operating_cash_flow",'Actuals'!$F$6:$F$163,"<>")=1,ISNUMBER(_xlfn.XLOOKUP("visa|"&G$8&"|operating_cash_flow",'Actuals'!$K$6:$K$163,'Actuals'!$F$6:$F$163,"n.a.",0)),_xlfn.XLOOKUP("visa|"&G$8&"|operating_cash_flow",'Actuals'!$K$6:$K$163,'Actuals'!$G$6:$G$163,"n.a.",0)="USD"),_xlfn.XLOOKUP("visa|"&G$8&"|operating_cash_flow",'Actuals'!$K$6:$K$163,'Actuals'!$F$6:$F$163,"n.a.",0)/1000000,"n.a."),"n.a.") -> 23059
B17: Cash and cash equivalents | C17: =IF(COUNTIFS('Actuals'!$K$6:$K$163,"visa|"&C$8&"|cash_and_cash_equivalents")=1,IF(AND(COUNTIFS('Actuals'!$K$6:$K$163,"visa|"&C$8&"|cash_and_cash_equivalents",'Actuals'!$F$6:$F$163,"<>")=1,ISNUMBER(_xlfn.XLOOKUP("visa|"&C$8&"|cash_and_cash_equivalents",'Actuals'!$K$6:$K$163,'Actuals'!$F$6:$F$163,"n.a.",0)),_xlfn.XLOOKUP("visa|"&C$8&"|cash_and_cash_equivalents",'Actuals'!$K$6:$K$163,'Actuals'!$G$6:$G$163,"n.a.",0)="USD"),_xlfn.XLOOKUP("visa|"&C$8&"|cash_and_cash_equivalents",'Actuals'!$K$6:$K$163,'Actuals'!$F$6:$F$163,"n.a.",0)/1000000,"n.a."),"n.a.") -> 16487 | D17: =IF(COUNTIFS('Actuals'!$K$6:$K$163,"visa|"&D$8&"|cash_and_cash_equivalents")=1,IF(AND(COUNTIFS('Actuals'!$K$6:$K$163,"visa|"&D$8&"|cash_and_cash_equivalents",'Actuals'!$F$6:$F$163,"<>")=1,ISNUMBER(_xlfn.XLOOKUP("visa|"&D$8&"|cash_and_cash_equivalents",'Actuals'!$K$6:$K$163,'Actuals'!$F$6:$F$163,"n.a.",0)),_xlfn.XLOOKUP("visa|"&D$8&"|cash_and_cash_equivalents",'Actuals'!$K$6:$K$163,'Actuals'!$G$6:$G$163,"n.a.",0)="USD"),_xlfn.XLOOKUP("visa|"&D$8&"|cash_and_cash_equivalents",'Actuals'!$K$6:$K$163,'Actuals'!$F$6:$F$163,"n.a.",0)/1000000,"n.a."),"n.a.") -> 15689 | E17: =IF(COUNTIFS('Actuals'!$K$6:$K$163,"visa|"&E$8&"|cash_and_cash_equivalents")=1,IF(AND(COUNTIFS('Actuals'!$K$6:$K$163,"visa|"&E$8&"|cash_and_cash_equivalents",'Actuals'!$F$6:$F$163,"<>")=1,ISNUMBER(_xlfn.XLOOKUP("visa|"&E$8&"|cash_and_cash_equivalents",'Actuals'!$K$6:$K$163,'Actuals'!$F$6:$F$163,"n.a.",0)),_xlfn.XLOOKUP("visa|"&E$8&"|cash_and_cash_equivalents",'Actuals'!$K$6:$K$163,'Actuals'!$G$6:$G$163,"n.a.",0)="USD"),_xlfn.XLOOKUP("visa|"&E$8&"|cash_and_cash_equivalents",'Actuals'!$K$6:$K$163,'Actuals'!$F$6:$F$163,"n.a.",0)/1000000,"n.a."),"n.a.") -> 16286 | F17: =IF(COUNTIFS('Actuals'!$K$6:$K$163,"visa|"&F$8&"|cash_and_cash_equivalents")=1,IF(AND(COUNTIFS('Actuals'!$K$6:$K$163,"visa|"&F$8&"|cash_and_cash_equivalents",'Actuals'!$F$6:$F$163,"<>")=1,ISNUMBER(_xlfn.XLOOKUP("visa|"&F$8&"|cash_and_cash_equivalents",'Actuals'!$K$6:$K$163,'Actuals'!$F$6:$F$163,"n.a.",0)),_xlfn.XLOOKUP("visa|"&F$8&"|cash_and_cash_equivalents",'Actuals'!$K$6:$K$163,'Actuals'!$G$6:$G$163,"n.a.",0)="USD"),_xlfn.XLOOKUP("visa|"&F$8&"|cash_and_cash_equivalents",'Actuals'!$K$6:$K$163,'Actuals'!$F$6:$F$163,"n.a.",0)/1000000,"n.a."),"n.a.") -> 11975 | G17: =IF(COUNTIFS('Actuals'!$K$6:$K$163,"visa|"&G$8&"|cash_and_cash_equivalents")=1,IF(AND(COUNTIFS('Actuals'!$K$6:$K$163,"visa|"&G$8&"|cash_and_cash_equivalents",'Actuals'!$F$6:$F$163,"<>")=1,ISNUMBER(_xlfn.XLOOKUP("visa|"&G$8&"|cash_and_cash_equivalents",'Actuals'!$K$6:$K$163,'Actuals'!$F$6:$F$163,"n.a.",0)),_xlfn.XLOOKUP("visa|"&G$8&"|cash_and_cash_equivalents",'Actuals'!$K$6:$K$163,'Actuals'!$G$6:$G$163,"n.a.",0)="USD"),_xlfn.XLOOKUP("visa|"&G$8&"|cash_and_cash_equivalents",'Actuals'!$K$6:$K$163,'Actuals'!$F$6:$F$163,"n.a.",0)/1000000,"n.a."),"n.a.") -> 17164
B18: Current debt carrying amount | C18: =IF(COUNTIFS('Actuals'!$K$6:$K$163,"visa|"&C$8&"|current_debt")=1,IF(AND(COUNTIFS('Actuals'!$K$6:$K$163,"visa|"&C$8&"|current_debt",'Actuals'!$F$6:$F$163,"<>")=1,ISNUMBER(_xlfn.XLOOKUP("visa|"&C$8&"|current_debt",'Actuals'!$K$6:$K$163,'Actuals'!$F$6:$F$163,"n.a.",0)),_xlfn.XLOOKUP("visa|"&C$8&"|current_debt",'Actuals'!$K$6:$K$163,'Actuals'!$G$6:$G$163,"n.a.",0)="USD"),_xlfn.XLOOKUP("visa|"&C$8&"|current_debt",'Actuals'!$K$6:$K$163,'Actuals'!$F$6:$F$163,"n.a.",0)/1000000,"n.a."),"n.a.") -> 999 | D18: =IF(COUNTIFS('Actuals'!$K$6:$K$163,"visa|"&D$8&"|current_debt")=1,IF(AND(COUNTIFS('Actuals'!$K$6:$K$163,"visa|"&D$8&"|current_debt",'Actuals'!$F$6:$F$163,"<>")=1,ISNUMBER(_xlfn.XLOOKUP("visa|"&D$8&"|current_debt",'Actuals'!$K$6:$K$163,'Actuals'!$F$6:$F$163,"n.a.",0)),_xlfn.XLOOKUP("visa|"&D$8&"|current_debt",'Actuals'!$K$6:$K$163,'Actuals'!$G$6:$G$163,"n.a.",0)="USD"),_xlfn.XLOOKUP("visa|"&D$8&"|current_debt",'Actuals'!$K$6:$K$163,'Actuals'!$F$6:$F$163,"n.a.",0)/1000000,"n.a."),"n.a.") -> 2250 | E18: =IF(COUNTIFS('Actuals'!$K$6:$K$163,"visa|"&E$8&"|current_debt")=1,IF(AND(COUNTIFS('Actuals'!$K$6:$K$163,"visa|"&E$8&"|current_debt",'Actuals'!$F$6:$F$163,"<>")=1,ISNUMBER(_xlfn.XLOOKUP("visa|"&E$8&"|current_debt",'Actuals'!$K$6:$K$163,'Actuals'!$F$6:$F$163,"n.a.",0)),_xlfn.XLOOKUP("visa|"&E$8&"|current_debt",'Actuals'!$K$6:$K$163,'Actuals'!$G$6:$G$163,"n.a.",0)="USD"),_xlfn.XLOOKUP("visa|"&E$8&"|current_debt",'Actuals'!$K$6:$K$163,'Actuals'!$F$6:$F$163,"n.a.",0)/1000000,"n.a."),"n.a.") -> 0 | F18: =IF(COUNTIFS('Actuals'!$K$6:$K$163,"visa|"&F$8&"|current_debt")=1,IF(AND(COUNTIFS('Actuals'!$K$6:$K$163,"visa|"&F$8&"|current_debt",'Actuals'!$F$6:$F$163,"<>")=1,ISNUMBER(_xlfn.XLOOKUP("visa|"&F$8&"|current_debt",'Actuals'!$K$6:$K$163,'Actuals'!$F$6:$F$163,"n.a.",0)),_xlfn.XLOOKUP("visa|"&F$8&"|current_debt",'Actuals'!$K$6:$K$163,'Actuals'!$G$6:$G$163,"n.a.",0)="USD"),_xlfn.XLOOKUP("visa|"&F$8&"|current_debt",'Actuals'!$K$6:$K$163,'Actuals'!$F$6:$F$163,"n.a.",0)/1000000,"n.a."),"n.a.") -> 0 | G18: =IF(COUNTIFS('Actuals'!$K$6:$K$163,"visa|"&G$8&"|current_debt")=1,IF(AND(COUNTIFS('Actuals'!$K$6:$K$163,"visa|"&G$8&"|current_debt",'Actuals'!$F$6:$F$163,"<>")=1,ISNUMBER(_xlfn.XLOOKUP("visa|"&G$8&"|current_debt",'Actuals'!$K$6:$K$163,'Actuals'!$F$6:$F$163,"n.a.",0)),_xlfn.XLOOKUP("visa|"&G$8&"|current_debt",'Actuals'!$K$6:$K$163,'Actuals'!$G$6:$G$163,"n.a.",0)="USD"),_xlfn.XLOOKUP("visa|"&G$8&"|current_debt",'Actuals'!$K$6:$K$163,'Actuals'!$F$6:$F$163,"n.a.",0)/1000000,"n.a."),"n.a.") -> 5569
B19: Noncurrent debt carrying amount | C19: =IF(COUNTIFS('Actuals'!$K$6:$K$163,"visa|"&C$8&"|noncurrent_debt")=1,IF(AND(COUNTIFS('Actuals'!$K$6:$K$163,"visa|"&C$8&"|noncurrent_debt",'Actuals'!$F$6:$F$163,"<>")=1,ISNUMBER(_xlfn.XLOOKUP("visa|"&C$8&"|noncurrent_debt",'Actuals'!$K$6:$K$163,'Actuals'!$F$6:$F$163,"n.a.",0)),_xlfn.XLOOKUP("visa|"&C$8&"|noncurrent_debt",'Actuals'!$K$6:$K$163,'Actuals'!$G$6:$G$163,"n.a.",0)="USD"),_xlfn.XLOOKUP("visa|"&C$8&"|noncurrent_debt",'Actuals'!$K$6:$K$163,'Actuals'!$F$6:$F$163,"n.a.",0)/1000000,"n.a."),"n.a.") -> 19978 | D19: =IF(COUNTIFS('Actuals'!$K$6:$K$163,"visa|"&D$8&"|noncurrent_debt")=1,IF(AND(COUNTIFS('Actuals'!$K$6:$K$163,"visa|"&D$8&"|noncurrent_debt",'Actuals'!$F$6:$F$163,"<>")=1,ISNUMBER(_xlfn.XLOOKUP("visa|"&D$8&"|noncurrent_debt",'Actuals'!$K$6:$K$163,'Actuals'!$F$6:$F$163,"n.a.",0)),_xlfn.XLOOKUP("visa|"&D$8&"|noncurrent_debt",'Actuals'!$K$6:$K$163,'Actuals'!$G$6:$G$163,"n.a.",0)="USD"),_xlfn.XLOOKUP("visa|"&D$8&"|noncurrent_debt",'Actuals'!$K$6:$K$163,'Actuals'!$F$6:$F$163,"n.a.",0)/1000000,"n.a."),"n.a.") -> 20200 | E19: =IF(COUNTIFS('Actuals'!$K$6:$K$163,"visa|"&E$8&"|noncurrent_debt")=1,IF(AND(COUNTIFS('Actuals'!$K$6:$K$163,"visa|"&E$8&"|noncurrent_debt",'Actuals'!$F$6:$F$163,"<>")=1,ISNUMBER(_xlfn.XLOOKUP("visa|"&E$8&"|noncurrent_debt",'Actuals'!$K$6:$K$163,'Actuals'!$F$6:$F$163,"n.a.",0)),_xlfn.XLOOKUP("visa|"&E$8&"|noncurrent_debt",'Actuals'!$K$6:$K$163,'Actuals'!$G$6:$G$163,"n.a.",0)="USD"),_xlfn.XLOOKUP("visa|"&E$8&"|noncurrent_debt",'Actuals'!$K$6:$K$163,'Actuals'!$F$6:$F$163,"n.a.",0)/1000000,"n.a."),"n.a.") -> 20463 | F19: =IF(COUNTIFS('Actuals'!$K$6:$K$163,"visa|"&F$8&"|noncurrent_debt")=1,IF(AND(COUNTIFS('Actuals'!$K$6:$K$163,"visa|"&F$8&"|noncurrent_debt",'Actuals'!$F$6:$F$163,"<>")=1,ISNUMBER(_xlfn.XLOOKUP("visa|"&F$8&"|noncurrent_debt",'Actuals'!$K$6:$K$163,'Actuals'!$F$6:$F$163,"n.a.",0)),_xlfn.XLOOKUP("visa|"&F$8&"|noncurrent_debt",'Actuals'!$K$6:$K$163,'Actuals'!$G$6:$G$163,"n.a.",0)="USD"),_xlfn.XLOOKUP("visa|"&F$8&"|noncurrent_debt",'Actuals'!$K$6:$K$163,'Actuals'!$F$6:$F$163,"n.a.",0)/1000000,"n.a."),"n.a.") -> 20836 | G19: =IF(COUNTIFS('Actuals'!$K$6:$K$163,"visa|"&G$8&"|noncurrent_debt")=1,IF(AND(COUNTIFS('Actuals'!$K$6:$K$163,"visa|"&G$8&"|noncurrent_debt",'Actuals'!$F$6:$F$163,"<>")=1,ISNUMBER(_xlfn.XLOOKUP("visa|"&G$8&"|noncurrent_debt",'Actuals'!$K$6:$K$163,'Actuals'!$F$6:$F$163,"n.a.",0)),_xlfn.XLOOKUP("visa|"&G$8&"|noncurrent_debt",'Actuals'!$K$6:$K$163,'Actuals'!$G$6:$G$163,"n.a.",0)="USD"),_xlfn.XLOOKUP("visa|"&G$8&"|noncurrent_debt",'Actuals'!$K$6:$K$163,'Actuals'!$F$6:$F$163,"n.a.",0)/1000000,"n.a."),"n.a.") -> 19602
B20: Reported total assets | C20: =IF(COUNTIFS('Actuals'!$K$6:$K$163,"visa|"&C$8&"|total_assets")=1,IF(AND(COUNTIFS('Actuals'!$K$6:$K$163,"visa|"&C$8&"|total_assets",'Actuals'!$F$6:$F$163,"<>")=1,ISNUMBER(_xlfn.XLOOKUP("visa|"&C$8&"|total_assets",'Actuals'!$K$6:$K$163,'Actuals'!$F$6:$F$163,"n.a.",0)),_xlfn.XLOOKUP("visa|"&C$8&"|total_assets",'Actuals'!$K$6:$K$163,'Actuals'!$G$6:$G$163,"n.a.",0)="USD"),_xlfn.XLOOKUP("visa|"&C$8&"|total_assets",'Actuals'!$K$6:$K$163,'Actuals'!$F$6:$F$163,"n.a.",0)/1000000,"n.a."),"n.a.") -> 82896 | D20: =IF(COUNTIFS('Actuals'!$K$6:$K$163,"visa|"&D$8&"|total_assets")=1,IF(AND(COUNTIFS('Actuals'!$K$6:$K$163,"visa|"&D$8&"|total_assets",'Actuals'!$F$6:$F$163,"<>")=1,ISNUMBER(_xlfn.XLOOKUP("visa|"&D$8&"|total_assets",'Actuals'!$K$6:$K$163,'Actuals'!$F$6:$F$163,"n.a.",0)),_xlfn.XLOOKUP("visa|"&D$8&"|total_assets",'Actuals'!$K$6:$K$163,'Actuals'!$G$6:$G$163,"n.a.",0)="USD"),_xlfn.XLOOKUP("visa|"&D$8&"|total_assets",'Actuals'!$K$6:$K$163,'Actuals'!$F$6:$F$163,"n.a.",0)/1000000,"n.a."),"n.a.") -> 85501 | E20: =IF(COUNTIFS('Actuals'!$K$6:$K$163,"visa|"&E$8&"|total_assets")=1,IF(AND(COUNTIFS('Actuals'!$K$6:$K$163,"visa|"&E$8&"|total_assets",'Actuals'!$F$6:$F$163,"<>")=1,ISNUMBER(_xlfn.XLOOKUP("visa|"&E$8&"|total_assets",'Actuals'!$K$6:$K$163,'Actuals'!$F$6:$F$163,"n.a.",0)),_xlfn.XLOOKUP("visa|"&E$8&"|total_assets",'Actuals'!$K$6:$K$163,'Actuals'!$G$6:$G$163,"n.a.",0)="USD"),_xlfn.XLOOKUP("visa|"&E$8&"|total_assets",'Actuals'!$K$6:$K$163,'Actuals'!$F$6:$F$163,"n.a.",0)/1000000,"n.a."),"n.a.") -> 90499 | F20: =IF(COUNTIFS('Actuals'!$K$6:$K$163,"visa|"&F$8&"|total_assets")=1,IF(AND(COUNTIFS('Actuals'!$K$6:$K$163,"visa|"&F$8&"|total_assets",'Actuals'!$F$6:$F$163,"<>")=1,ISNUMBER(_xlfn.XLOOKUP("visa|"&F$8&"|total_assets",'Actuals'!$K$6:$K$163,'Actuals'!$F$6:$F$163,"n.a.",0)),_xlfn.XLOOKUP("visa|"&F$8&"|total_assets",'Actuals'!$K$6:$K$163,'Actuals'!$G$6:$G$163,"n.a.",0)="USD"),_xlfn.XLOOKUP("visa|"&F$8&"|total_assets",'Actuals'!$K$6:$K$163,'Actuals'!$F$6:$F$163,"n.a.",0)/1000000,"n.a."),"n.a.") -> 94511 | G20: =IF(COUNTIFS('Actuals'!$K$6:$K$163,"visa|"&G$8&"|total_assets")=1,IF(AND(COUNTIFS('Actuals'!$K$6:$K$163,"visa|"&G$8&"|total_assets",'Actuals'!$F$6:$F$163,"<>")=1,ISNUMBER(_xlfn.XLOOKUP("visa|"&G$8&"|total_assets",'Actuals'!$K$6:$K$163,'Actuals'!$F$6:$F$163,"n.a.",0)),_xlfn.XLOOKUP("visa|"&G$8&"|total_assets",'Actuals'!$K$6:$K$163,'Actuals'!$G$6:$G$163,"n.a.",0)="USD"),_xlfn.XLOOKUP("visa|"&G$8&"|total_assets",'Actuals'!$K$6:$K$163,'Actuals'!$F$6:$F$163,"n.a.",0)/1000000,"n.a."),"n.a.") -> 99627
B21: Reported total liabilities | C21: =IF(COUNTIFS('Actuals'!$K$6:$K$163,"visa|"&C$8&"|total_liabilities")=1,IF(AND(COUNTIFS('Actuals'!$K$6:$K$163,"visa|"&C$8&"|total_liabilities",'Actuals'!$F$6:$F$163,"<>")=1,ISNUMBER(_xlfn.XLOOKUP("visa|"&C$8&"|total_liabilities",'Actuals'!$K$6:$K$163,'Actuals'!$F$6:$F$163,"n.a.",0)),_xlfn.XLOOKUP("visa|"&C$8&"|total_liabilities",'Actuals'!$K$6:$K$163,'Actuals'!$G$6:$G$163,"n.a.",0)="USD"),_xlfn.XLOOKUP("visa|"&C$8&"|total_liabilities",'Actuals'!$K$6:$K$163,'Actuals'!$F$6:$F$163,"n.a.",0)/1000000,"n.a."),"n.a.") -> 45307 | D21: =IF(COUNTIFS('Actuals'!$K$6:$K$163,"visa|"&D$8&"|total_liabilities")=1,IF(AND(COUNTIFS('Actuals'!$K$6:$K$163,"visa|"&D$8&"|total_liabilities",'Actuals'!$F$6:$F$163,"<>")=1,ISNUMBER(_xlfn.XLOOKUP("visa|"&D$8&"|total_liabilities",'Actuals'!$K$6:$K$163,'Actuals'!$F$6:$F$163,"n.a.",0)),_xlfn.XLOOKUP("visa|"&D$8&"|total_liabilities",'Actuals'!$K$6:$K$163,'Actuals'!$G$6:$G$163,"n.a.",0)="USD"),_xlfn.XLOOKUP("visa|"&D$8&"|total_liabilities",'Actuals'!$K$6:$K$163,'Actuals'!$F$6:$F$163,"n.a.",0)/1000000,"n.a."),"n.a.") -> 49920 | E21: =IF(COUNTIFS('Actuals'!$K$6:$K$163,"visa|"&E$8&"|total_liabilities")=1,IF(AND(COUNTIFS('Actuals'!$K$6:$K$163,"visa|"&E$8&"|total_liabilities",'Actuals'!$F$6:$F$163,"<>")=1,ISNUMBER(_xlfn.XLOOKUP("visa|"&E$8&"|total_liabilities",'Actuals'!$K$6:$K$163,'Actuals'!$F$6:$F$163,"n.a.",0)),_xlfn.XLOOKUP("visa|"&E$8&"|total_liabilities",'Actuals'!$K$6:$K$163,'Actuals'!$G$6:$G$163,"n.a.",0)="USD"),_xlfn.XLOOKUP("visa|"&E$8&"|total_liabilities",'Actuals'!$K$6:$K$163,'Actuals'!$F$6:$F$163,"n.a.",0)/1000000,"n.a."),"n.a.") -> 51766 | F21: =IF(COUNTIFS('Actuals'!$K$6:$K$163,"visa|"&F$8&"|total_liabilities")=1,IF(AND(COUNTIFS('Actuals'!$K$6:$K$163,"visa|"&F$8&"|total_liabilities",'Actuals'!$F$6:$F$163,"<>")=1,ISNUMBER(_xlfn.XLOOKUP("visa|"&F$8&"|total_liabilities",'Actuals'!$K$6:$K$163,'Actuals'!$F$6:$F$163,"n.a.",0)),_xlfn.XLOOKUP("visa|"&F$8&"|total_liabilities",'Actuals'!$K$6:$K$163,'Actuals'!$G$6:$G$163,"n.a.",0)="USD"),_xlfn.XLOOKUP("visa|"&F$8&"|total_liabilities",'Actuals'!$K$6:$K$163,'Actuals'!$F$6:$F$163,"n.a.",0)/1000000,"n.a."),"n.a.") -> 55374 | G21: =IF(COUNTIFS('Actuals'!$K$6:$K$163,"visa|"&G$8&"|total_liabilities")=1,IF(AND(COUNTIFS('Actuals'!$K$6:$K$163,"visa|"&G$8&"|total_liabilities",'Actuals'!$F$6:$F$163,"<>")=1,ISNUMBER(_xlfn.XLOOKUP("visa|"&G$8&"|total_liabilities",'Actuals'!$K$6:$K$163,'Actuals'!$F$6:$F$163,"n.a.",0)),_xlfn.XLOOKUP("visa|"&G$8&"|total_liabilities",'Actuals'!$K$6:$K$163,'Actuals'!$G$6:$G$163,"n.a.",0)="USD"),_xlfn.XLOOKUP("visa|"&G$8&"|total_liabilities",'Actuals'!$K$6:$K$163,'Actuals'!$F$6:$F$163,"n.a.",0)/1000000,"n.a."),"n.a.") -> 61718
B22: Reported net revenue YoY growth | C22: ="n.a." -> n.a. | D22: =IF(AND(ISNUMBER(D12),ISNUMBER(C12),C12>0),D12/C12-1,"n.a.") -> 0.2159303 | E22: =IF(AND(ISNUMBER(E12),ISNUMBER(D12),D12>0),E12/D12-1,"n.a.") -> 0.11405664 | F22: =IF(AND(ISNUMBER(F12),ISNUMBER(E12),E12>0),F12/E12-1,"n.a.") -> 0.10023581 | G22: =IF(AND(ISNUMBER(G12),ISNUMBER(F12),F12>0),G12/F12-1,"n.a.") -> 0.11339977
B23: Reported operating income YoY growth | C23: ="n.a." -> n.a. | D23: =IF(AND(ISNUMBER(D14),ISNUMBER(C14),C14>0),D14/C14-1,"n.a.") -> 0.19039484 | E23: =IF(AND(ISNUMBER(E14),ISNUMBER(D14),D14>0),E14/D14-1,"n.a.") -> 0.1162494 | F23: =IF(AND(ISNUMBER(F14),ISNUMBER(E14),E14>0),F14/E14-1,"n.a.") -> 0.12357143 | G23: =IF(AND(ISNUMBER(G14),ISNUMBER(F14),F14>0),G14/F14-1,"n.a.") -> 0.016910362
B24: Operating margin | C24: =IF(AND(ISNUMBER(C14),ISNUMBER(C12),C12>0),C14/C12,"n.a.") -> 0.65563161 | D24: =IF(AND(ISNUMBER(D14),ISNUMBER(D12),D12>0),D14/D12,"n.a.") -> 0.64186285 | E24: =IF(AND(ISNUMBER(E14),ISNUMBER(E12),E12>0),E14/E12,"n.a.") -> 0.64312621 | F24: =IF(AND(ISNUMBER(F14),ISNUMBER(F12),F12>0),F14/F12,"n.a.") -> 0.65676669 | G24: =IF(AND(ISNUMBER(G14),ISNUMBER(G12),G12>0),G14/G12,"n.a.") -> 0.59985
B25: Consolidated net margin | C25: =IF(AND(ISNUMBER(C15),ISNUMBER(C12),C12>0),C15/C12,"n.a.") -> 0.51072392 | D25: =IF(AND(ISNUMBER(D15),ISNUMBER(D12),D12>0),D15/D12,"n.a.") -> 0.51030365 | E25: =IF(AND(ISNUMBER(E15),ISNUMBER(E12),E12>0),E15/E12,"n.a.") -> 0.52898662 | F25: =IF(AND(ISNUMBER(F15),ISNUMBER(F12),F12>0),F15/F12,"n.a.") -> 0.54954629 | G25: =IF(AND(ISNUMBER(G15),ISNUMBER(G12),G12>0),G15/G12,"n.a.") -> 0.50145
B26: Operating expense ratio | C26: =IF(AND(ISNUMBER(C13),ISNUMBER(C12),C12>0),C13/C12,"n.a.") -> 0.34436839 | D26: =IF(AND(ISNUMBER(D13),ISNUMBER(D12),D12>0),D13/D12,"n.a.") -> 0.35813715 | E26: =IF(AND(ISNUMBER(E13),ISNUMBER(E12),E12>0),E13/E12,"n.a.") -> 0.35687379 | F26: =IF(AND(ISNUMBER(F13),ISNUMBER(F12),F12>0),F13/F12,"n.a.") -> 0.34323331 | G26: =IF(AND(ISNUMBER(G13),ISNUMBER(G12),G12>0),G13/G12,"n.a.") -> 0.40015
B27: OCF / consolidated net income | C27: =IF(AND(ISNUMBER(C16),ISNUMBER(C15),C15>0),C16/C15,"n.a.") -> 1.2368613 | D27: =IF(AND(ISNUMBER(D16),ISNUMBER(D15),D15>0),D16/D15,"n.a.") -> 1.2602126 | E27: =IF(AND(ISNUMBER(E16),ISNUMBER(E15),E15>0),E16/E15,"n.a.") -> 1.2015863 | F27: =IF(AND(ISNUMBER(F16),ISNUMBER(F15),F15>0),F16/F15,"n.a.") -> 1.0104847 | G27: =IF(AND(ISNUMBER(G16),ISNUMBER(G15),G15>0),G16/G15,"n.a.") -> 1.1496161
B28: Operating margin YoY change | C28: ="n.a." -> n.a. | D28: =IF(AND(ISNUMBER(D24),ISNUMBER(C24)),(D24-C24)*100,"n.a.") -> -1.3768766 | E28: =IF(AND(ISNUMBER(E24),ISNUMBER(D24)),(E24-D24)*100,"n.a.") -> 0.12633604 | F28: =IF(AND(ISNUMBER(F24),ISNUMBER(E24)),(F24-E24)*100,"n.a.") -> 1.3640481 | G28: =IF(AND(ISNUMBER(G24),ISNUMBER(F24)),(G24-F24)*100,"n.a.") -> -5.6916687
B29: Defined capital cash payments | C29: =IF(AND(ISNUMBER(IF(COUNTIFS('Actuals'!$K$6:$K$163,"visa|"&C$8&"|capital_payments_primary")=1,IF(AND(COUNTIFS('Actuals'!$K$6:$K$163,"visa|"&C$8&"|capital_payments_primary",'Actuals'!$F$6:$F$163,"<>")=1,ISNUMBER(_xlfn.XLOOKUP("visa|"&C$8&"|capital_payments_primary",'Actuals'!$K$6:$K$163,'Actuals'!$F$6:$F$163,"n.a.",0)),_xlfn.XLOOKUP("visa|"&C$8&"|capital_payments_primary",'Actuals'!$K$6:$K$163,'Actuals'!$G$6:$G$163,"n.a.",0)="USD"),_xlfn.XLOOKUP("visa|"&C$8&"|capital_payments_primary",'Actuals'!$K$6:$K$163,'Actuals'!$F$6:$F$163,"n.a.",0)/1000000,"n.a."),"n.a."))),SUM(IF(COUNTIFS('Actuals'!$K$6:$K$163,"visa|"&C$8&"|capital_payments_primary")=1,IF(AND(COUNTIFS('Actuals'!$K$6:$K$163,"visa|"&C$8&"|capital_payments_primary",'Actuals'!$F$6:$F$163,"<>")=1,ISNUMBER(_xlfn.XLOOKUP("visa|"&C$8&"|capital_payments_primary",'Actuals'!$K$6:$K$163,'Actuals'!$F$6:$F$163,"n.a.",0)),_xlfn.XLOOKUP("visa|"&C$8&"|capital_payments_primary",'Actuals'!$K$6:$K$163,'Actuals'!$G$6:$G$163,"n.a.",0)="USD"),_xlfn.XLOOKUP("visa|"&C$8&"|capital_payments_primary",'Actuals'!$K$6:$K$163,'Actuals'!$F$6:$F$163,"n.a.",0)/1000000,"n.a."),"n.a.")),"n.a.") -> 705 | D29: =IF(AND(ISNUMBER(IF(COUNTIFS('Actuals'!$K$6:$K$163,"visa|"&D$8&"|capital_payments_primary")=1,IF(AND(COUNTIFS('Actuals'!$K$6:$K$163,"visa|"&D$8&"|capital_payments_primary",'Actuals'!$F$6:$F$163,"<>")=1,ISNUMBER(_xlfn.XLOOKUP("visa|"&D$8&"|capital_payments_primary",'Actuals'!$K$6:$K$163,'Actuals'!$F$6:$F$163,"n.a.",0)),_xlfn.XLOOKUP("visa|"&D$8&"|capital_payments_primary",'Actuals'!$K$6:$K$163,'Actuals'!$G$6:$G$163,"n.a.",0)="USD"),_xlfn.XLOOKUP("visa|"&D$8&"|capital_payments_primary",'Actuals'!$K$6:$K$163,'Actuals'!$F$6:$F$163,"n.a.",0)/1000000,"n.a."),"n.a."))),SUM(IF(COUNTIFS('Actuals'!$K$6:$K$163,"visa|"&D$8&"|capital_payments_primary")=1,IF(AND(COUNTIFS('Actuals'!$K$6:$K$163,"visa|"&D$8&"|capital_payments_primary",'Actuals'!$F$6:$F$163,"<>")=1,ISNUMBER(_xlfn.XLOOKUP("visa|"&D$8&"|capital_payments_primary",'Actuals'!$K$6:$K$163,'Actuals'!$F$6:$F$163,"n.a.",0)),_xlfn.XLOOKUP("visa|"&D$8&"|capital_payments_primary",'Actuals'!$K$6:$K$163,'Actuals'!$G$6:$G$163,"n.a.",0)="USD"),_xlfn.XLOOKUP("visa|"&D$8&"|capital_payments_primary",'Actuals'!$K$6:$K$163,'Actuals'!$F$6:$F$163,"n.a.",0)/1000000,"n.a."),"n.a.")),"n.a.") -> 970 | E29: =IF(AND(ISNUMBER(IF(COUNTIFS('Actuals'!$K$6:$K$163,"visa|"&E$8&"|capital_payments_primary")=1,IF(AND(COUNTIFS('Actuals'!$K$6:$K$163,"visa|"&E$8&"|capital_payments_primary",'Actuals'!$F$6:$F$163,"<>")=1,ISNUMBER(_xlfn.XLOOKUP("visa|"&E$8&"|capital_payments_primary",'Actuals'!$K$6:$K$163,'Actuals'!$F$6:$F$163,"n.a.",0)),_xlfn.XLOOKUP("visa|"&E$8&"|capital_payments_primary",'Actuals'!$K$6:$K$163,'Actuals'!$G$6:$G$163,"n.a.",0)="USD"),_xlfn.XLOOKUP("visa|"&E$8&"|capital_payments_primary",'Actuals'!$K$6:$K$163,'Actuals'!$F$6:$F$163,"n.a.",0)/1000000,"n.a."),"n.a."))),SUM(IF(COUNTIFS('Actuals'!$K$6:$K$163,"visa|"&E$8&"|capital_payments_primary")=1,IF(AND(COUNTIFS('Actuals'!$K$6:$K$163,"visa|"&E$8&"|capital_payments_primary",'Actuals'!$F$6:$F$163,"<>")=1,ISNUMBER(_xlfn.XLOOKUP("visa|"&E$8&"|capital_payments_primary",'Actuals'!$K$6:$K$163,'Actuals'!$F$6:$F$163,"n.a.",0)),_xlfn.XLOOKUP("visa|"&E$8&"|capital_payments_primary",'Actuals'!$K$6:$K$163,'Actuals'!$G$6:$G$163,"n.a.",0)="USD"),_xlfn.XLOOKUP("visa|"&E$8&"|capital_payments_primary",'Actuals'!$K$6:$K$163,'Actuals'!$F$6:$F$163,"n.a.",0)/1000000,"n.a."),"n.a.")),"n.a.") -> 1059 | F29: =IF(AND(ISNUMBER(IF(COUNTIFS('Actuals'!$K$6:$K$163,"visa|"&F$8&"|capital_payments_primary")=1,IF(AND(COUNTIFS('Actuals'!$K$6:$K$163,"visa|"&F$8&"|capital_payments_primary",'Actuals'!$F$6:$F$163,"<>")=1,ISNUMBER(_xlfn.XLOOKUP("visa|"&F$8&"|capital_payments_primary",'Actuals'!$K$6:$K$163,'Actuals'!$F$6:$F$163,"n.a.",0)),_xlfn.XLOOKUP("visa|"&F$8&"|capital_payments_primary",'Actuals'!$K$6:$K$163,'Actuals'!$G$6:$G$163,"n.a.",0)="USD"),_xlfn.XLOOKUP("visa|"&F$8&"|capital_payments_primary",'Actuals'!$K$6:$K$163,'Actuals'!$F$6:$F$163,"n.a.",0)/1000000,"n.a."),"n.a."))),SUM(IF(COUNTIFS('Actuals'!$K$6:$K$163,"visa|"&F$8&"|capital_payments_primary")=1,IF(AND(COUNTIFS('Actuals'!$K$6:$K$163,"visa|"&F$8&"|capital_payments_primary",'Actuals'!$F$6:$F$163,"<>")=1,ISNUMBER(_xlfn.XLOOKUP("visa|"&F$8&"|capital_payments_primary",'Actuals'!$K$6:$K$163,'Actuals'!$F$6:$F$163,"n.a.",0)),_xlfn.XLOOKUP("visa|"&F$8&"|capital_payments_primary",'Actuals'!$K$6:$K$163,'Actuals'!$G$6:$G$163,"n.a.",0)="USD"),_xlfn.XLOOKUP("visa|"&F$8&"|capital_payments_primary",'Actuals'!$K$6:$K$163,'Actuals'!$F$6:$F$163,"n.a.",0)/1000000,"n.a."),"n.a.")),"n.a.") -> 1257 | G29: =IF(AND(ISNUMBER(IF(COUNTIFS('Actuals'!$K$6:$K$163,"visa|"&G$8&"|capital_payments_primary")=1,IF(AND(COUNTIFS('Actuals'!$K$6:$K$163,"visa|"&G$8&"|capital_payments_primary",'Actuals'!$F$6:$F$163,"<>")=1,ISNUMBER(_xlfn.XLOOKUP("visa|"&G$8&"|capital_payments_primary",'Actuals'!$K$6:$K$163,'Actuals'!$F$6:$F$163,"n.a.",0)),_xlfn.XLOOKUP("visa|"&G$8&"|capital_payments_primary",'Actuals'!$K$6:$K$163,'Actuals'!$G$6:$G$163,"n.a.",0)="USD"),_xlfn.XLOOKUP("visa|"&G$8&"|capital_payments_primary",'Actuals'!$K$6:$K$163,'Actuals'!$F$6:$F$163,"n.a.",0)/1000000,"n.a."),"n.a."))),SUM(IF(COUNTIFS('Actuals'!$K$6:$K$163,"visa|"&G$8&"|capital_payments_primary")=1,IF(AND(COUNTIFS('Actuals'!$K$6:$K$163,"visa|"&G$8&"|capital_payments_primary",'Actuals'!$F$6:$F$163,"<>")=1,ISNUMBER(_xlfn.XLOOKUP("visa|"&G$8&"|capital_payments_primary",'Actuals'!$K$6:$K$163,'Actuals'!$F$6:$F$163,"n.a.",0)),_xlfn.XLOOKUP("visa|"&G$8&"|capital_payments_primary",'Actuals'!$K$6:$K$163,'Actuals'!$G$6:$G$163,"n.a.",0)="USD"),_xlfn.XLOOKUP("visa|"&G$8&"|capital_payments_primary",'Actuals'!$K$6:$K$163,'Actuals'!$F$6:$F$163,"n.a.",0)/1000000,"n.a."),"n.a.")),"n.a.") -> 1482
B30: OCF less defined capital payments | C30: =IF(AND(ISNUMBER(C16),ISNUMBER(C29)),C16-C29,"n.a.") -> 14522 | D30: =IF(AND(ISNUMBER(D16),ISNUMBER(D29)),D16-D29,"n.a.") -> 17879 | E30: =IF(AND(ISNUMBER(E16),ISNUMBER(E29)),E16-E29,"n.a.") -> 19696 | F30: =IF(AND(ISNUMBER(F16),ISNUMBER(F29)),F16-F29,"n.a.") -> 18693 | G30: =IF(AND(ISNUMBER(G16),ISNUMBER(G29)),G16-G29,"n.a.") -> 21577
B31: FCF proxy / net revenue | C31: =IF(AND(ISNUMBER(C30),ISNUMBER(C12),C12>0),C30/C12,"n.a.") -> 0.60244762 | D31: =IF(AND(ISNUMBER(D30),ISNUMBER(D12),D12>0),D30/D12,"n.a.") -> 0.60999659 | E31: =IF(AND(ISNUMBER(E30),ISNUMBER(E12),E12>0),E30/E12,"n.a.") -> 0.60319113 | F31: =IF(AND(ISNUMBER(F30),ISNUMBER(F12),F12>0),F30/F12,"n.a.") -> 0.52031955 | G31: =IF(AND(ISNUMBER(G30),ISNUMBER(G12),G12>0),G30/G12,"n.a.") -> 0.539425
B32: Selected debt carrying total | C32: =IF(AND(ISNUMBER(C18),ISNUMBER(C19)),SUM(C18,C19),"n.a.") -> 20977 | D32: =IF(AND(ISNUMBER(D18),ISNUMBER(D19)),SUM(D18,D19),"n.a.") -> 22450 | E32: =IF(AND(ISNUMBER(E18),ISNUMBER(E19)),SUM(E18,E19),"n.a.") -> 20463 | F32: =IF(AND(ISNUMBER(F18),ISNUMBER(F19)),SUM(F18,F19),"n.a.") -> 20836 | G32: =IF(AND(ISNUMBER(G18),ISNUMBER(G19)),SUM(G18,G19),"n.a.") -> 25171
B33: Selected debt less cash proxy | C33: =IF(AND(ISNUMBER(C32),ISNUMBER(C17)),C32-C17,"n.a.") -> 4490 | D33: =IF(AND(ISNUMBER(D32),ISNUMBER(D17)),D32-D17,"n.a.") -> 6761 | E33: =IF(AND(ISNUMBER(E32),ISNUMBER(E17)),E32-E17,"n.a.") -> 4177 | F33: =IF(AND(ISNUMBER(F32),ISNUMBER(F17)),F32-F17,"n.a.") -> 8861 | G33: =IF(AND(ISNUMBER(G32),ISNUMBER(G17)),G32-G17,"n.a.") -> 8007
B34: Selected debt / total assets | C34: =IF(AND(ISNUMBER(C32),ISNUMBER(C20),C20>0),C32/C20,"n.a.") -> 0.25305202 | D34: =IF(AND(ISNUMBER(D32),ISNUMBER(D20),D20>0),D32/D20,"n.a.") -> 0.26257003 | E34: =IF(AND(ISNUMBER(E32),ISNUMBER(E20),E20>0),E32/E20,"n.a.") -> 0.226113 | F34: =IF(AND(ISNUMBER(F32),ISNUMBER(F20),F20>0),F32/F20,"n.a.") -> 0.22046111 | G34: =IF(AND(ISNUMBER(G32),ISNUMBER(G20),G20>0),G32/G20,"n.a.") -> 0.25265239
B35: Total liabilities / total assets | C35: =IF(AND(ISNUMBER(C21),ISNUMBER(C20),C20>0),C21/C20,"n.a.") -> 0.54655231 | D35: =IF(AND(ISNUMBER(D21),ISNUMBER(D20),D20>0),D21/D20,"n.a.") -> 0.58385282 | E35: =IF(AND(ISNUMBER(E21),ISNUMBER(E20),E20>0),E21/E20,"n.a.") -> 0.57200632 | F35: =IF(AND(ISNUMBER(F21),ISNUMBER(F20),F20>0),F21/F20,"n.a.") -> 0.58590005 | G35: =IF(AND(ISNUMBER(G21),ISNUMBER(G20),G20>0),G21/G20,"n.a.") -> 0.6194907
B36: Cash equivalents / selected debt | C36: =IF(AND(ISNUMBER(C17),ISNUMBER(C32),C32>0),C17/C32,"n.a.") -> 0.78595605 | D36: =IF(AND(ISNUMBER(D17),ISNUMBER(D32),D32>0),D17/D32,"n.a.") -> 0.69884187 | E36: =IF(AND(ISNUMBER(E17),ISNUMBER(E32),E32>0),E17/E32,"n.a.") -> 0.79587548 | F36: =IF(AND(ISNUMBER(F17),ISNUMBER(F32),F32>0),F17/F32,"n.a.") -> 0.57472644 | G36: =IF(AND(ISNUMBER(G17),ISNUMBER(G32),G32>0),G17/G32,"n.a.") -> 0.68189583
B38: First-year changes are n.a.: no verified FY2020 input.
B40: Visa year end Sep30; Mastercard Dec31. No calendar adjustment.
B45: Mastercard reported fiscal years
B46: Fiscal year | C46: 2021 | D46: 2022 | E46: 2023 | F46: 2024 | G46: 2025
B47: Period start | C47: 2021-01-01T00:00:00.000Z | D47: 2022-01-01T00:00:00.000Z | E47: 2023-01-01T00:00:00.000Z | F47: 2024-01-01T00:00:00.000Z | G47: 2025-01-01T00:00:00.000Z
B48: Period end | C48: 2021-12-31T00:00:00.000Z | D48: 2022-12-31T00:00:00.000Z | E48: 2023-12-31T00:00:00.000Z | F48: 2024-12-31T00:00:00.000Z | G48: 2025-12-31T00:00:00.000Z
B50: Reported net revenue | C50: =IF(COUNTIFS('Actuals'!$K$6:$K$163,"mastercard|"&C$46&"|net_revenue")=1,IF(AND(COUNTIFS('Actuals'!$K$6:$K$163,"mastercard|"&C$46&"|net_revenue",'Actuals'!$F$6:$F$163,"<>")=1,ISNUMBER(_xlfn.XLOOKUP("mastercard|"&C$46&"|net_revenue",'Actuals'!$K$6:$K$163,'Actuals'!$F$6:$F$163,"n.a.",0)),_xlfn.XLOOKUP("mastercard|"&C$46&"|net_revenue",'Actuals'!$K$6:$K$163,'Actuals'!$G$6:$G$163,"n.a.",0)="USD"),_xlfn.XLOOKUP("mastercard|"&C$46&"|net_revenue",'Actuals'!$K$6:$K$163,'Actuals'!$F$6:$F$163,"n.a.",0)/1000000,"n.a."),"n.a.") -> 18884 | D50: =IF(COUNTIFS('Actuals'!$K$6:$K$163,"mastercard|"&D$46&"|net_revenue")=1,IF(AND(COUNTIFS('Actuals'!$K$6:$K$163,"mastercard|"&D$46&"|net_revenue",'Actuals'!$F$6:$F$163,"<>")=1,ISNUMBER(_xlfn.XLOOKUP("mastercard|"&D$46&"|net_revenue",'Actuals'!$K$6:$K$163,'Actuals'!$F$6:$F$163,"n.a.",0)),_xlfn.XLOOKUP("mastercard|"&D$46&"|net_revenue",'Actuals'!$K$6:$K$163,'Actuals'!$G$6:$G$163,"n.a.",0)="USD"),_xlfn.XLOOKUP("mastercard|"&D$46&"|net_revenue",'Actuals'!$K$6:$K$163,'Actuals'!$F$6:$F$163,"n.a.",0)/1000000,"n.a."),"n.a.") -> 22237 | E50: =IF(COUNTIFS('Actuals'!$K$6:$K$163,"mastercard|"&E$46&"|net_revenue")=1,IF(AND(COUNTIFS('Actuals'!$K$6:$K$163,"mastercard|"&E$46&"|net_revenue",'Actuals'!$F$6:$F$163,"<>")=1,ISNUMBER(_xlfn.XLOOKUP("mastercard|"&E$46&"|net_revenue",'Actuals'!$K$6:$K$163,'Actuals'!$F$6:$F$163,"n.a.",0)),_xlfn.XLOOKUP("mastercard|"&E$46&"|net_revenue",'Actuals'!$K$6:$K$163,'Actuals'!$G$6:$G$163,"n.a.",0)="USD"),_xlfn.XLOOKUP("mastercard|"&E$46&"|net_revenue",'Actuals'!$K$6:$K$163,'Actuals'!$F$6:$F$163,"n.a.",0)/1000000,"n.a."),"n.a.") -> 25098 | F50: =IF(COUNTIFS('Actuals'!$K$6:$K$163,"mastercard|"&F$46&"|net_revenue")=1,IF(AND(COUNTIFS('Actuals'!$K$6:$K$163,"mastercard|"&F$46&"|net_revenue",'Actuals'!$F$6:$F$163,"<>")=1,ISNUMBER(_xlfn.XLOOKUP("mastercard|"&F$46&"|net_revenue",'Actuals'!$K$6:$K$163,'Actuals'!$F$6:$F$163,"n.a.",0)),_xlfn.XLOOKUP("mastercard|"&F$46&"|net_revenue",'Actuals'!$K$6:$K$163,'Actuals'!$G$6:$G$163,"n.a.",0)="USD"),_xlfn.XLOOKUP("mastercard|"&F$46&"|net_revenue",'Actuals'!$K$6:$K$163,'Actuals'!$F$6:$F$163,"n.a.",0)/1000000,"n.a."),"n.a.") -> 28167 | G50: =IF(COUNTIFS('Actuals'!$K$6:$K$163,"mastercard|"&G$46&"|net_revenue")=1,IF(AND(COUNTIFS('Actuals'!$K$6:$K$163,"mastercard|"&G$46&"|net_revenue",'Actuals'!$F$6:$F$163,"<>")=1,ISNUMBER(_xlfn.XLOOKUP("mastercard|"&G$46&"|net_revenue",'Actuals'!$K$6:$K$163,'Actuals'!$F$6:$F$163,"n.a.",0)),_xlfn.XLOOKUP("mastercard|"&G$46&"|net_revenue",'Actuals'!$K$6:$K$163,'Actuals'!$G$6:$G$163,"n.a.",0)="USD"),_xlfn.XLOOKUP("mastercard|"&G$46&"|net_revenue",'Actuals'!$K$6:$K$163,'Actuals'!$F$6:$F$163,"n.a.",0)/1000000,"n.a."),"n.a.") -> 32791
B51: Reported operating expenses | C51: =IF(COUNTIFS('Actuals'!$K$6:$K$163,"mastercard|"&C$46&"|operating_expenses")=1,IF(AND(COUNTIFS('Actuals'!$K$6:$K$163,"mastercard|"&C$46&"|operating_expenses",'Actuals'!$F$6:$F$163,"<>")=1,ISNUMBER(_xlfn.XLOOKUP("mastercard|"&C$46&"|operating_expenses",'Actuals'!$K$6:$K$163,'Actuals'!$F$6:$F$163,"n.a.",0)),_xlfn.XLOOKUP("mastercard|"&C$46&"|operating_expenses",'Actuals'!$K$6:$K$163,'Actuals'!$G$6:$G$163,"n.a.",0)="USD"),_xlfn.XLOOKUP("mastercard|"&C$46&"|operating_expenses",'Actuals'!$K$6:$K$163,'Actuals'!$F$6:$F$163,"n.a.",0)/1000000,"n.a."),"n.a.") -> 8802 | D51: =IF(COUNTIFS('Actuals'!$K$6:$K$163,"mastercard|"&D$46&"|operating_expenses")=1,IF(AND(COUNTIFS('Actuals'!$K$6:$K$163,"mastercard|"&D$46&"|operating_expenses",'Actuals'!$F$6:$F$163,"<>")=1,ISNUMBER(_xlfn.XLOOKUP("mastercard|"&D$46&"|operating_expenses",'Actuals'!$K$6:$K$163,'Actuals'!$F$6:$F$163,"n.a.",0)),_xlfn.XLOOKUP("mastercard|"&D$46&"|operating_expenses",'Actuals'!$K$6:$K$163,'Actuals'!$G$6:$G$163,"n.a.",0)="USD"),_xlfn.XLOOKUP("mastercard|"&D$46&"|operating_expenses",'Actuals'!$K$6:$K$163,'Actuals'!$F$6:$F$163,"n.a.",0)/1000000,"n.a."),"n.a.") -> 9973 | E51: =IF(COUNTIFS('Actuals'!$K$6:$K$163,"mastercard|"&E$46&"|operating_expenses")=1,IF(AND(COUNTIFS('Actuals'!$K$6:$K$163,"mastercard|"&E$46&"|operating_expenses",'Actuals'!$F$6:$F$163,"<>")=1,ISNUMBER(_xlfn.XLOOKUP("mastercard|"&E$46&"|operating_expenses",'Actuals'!$K$6:$K$163,'Actuals'!$F$6:$F$163,"n.a.",0)),_xlfn.XLOOKUP("mastercard|"&E$46&"|operating_expenses",'Actuals'!$K$6:$K$163,'Actuals'!$G$6:$G$163,"n.a.",0)="USD"),_xlfn.XLOOKUP("mastercard|"&E$46&"|operating_expenses",'Actuals'!$K$6:$K$163,'Actuals'!$F$6:$F$163,"n.a.",0)/1000000,"n.a."),"n.a.") -> 11090 | F51: =IF(COUNTIFS('Actuals'!$K$6:$K$163,"mastercard|"&F$46&"|operating_expenses")=1,IF(AND(COUNTIFS('Actuals'!$K$6:$K$163,"mastercard|"&F$46&"|operating_expenses",'Actuals'!$F$6:$F$163,"<>")=1,ISNUMBER(_xlfn.XLOOKUP("mastercard|"&F$46&"|operating_expenses",'Actuals'!$K$6:$K$163,'Actuals'!$F$6:$F$163,"n.a.",0)),_xlfn.XLOOKUP("mastercard|"&F$46&"|operating_expenses",'Actuals'!$K$6:$K$163,'Actuals'!$G$6:$G$163,"n.a.",0)="USD"),_xlfn.XLOOKUP("mastercard|"&F$46&"|operating_expenses",'Actuals'!$K$6:$K$163,'Actuals'!$F$6:$F$163,"n.a.",0)/1000000,"n.a."),"n.a.") -> 12585 | G51: =IF(COUNTIFS('Actuals'!$K$6:$K$163,"mastercard|"&G$46&"|operating_expenses")=1,IF(AND(COUNTIFS('Actuals'!$K$6:$K$163,"mastercard|"&G$46&"|operating_expenses",'Actuals'!$F$6:$F$163,"<>")=1,ISNUMBER(_xlfn.XLOOKUP("mastercard|"&G$46&"|operating_expenses",'Actuals'!$K$6:$K$163,'Actuals'!$F$6:$F$163,"n.a.",0)),_xlfn.XLOOKUP("mastercard|"&G$46&"|operating_expenses",'Actuals'!$K$6:$K$163,'Actuals'!$G$6:$G$163,"n.a.",0)="USD"),_xlfn.XLOOKUP("mastercard|"&G$46&"|operating_expenses",'Actuals'!$K$6:$K$163,'Actuals'!$F$6:$F$163,"n.a.",0)/1000000,"n.a."),"n.a.") -> 13894
B52: Reported operating income | C52: =IF(COUNTIFS('Actuals'!$K$6:$K$163,"mastercard|"&C$46&"|operating_income")=1,IF(AND(COUNTIFS('Actuals'!$K$6:$K$163,"mastercard|"&C$46&"|operating_income",'Actuals'!$F$6:$F$163,"<>")=1,ISNUMBER(_xlfn.XLOOKUP("mastercard|"&C$46&"|operating_income",'Actuals'!$K$6:$K$163,'Actuals'!$F$6:$F$163,"n.a.",0)),_xlfn.XLOOKUP("mastercard|"&C$46&"|operating_income",'Actuals'!$K$6:$K$163,'Actuals'!$G$6:$G$163,"n.a.",0)="USD"),_xlfn.XLOOKUP("mastercard|"&C$46&"|operating_income",'Actuals'!$K$6:$K$163,'Actuals'!$F$6:$F$163,"n.a.",0)/1000000,"n.a."),"n.a.") -> 10082 | D52: =IF(COUNTIFS('Actuals'!$K$6:$K$163,"mastercard|"&D$46&"|operating_income")=1,IF(AND(COUNTIFS('Actuals'!$K$6:$K$163,"mastercard|"&D$46&"|operating_income",'Actuals'!$F$6:$F$163,"<>")=1,ISNUMBER(_xlfn.XLOOKUP("mastercard|"&D$46&"|operating_income",'Actuals'!$K$6:$K$163,'Actuals'!$F$6:$F$163,"n.a.",0)),_xlfn.XLOOKUP("mastercard|"&D$46&"|operating_income",'Actuals'!$K$6:$K$163,'Actuals'!$G$6:$G$163,"n.a.",0)="USD"),_xlfn.XLOOKUP("mastercard|"&D$46&"|operating_income",'Actuals'!$K$6:$K$163,'Actuals'!$F$6:$F$163,"n.a.",0)/1000000,"n.a."),"n.a.") -> 12264 | E52: =IF(COUNTIFS('Actuals'!$K$6:$K$163,"mastercard|"&E$46&"|operating_income")=1,IF(AND(COUNTIFS('Actuals'!$K$6:$K$163,"mastercard|"&E$46&"|operating_income",'Actuals'!$F$6:$F$163,"<>")=1,ISNUMBER(_xlfn.XLOOKUP("mastercard|"&E$46&"|operating_income",'Actuals'!$K$6:$K$163,'Actuals'!$F$6:$F$163,"n.a.",0)),_xlfn.XLOOKUP("mastercard|"&E$46&"|operating_income",'Actuals'!$K$6:$K$163,'Actuals'!$G$6:$G$163,"n.a.",0)="USD"),_xlfn.XLOOKUP("mastercard|"&E$46&"|operating_income",'Actuals'!$K$6:$K$163,'Actuals'!$F$6:$F$163,"n.a.",0)/1000000,"n.a."),"n.a.") -> 14008 | F52: =IF(COUNTIFS('Actuals'!$K$6:$K$163,"mastercard|"&F$46&"|operating_income")=1,IF(AND(COUNTIFS('Actuals'!$K$6:$K$163,"mastercard|"&F$46&"|operating_income",'Actuals'!$F$6:$F$163,"<>")=1,ISNUMBER(_xlfn.XLOOKUP("mastercard|"&F$46&"|operating_income",'Actuals'!$K$6:$K$163,'Actuals'!$F$6:$F$163,"n.a.",0)),_xlfn.XLOOKUP("mastercard|"&F$46&"|operating_income",'Actuals'!$K$6:$K$163,'Actuals'!$G$6:$G$163,"n.a.",0)="USD"),_xlfn.XLOOKUP("mastercard|"&F$46&"|operating_income",'Actuals'!$K$6:$K$163,'Actuals'!$F$6:$F$163,"n.a.",0)/1000000,"n.a."),"n.a.") -> 15582 | G52: =IF(COUNTIFS('Actuals'!$K$6:$K$163,"mastercard|"&G$46&"|operating_income")=1,IF(AND(COUNTIFS('Actuals'!$K$6:$K$163,"mastercard|"&G$46&"|operating_income",'Actuals'!$F$6:$F$163,"<>")=1,ISNUMBER(_xlfn.XLOOKUP("mastercard|"&G$46&"|operating_income",'Actuals'!$K$6:$K$163,'Actuals'!$F$6:$F$163,"n.a.",0)),_xlfn.XLOOKUP("mastercard|"&G$46&"|operating_income",'Actuals'!$K$6:$K$163,'Actuals'!$G$6:$G$163,"n.a.",0)="USD"),_xlfn.XLOOKUP("mastercard|"&G$46&"|operating_income",'Actuals'!$K$6:$K$163,'Actuals'!$F$6:$F$163,"n.a.",0)/1000000,"n.a."),"n.a.") -> 18897
B53: Reported consolidated net income | C53: =IF(COUNTIFS('Actuals'!$K$6:$K$163,"mastercard|"&C$46&"|net_income")=1,IF(AND(COUNTIFS('Actuals'!$K$6:$K$163,"mastercard|"&C$46&"|net_income",'Actuals'!$F$6:$F$163,"<>")=1,ISNUMBER(_xlfn.XLOOKUP("mastercard|"&C$46&"|net_income",'Actuals'!$K$6:$K$163,'Actuals'!$F$6:$F$163,"n.a.",0)),_xlfn.XLOOKUP("mastercard|"&C$46&"|net_income",'Actuals'!$K$6:$K$163,'Actuals'!$G$6:$G$163,"n.a.",0)="USD"),_xlfn.XLOOKUP("mastercard|"&C$46&"|net_income",'Actuals'!$K$6:$K$163,'Actuals'!$F$6:$F$163,"n.a.",0)/1000000,"n.a."),"n.a.") -> 8687 | D53: =IF(COUNTIFS('Actuals'!$K$6:$K$163,"mastercard|"&D$46&"|net_income")=1,IF(AND(COUNTIFS('Actuals'!$K$6:$K$163,"mastercard|"&D$46&"|net_income",'Actuals'!$F$6:$F$163,"<>")=1,ISNUMBER(_xlfn.XLOOKUP("mastercard|"&D$46&"|net_income",'Actuals'!$K$6:$K$163,'Actuals'!$F$6:$F$163,"n.a.",0)),_xlfn.XLOOKUP("mastercard|"&D$46&"|net_income",'Actuals'!$K$6:$K$163,'Actuals'!$G$6:$G$163,"n.a.",0)="USD"),_xlfn.XLOOKUP("mastercard|"&D$46&"|net_income",'Actuals'!$K$6:$K$163,'Actuals'!$F$6:$F$163,"n.a.",0)/1000000,"n.a."),"n.a.") -> 9930 | E53: =IF(COUNTIFS('Actuals'!$K$6:$K$163,"mastercard|"&E$46&"|net_income")=1,IF(AND(COUNTIFS('Actuals'!$K$6:$K$163,"mastercard|"&E$46&"|net_income",'Actuals'!$F$6:$F$163,"<>")=1,ISNUMBER(_xlfn.XLOOKUP("mastercard|"&E$46&"|net_income",'Actuals'!$K$6:$K$163,'Actuals'!$F$6:$F$163,"n.a.",0)),_xlfn.XLOOKUP("mastercard|"&E$46&"|net_income",'Actuals'!$K$6:$K$163,'Actuals'!$G$6:$G$163,"n.a.",0)="USD"),_xlfn.XLOOKUP("mastercard|"&E$46&"|net_income",'Actuals'!$K$6:$K$163,'Actuals'!$F$6:$F$163,"n.a.",0)/1000000,"n.a."),"n.a.") -> 11195 | F53: =IF(COUNTIFS('Actuals'!$K$6:$K$163,"mastercard|"&F$46&"|net_income")=1,IF(AND(COUNTIFS('Actuals'!$K$6:$K$163,"mastercard|"&F$46&"|net_income",'Actuals'!$F$6:$F$163,"<>")=1,ISNUMBER(_xlfn.XLOOKUP("mastercard|"&F$46&"|net_income",'Actuals'!$K$6:$K$163,'Actuals'!$F$6:$F$163,"n.a.",0)),_xlfn.XLOOKUP("mastercard|"&F$46&"|net_income",'Actuals'!$K$6:$K$163,'Actuals'!$G$6:$G$163,"n.a.",0)="USD"),_xlfn.XLOOKUP("mastercard|"&F$46&"|net_income",'Actuals'!$K$6:$K$163,'Actuals'!$F$6:$F$163,"n.a.",0)/1000000,"n.a."),"n.a.") -> 12874 | G53: =IF(COUNTIFS('Actuals'!$K$6:$K$163,"mastercard|"&G$46&"|net_income")=1,IF(AND(COUNTIFS('Actuals'!$K$6:$K$163,"mastercard|"&G$46&"|net_income",'Actuals'!$F$6:$F$163,"<>")=1,ISNUMBER(_xlfn.XLOOKUP("mastercard|"&G$46&"|net_income",'Actuals'!$K$6:$K$163,'Actuals'!$F$6:$F$163,"n.a.",0)),_xlfn.XLOOKUP("mastercard|"&G$46&"|net_income",'Actuals'!$K$6:$K$163,'Actuals'!$G$6:$G$163,"n.a.",0)="USD"),_xlfn.XLOOKUP("mastercard|"&G$46&"|net_income",'Actuals'!$K$6:$K$163,'Actuals'!$F$6:$F$163,"n.a.",0)/1000000,"n.a."),"n.a.") -> 14968
B54: Reported operating cash flow | C54: =IF(COUNTIFS('Actuals'!$K$6:$K$163,"mastercard|"&C$46&"|operating_cash_flow")=1,IF(AND(COUNTIFS('Actuals'!$K$6:$K$163,"mastercard|"&C$46&"|operating_cash_flow",'Actuals'!$F$6:$F$163,"<>")=1,ISNUMBER(_xlfn.XLOOKUP("mastercard|"&C$46&"|operating_cash_flow",'Actuals'!$K$6:$K$163,'Actuals'!$F$6:$F$163,"n.a.",0)),_xlfn.XLOOKUP("mastercard|"&C$46&"|operating_cash_flow",'Actuals'!$K$6:$K$163,'Actuals'!$G$6:$G$163,"n.a.",0)="USD"),_xlfn.XLOOKUP("mastercard|"&C$46&"|operating_cash_flow",'Actuals'!$K$6:$K$163,'Actuals'!$F$6:$F$163,"n.a.",0)/1000000,"n.a."),"n.a.") -> 9463 | D54: =IF(COUNTIFS('Actuals'!$K$6:$K$163,"mastercard|"&D$46&"|operating_cash_flow")=1,IF(AND(COUNTIFS('Actuals'!$K$6:$K$163,"mastercard|"&D$46&"|operating_cash_flow",'Actuals'!$F$6:$F$163,"<>")=1,ISNUMBER(_xlfn.XLOOKUP("mastercard|"&D$46&"|operating_cash_flow",'Actuals'!$K$6:$K$163,'Actuals'!$F$6:$F$163,"n.a.",0)),_xlfn.XLOOKUP("mastercard|"&D$46&"|operating_cash_flow",'Actuals'!$K$6:$K$163,'Actuals'!$G$6:$G$163,"n.a.",0)="USD"),_xlfn.XLOOKUP("mastercard|"&D$46&"|operating_cash_flow",'Actuals'!$K$6:$K$163,'Actuals'!$F$6:$F$163,"n.a.",0)/1000000,"n.a."),"n.a.") -> 11195 | E54: =IF(COUNTIFS('Actuals'!$K$6:$K$163,"mastercard|"&E$46&"|operating_cash_flow")=1,IF(AND(COUNTIFS('Actuals'!$K$6:$K$163,"mastercard|"&E$46&"|operating_cash_flow",'Actuals'!$F$6:$F$163,"<>")=1,ISNUMBER(_xlfn.XLOOKUP("mastercard|"&E$46&"|operating_cash_flow",'Actuals'!$K$6:$K$163,'Actuals'!$F$6:$F$163,"n.a.",0)),_xlfn.XLOOKUP("mastercard|"&E$46&"|operating_cash_flow",'Actuals'!$K$6:$K$163,'Actuals'!$G$6:$G$163,"n.a.",0)="USD"),_xlfn.XLOOKUP("mastercard|"&E$46&"|operating_cash_flow",'Actuals'!$K$6:$K$163,'Actuals'!$F$6:$F$163,"n.a.",0)/1000000,"n.a."),"n.a.") -> 11980 | F54: =IF(COUNTIFS('Actuals'!$K$6:$K$163,"mastercard|"&F$46&"|operating_cash_flow")=1,IF(AND(COUNTIFS('Actuals'!$K$6:$K$163,"mastercard|"&F$46&"|operating_cash_flow",'Actuals'!$F$6:$F$163,"<>")=1,ISNUMBER(_xlfn.XLOOKUP("mastercard|"&F$46&"|operating_cash_flow",'Actuals'!$K$6:$K$163,'Actuals'!$F$6:$F$163,"n.a.",0)),_xlfn.XLOOKUP("mastercard|"&F$46&"|operating_cash_flow",'Actuals'!$K$6:$K$163,'Actuals'!$G$6:$G$163,"n.a.",0)="USD"),_xlfn.XLOOKUP("mastercard|"&F$46&"|operating_cash_flow",'Actuals'!$K$6:$K$163,'Actuals'!$F$6:$F$163,"n.a.",0)/1000000,"n.a."),"n.a.") -> 14780 | G54: =IF(COUNTIFS('Actuals'!$K$6:$K$163,"mastercard|"&G$46&"|operating_cash_flow")=1,IF(AND(COUNTIFS('Actuals'!$K$6:$K$163,"mastercard|"&G$46&"|operating_cash_flow",'Actuals'!$F$6:$F$163,"<>")=1,ISNUMBER(_xlfn.XLOOKUP("mastercard|"&G$46&"|operating_cash_flow",'Actuals'!$K$6:$K$163,'Actuals'!$F$6:$F$163,"n.a.",0)),_xlfn.XLOOKUP("mastercard|"&G$46&"|operating_cash_flow",'Actuals'!$K$6:$K$163,'Actuals'!$G$6:$G$163,"n.a.",0)="USD"),_xlfn.XLOOKUP("mastercard|"&G$46&"|operating_cash_flow",'Actuals'!$K$6:$K$163,'Actuals'!$F$6:$F$163,"n.a.",0)/1000000,"n.a."),"n.a.") -> 17648
B55: Cash and cash equivalents | C55: =IF(COUNTIFS('Actuals'!$K$6:$K$163,"mastercard|"&C$46&"|cash_and_cash_equivalents")=1,IF(AND(COUNTIFS('Actuals'!$K$6:$K$163,"mastercard|"&C$46&"|cash_and_cash_equivalents",'Actuals'!$F$6:$F$163,"<>")=1,ISNUMBER(_xlfn.XLOOKUP("mastercard|"&C$46&"|cash_and_cash_equivalents",'Actuals'!$K$6:$K$163,'Actuals'!$F$6:$F$163,"n.a.",0)),_xlfn.XLOOKUP("mastercard|"&C$46&"|cash_and_cash_equivalents",'Actuals'!$K$6:$K$163,'Actuals'!$G$6:$G$163,"n.a.",0)="USD"),_xlfn.XLOOKUP("mastercard|"&C$46&"|cash_and_cash_equivalents",'Actuals'!$K$6:$K$163,'Actuals'!$F$6:$F$163,"n.a.",0)/1000000,"n.a."),"n.a.") -> 7421 | D55: =IF(COUNTIFS('Actuals'!$K$6:$K$163,"mastercard|"&D$46&"|cash_and_cash_equivalents")=1,IF(AND(COUNTIFS('Actuals'!$K$6:$K$163,"mastercard|"&D$46&"|cash_and_cash_equivalents",'Actuals'!$F$6:$F$163,"<>")=1,ISNUMBER(_xlfn.XLOOKUP("mastercard|"&D$46&"|cash_and_cash_equivalents",'Actuals'!$K$6:$K$163,'Actuals'!$F$6:$F$163,"n.a.",0)),_xlfn.XLOOKUP("mastercard|"&D$46&"|cash_and_cash_equivalents",'Actuals'!$K$6:$K$163,'Actuals'!$G$6:$G$163,"n.a.",0)="USD"),_xlfn.XLOOKUP("mastercard|"&D$46&"|cash_and_cash_equivalents",'Actuals'!$K$6:$K$163,'Actuals'!$F$6:$F$163,"n.a.",0)/1000000,"n.a."),"n.a.") -> 7008 | E55: =IF(COUNTIFS('Actuals'!$K$6:$K$163,"mastercard|"&E$46&"|cash_and_cash_equivalents")=1,IF(AND(COUNTIFS('Actuals'!$K$6:$K$163,"mastercard|"&E$46&"|cash_and_cash_equivalents",'Actuals'!$F$6:$F$163,"<>")=1,ISNUMBER(_xlfn.XLOOKUP("mastercard|"&E$46&"|cash_and_cash_equivalents",'Actuals'!$K$6:$K$163,'Actuals'!$F$6:$F$163,"n.a.",0)),_xlfn.XLOOKUP("mastercard|"&E$46&"|cash_and_cash_equivalents",'Actuals'!$K$6:$K$163,'Actuals'!$G$6:$G$163,"n.a.",0)="USD"),_xlfn.XLOOKUP("mastercard|"&E$46&"|cash_and_cash_equivalents",'Actuals'!$K$6:$K$163,'Actuals'!$F$6:$F$163,"n.a.",0)/1000000,"n.a."),"n.a.") -> 8588 | F55: =IF(COUNTIFS('Actuals'!$K$6:$K$163,"mastercard|"&F$46&"|cash_and_cash_equivalents")=1,IF(AND(COUNTIFS('Actuals'!$K$6:$K$163,"mastercard|"&F$46&"|cash_and_cash_equivalents",'Actuals'!$F$6:$F$163,"<>")=1,ISNUMBER(_xlfn.XLOOKUP("mastercard|"&F$46&"|cash_and_cash_equivalents",'Actuals'!$K$6:$K$163,'Actuals'!$F$6:$F$163,"n.a.",0)),_xlfn.XLOOKUP("mastercard|"&F$46&"|cash_and_cash_equivalents",'Actuals'!$K$6:$K$163,'Actuals'!$G$6:$G$163,"n.a.",0)="USD"),_xlfn.XLOOKUP("mastercard|"&F$46&"|cash_and_cash_equivalents",'Actuals'!$K$6:$K$163,'Actuals'!$F$6:$F$163,"n.a.",0)/1000000,"n.a."),"n.a.") -> 8442 | G55: =IF(COUNTIFS('Actuals'!$K$6:$K$163,"mastercard|"&G$46&"|cash_and_cash_equivalents")=1,IF(AND(COUNTIFS('Actuals'!$K$6:$K$163,"mastercard|"&G$46&"|cash_and_cash_equivalents",'Actuals'!$F$6:$F$163,"<>")=1,ISNUMBER(_xlfn.XLOOKUP("mastercard|"&G$46&"|cash_and_cash_equivalents",'Actuals'!$K$6:$K$163,'Actuals'!$F$6:$F$163,"n.a.",0)),_xlfn.XLOOKUP("mastercard|"&G$46&"|cash_and_cash_equivalents",'Actuals'!$K$6:$K$163,'Actuals'!$G$6:$G$163,"n.a.",0)="USD"),_xlfn.XLOOKUP("mastercard|"&G$46&"|cash_and_cash_equivalents",'Actuals'!$K$6:$K$163,'Actuals'!$F$6:$F$163,"n.a.",0)/1000000,"n.a."),"n.a.") -> 10566
B56: Current debt carrying amount | C56: =IF(COUNTIFS('Actuals'!$K$6:$K$163,"mastercard|"&C$46&"|current_debt")=1,IF(AND(COUNTIFS('Actuals'!$K$6:$K$163,"mastercard|"&C$46&"|current_debt",'Actuals'!$F$6:$F$163,"<>")=1,ISNUMBER(_xlfn.XLOOKUP("mastercard|"&C$46&"|current_debt",'Actuals'!$K$6:$K$163,'Actuals'!$F$6:$F$163,"n.a.",0)),_xlfn.XLOOKUP("mastercard|"&C$46&"|current_debt",'Actuals'!$K$6:$K$163,'Actuals'!$G$6:$G$163,"n.a.",0)="USD"),_xlfn.XLOOKUP("mastercard|"&C$46&"|current_debt",'Actuals'!$K$6:$K$163,'Actuals'!$F$6:$F$163,"n.a.",0)/1000000,"n.a."),"n.a.") -> 792 | D56: =IF(COUNTIFS('Actuals'!$K$6:$K$163,"mastercard|"&D$46&"|current_debt")=1,IF(AND(COUNTIFS('Actuals'!$K$6:$K$163,"mastercard|"&D$46&"|current_debt",'Actuals'!$F$6:$F$163,"<>")=1,ISNUMBER(_xlfn.XLOOKUP("mastercard|"&D$46&"|current_debt",'Actuals'!$K$6:$K$163,'Actuals'!$F$6:$F$163,"n.a.",0)),_xlfn.XLOOKUP("mastercard|"&D$46&"|current_debt",'Actuals'!$K$6:$K$163,'Actuals'!$G$6:$G$163,"n.a.",0)="USD"),_xlfn.XLOOKUP("mastercard|"&D$46&"|current_debt",'Actuals'!$K$6:$K$163,'Actuals'!$F$6:$F$163,"n.a.",0)/1000000,"n.a."),"n.a.") -> 274 | E56: =IF(COUNTIFS('Actuals'!$K$6:$K$163,"mastercard|"&E$46&"|current_debt")=1,IF(AND(COUNTIFS('Actuals'!$K$6:$K$163,"mastercard|"&E$46&"|current_debt",'Actuals'!$F$6:$F$163,"<>")=1,ISNUMBER(_xlfn.XLOOKUP("mastercard|"&E$46&"|current_debt",'Actuals'!$K$6:$K$163,'Actuals'!$F$6:$F$163,"n.a.",0)),_xlfn.XLOOKUP("mastercard|"&E$46&"|current_debt",'Actuals'!$K$6:$K$163,'Actuals'!$G$6:$G$163,"n.a.",0)="USD"),_xlfn.XLOOKUP("mastercard|"&E$46&"|current_debt",'Actuals'!$K$6:$K$163,'Actuals'!$F$6:$F$163,"n.a.",0)/1000000,"n.a."),"n.a.") -> 1337 | F56: =IF(COUNTIFS('Actuals'!$K$6:$K$163,"mastercard|"&F$46&"|current_debt")=1,IF(AND(COUNTIFS('Actuals'!$K$6:$K$163,"mastercard|"&F$46&"|current_debt",'Actuals'!$F$6:$F$163,"<>")=1,ISNUMBER(_xlfn.XLOOKUP("mastercard|"&F$46&"|current_debt",'Actuals'!$K$6:$K$163,'Actuals'!$F$6:$F$163,"n.a.",0)),_xlfn.XLOOKUP("mastercard|"&F$46&"|current_debt",'Actuals'!$K$6:$K$163,'Actuals'!$G$6:$G$163,"n.a.",0)="USD"),_xlfn.XLOOKUP("mastercard|"&F$46&"|current_debt",'Actuals'!$K$6:$K$163,'Actuals'!$F$6:$F$163,"n.a.",0)/1000000,"n.a."),"n.a.") -> 750 | G56: =IF(COUNTIFS('Actuals'!$K$6:$K$163,"mastercard|"&G$46&"|current_debt")=1,IF(AND(COUNTIFS('Actuals'!$K$6:$K$163,"mastercard|"&G$46&"|current_debt",'Actuals'!$F$6:$F$163,"<>")=1,ISNUMBER(_xlfn.XLOOKUP("mastercard|"&G$46&"|current_debt",'Actuals'!$K$6:$K$163,'Actuals'!$F$6:$F$163,"n.a.",0)),_xlfn.XLOOKUP("mastercard|"&G$46&"|current_debt",'Actuals'!$K$6:$K$163,'Actuals'!$G$6:$G$163,"n.a.",0)="USD"),_xlfn.XLOOKUP("mastercard|"&G$46&"|current_debt",'Actuals'!$K$6:$K$163,'Actuals'!$F$6:$F$163,"n.a.",0)/1000000,"n.a."),"n.a.") -> 749
B57: Noncurrent debt carrying amount | C57: =IF(COUNTIFS('Actuals'!$K$6:$K$163,"mastercard|"&C$46&"|noncurrent_debt")=1,IF(AND(COUNTIFS('Actuals'!$K$6:$K$163,"mastercard|"&C$46&"|noncurrent_debt",'Actuals'!$F$6:$F$163,"<>")=1,ISNUMBER(_xlfn.XLOOKUP("mastercard|"&C$46&"|noncurrent_debt",'Actuals'!$K$6:$K$163,'Actuals'!$F$6:$F$163,"n.a.",0)),_xlfn.XLOOKUP("mastercard|"&C$46&"|noncurrent_debt",'Actuals'!$K$6:$K$163,'Actuals'!$G$6:$G$163,"n.a.",0)="USD"),_xlfn.XLOOKUP("mastercard|"&C$46&"|noncurrent_debt",'Actuals'!$K$6:$K$163,'Actuals'!$F$6:$F$163,"n.a.",0)/1000000,"n.a."),"n.a.") -> 13109 | D57: =IF(COUNTIFS('Actuals'!$K$6:$K$163,"mastercard|"&D$46&"|noncurrent_debt")=1,IF(AND(COUNTIFS('Actuals'!$K$6:$K$163,"mastercard|"&D$46&"|noncurrent_debt",'Actuals'!$F$6:$F$163,"<>")=1,ISNUMBER(_xlfn.XLOOKUP("mastercard|"&D$46&"|noncurrent_debt",'Actuals'!$K$6:$K$163,'Actuals'!$F$6:$F$163,"n.a.",0)),_xlfn.XLOOKUP("mastercard|"&D$46&"|noncurrent_debt",'Actuals'!$K$6:$K$163,'Actuals'!$G$6:$G$163,"n.a.",0)="USD"),_xlfn.XLOOKUP("mastercard|"&D$46&"|noncurrent_debt",'Actuals'!$K$6:$K$163,'Actuals'!$F$6:$F$163,"n.a.",0)/1000000,"n.a."),"n.a.") -> 13749 | E57: =IF(COUNTIFS('Actuals'!$K$6:$K$163,"mastercard|"&E$46&"|noncurrent_debt")=1,IF(AND(COUNTIFS('Actuals'!$K$6:$K$163,"mastercard|"&E$46&"|noncurrent_debt",'Actuals'!$F$6:$F$163,"<>")=1,ISNUMBER(_xlfn.XLOOKUP("mastercard|"&E$46&"|noncurrent_debt",'Actuals'!$K$6:$K$163,'Actuals'!$F$6:$F$163,"n.a.",0)),_xlfn.XLOOKUP("mastercard|"&E$46&"|noncurrent_debt",'Actuals'!$K$6:$K$163,'Actuals'!$G$6:$G$163,"n.a.",0)="USD"),_xlfn.XLOOKUP("mastercard|"&E$46&"|noncurrent_debt",'Actuals'!$K$6:$K$163,'Actuals'!$F$6:$F$163,"n.a.",0)/1000000,"n.a."),"n.a.") -> 14344 | F57: =IF(COUNTIFS('Actuals'!$K$6:$K$163,"mastercard|"&F$46&"|noncurrent_debt")=1,IF(AND(COUNTIFS('Actuals'!$K$6:$K$163,"mastercard|"&F$46&"|noncurrent_debt",'Actuals'!$F$6:$F$163,"<>")=1,ISNUMBER(_xlfn.XLOOKUP("mastercard|"&F$46&"|noncurrent_debt",'Actuals'!$K$6:$K$163,'Actuals'!$F$6:$F$163,"n.a.",0)),_xlfn.XLOOKUP("mastercard|"&F$46&"|noncurrent_debt",'Actuals'!$K$6:$K$163,'Actuals'!$G$6:$G$163,"n.a.",0)="USD"),_xlfn.XLOOKUP("mastercard|"&F$46&"|noncurrent_debt",'Actuals'!$K$6:$K$163,'Actuals'!$F$6:$F$163,"n.a.",0)/1000000,"n.a."),"n.a.") -> 17476 | G57: =IF(COUNTIFS('Actuals'!$K$6:$K$163,"mastercard|"&G$46&"|noncurrent_debt")=1,IF(AND(COUNTIFS('Actuals'!$K$6:$K$163,"mastercard|"&G$46&"|noncurrent_debt",'Actuals'!$F$6:$F$163,"<>")=1,ISNUMBER(_xlfn.XLOOKUP("mastercard|"&G$46&"|noncurrent_debt",'Actuals'!$K$6:$K$163,'Actuals'!$F$6:$F$163,"n.a.",0)),_xlfn.XLOOKUP("mastercard|"&G$46&"|noncurrent_debt",'Actuals'!$K$6:$K$163,'Actuals'!$G$6:$G$163,"n.a.",0)="USD"),_xlfn.XLOOKUP("mastercard|"&G$46&"|noncurrent_debt",'Actuals'!$K$6:$K$163,'Actuals'!$F$6:$F$163,"n.a.",0)/1000000,"n.a."),"n.a.") -> 18251
B58: Reported total assets | C58: =IF(COUNTIFS('Actuals'!$K$6:$K$163,"mastercard|"&C$46&"|total_assets")=1,IF(AND(COUNTIFS('Actuals'!$K$6:$K$163,"mastercard|"&C$46&"|total_assets",'Actuals'!$F$6:$F$163,"<>")=1,ISNUMBER(_xlfn.XLOOKUP("mastercard|"&C$46&"|total_assets",'Actuals'!$K$6:$K$163,'Actuals'!$F$6:$F$163,"n.a.",0)),_xlfn.XLOOKUP("mastercard|"&C$46&"|total_assets",'Actuals'!$K$6:$K$163,'Actuals'!$G$6:$G$163,"n.a.",0)="USD"),_xlfn.XLOOKUP("mastercard|"&C$46&"|total_assets",'Actuals'!$K$6:$K$163,'Actuals'!$F$6:$F$163,"n.a.",0)/1000000,"n.a."),"n.a.") -> 37669 | D58: =IF(COUNTIFS('Actuals'!$K$6:$K$163,"mastercard|"&D$46&"|total_assets")=1,IF(AND(COUNTIFS('Actuals'!$K$6:$K$163,"mastercard|"&D$46&"|total_assets",'Actuals'!$F$6:$F$163,"<>")=1,ISNUMBER(_xlfn.XLOOKUP("mastercard|"&D$46&"|total_assets",'Actuals'!$K$6:$K$163,'Actuals'!$F$6:$F$163,"n.a.",0)),_xlfn.XLOOKUP("mastercard|"&D$46&"|total_assets",'Actuals'!$K$6:$K$163,'Actuals'!$G$6:$G$163,"n.a.",0)="USD"),_xlfn.XLOOKUP("mastercard|"&D$46&"|total_assets",'Actuals'!$K$6:$K$163,'Actuals'!$F$6:$F$163,"n.a.",0)/1000000,"n.a."),"n.a.") -> 38724 | E58: =IF(COUNTIFS('Actuals'!$K$6:$K$163,"mastercard|"&E$46&"|total_assets")=1,IF(AND(COUNTIFS('Actuals'!$K$6:$K$163,"mastercard|"&E$46&"|total_assets",'Actuals'!$F$6:$F$163,"<>")=1,ISNUMBER(_xlfn.XLOOKUP("mastercard|"&E$46&"|total_assets",'Actuals'!$K$6:$K$163,'Actuals'!$F$6:$F$163,"n.a.",0)),_xlfn.XLOOKUP("mastercard|"&E$46&"|total_assets",'Actuals'!$K$6:$K$163,'Actuals'!$G$6:$G$163,"n.a.",0)="USD"),_xlfn.XLOOKUP("mastercard|"&E$46&"|total_assets",'Actuals'!$K$6:$K$163,'Actuals'!$F$6:$F$163,"n.a.",0)/1000000,"n.a."),"n.a.") -> 42448 | F58: =IF(COUNTIFS('Actuals'!$K$6:$K$163,"mastercard|"&F$46&"|total_assets")=1,IF(AND(COUNTIFS('Actuals'!$K$6:$K$163,"mastercard|"&F$46&"|total_assets",'Actuals'!$F$6:$F$163,"<>")=1,ISNUMBER(_xlfn.XLOOKUP("mastercard|"&F$46&"|total_assets",'Actuals'!$K$6:$K$163,'Actuals'!$F$6:$F$163,"n.a.",0)),_xlfn.XLOOKUP("mastercard|"&F$46&"|total_assets",'Actuals'!$K$6:$K$163,'Actuals'!$G$6:$G$163,"n.a.",0)="USD"),_xlfn.XLOOKUP("mastercard|"&F$46&"|total_assets",'Actuals'!$K$6:$K$163,'Actuals'!$F$6:$F$163,"n.a.",0)/1000000,"n.a."),"n.a.") -> 48081 | G58: =IF(COUNTIFS('Actuals'!$K$6:$K$163,"mastercard|"&G$46&"|total_assets")=1,IF(AND(COUNTIFS('Actuals'!$K$6:$K$163,"mastercard|"&G$46&"|total_assets",'Actuals'!$F$6:$F$163,"<>")=1,ISNUMBER(_xlfn.XLOOKUP("mastercard|"&G$46&"|total_assets",'Actuals'!$K$6:$K$163,'Actuals'!$F$6:$F$163,"n.a.",0)),_xlfn.XLOOKUP("mastercard|"&G$46&"|total_assets",'Actuals'!$K$6:$K$163,'Actuals'!$G$6:$G$163,"n.a.",0)="USD"),_xlfn.XLOOKUP("mastercard|"&G$46&"|total_assets",'Actuals'!$K$6:$K$163,'Actuals'!$F$6:$F$163,"n.a.",0)/1000000,"n.a."),"n.a.") -> 54157
B59: Reported total liabilities | C59: =IF(COUNTIFS('Actuals'!$K$6:$K$163,"mastercard|"&C$46&"|total_liabilities")=1,IF(AND(COUNTIFS('Actuals'!$K$6:$K$163,"mastercard|"&C$46&"|total_liabilities",'Actuals'!$F$6:$F$163,"<>")=1,ISNUMBER(_xlfn.XLOOKUP("mastercard|"&C$46&"|total_liabilities",'Actuals'!$K$6:$K$163,'Actuals'!$F$6:$F$163,"n.a.",0)),_xlfn.XLOOKUP("mastercard|"&C$46&"|total_liabilities",'Actuals'!$K$6:$K$163,'Actuals'!$G$6:$G$163,"n.a.",0)="USD"),_xlfn.XLOOKUP("mastercard|"&C$46&"|total_liabilities",'Actuals'!$K$6:$K$163,'Actuals'!$F$6:$F$163,"n.a.",0)/1000000,"n.a."),"n.a.") -> 30257 | D59: =IF(COUNTIFS('Actuals'!$K$6:$K$163,"mastercard|"&D$46&"|total_liabilities")=1,IF(AND(COUNTIFS('Actuals'!$K$6:$K$163,"mastercard|"&D$46&"|total_liabilities",'Actuals'!$F$6:$F$163,"<>")=1,ISNUMBER(_xlfn.XLOOKUP("mastercard|"&D$46&"|total_liabilities",'Actuals'!$K$6:$K$163,'Actuals'!$F$6:$F$163,"n.a.",0)),_xlfn.XLOOKUP("mastercard|"&D$46&"|total_liabilities",'Actuals'!$K$6:$K$163,'Actuals'!$G$6:$G$163,"n.a.",0)="USD"),_xlfn.XLOOKUP("mastercard|"&D$46&"|total_liabilities",'Actuals'!$K$6:$K$163,'Actuals'!$F$6:$F$163,"n.a.",0)/1000000,"n.a."),"n.a.") -> 32347 | E59: =IF(COUNTIFS('Actuals'!$K$6:$K$163,"mastercard|"&E$46&"|total_liabilities")=1,IF(AND(COUNTIFS('Actuals'!$K$6:$K$163,"mastercard|"&E$46&"|total_liabilities",'Actuals'!$F$6:$F$163,"<>")=1,ISNUMBER(_xlfn.XLOOKUP("mastercard|"&E$46&"|total_liabilities",'Actuals'!$K$6:$K$163,'Actuals'!$F$6:$F$163,"n.a.",0)),_xlfn.XLOOKUP("mastercard|"&E$46&"|total_liabilities",'Actuals'!$K$6:$K$163,'Actuals'!$G$6:$G$163,"n.a.",0)="USD"),_xlfn.XLOOKUP("mastercard|"&E$46&"|total_liabilities",'Actuals'!$K$6:$K$163,'Actuals'!$F$6:$F$163,"n.a.",0)/1000000,"n.a."),"n.a.") -> 35451 | F59: =IF(COUNTIFS('Actuals'!$K$6:$K$163,"mastercard|"&F$46&"|total_liabilities")=1,IF(AND(COUNTIFS('Actuals'!$K$6:$K$163,"mastercard|"&F$46&"|total_liabilities",'Actuals'!$F$6:$F$163,"<>")=1,ISNUMBER(_xlfn.XLOOKUP("mastercard|"&F$46&"|total_liabilities",'Actuals'!$K$6:$K$163,'Actuals'!$F$6:$F$163,"n.a.",0)),_xlfn.XLOOKUP("mastercard|"&F$46&"|total_liabilities",'Actuals'!$K$6:$K$163,'Actuals'!$G$6:$G$163,"n.a.",0)="USD"),_xlfn.XLOOKUP("mastercard|"&F$46&"|total_liabilities",'Actuals'!$K$6:$K$163,'Actuals'!$F$6:$F$163,"n.a.",0)/1000000,"n.a."),"n.a.") -> 41566 | G59: =IF(COUNTIFS('Actuals'!$K$6:$K$163,"mastercard|"&G$46&"|total_liabilities")=1,IF(AND(COUNTIFS('Actuals'!$K$6:$K$163,"mastercard|"&G$46&"|total_liabilities",'Actuals'!$F$6:$F$163,"<>")=1,ISNUMBER(_xlfn.XLOOKUP("mastercard|"&G$46&"|total_liabilities",'Actuals'!$K$6:$K$163,'Actuals'!$F$6:$F$163,"n.a.",0)),_xlfn.XLOOKUP("mastercard|"&G$46&"|total_liabilities",'Actuals'!$K$6:$K$163,'Actuals'!$G$6:$G$163,"n.a.",0)="USD"),_xlfn.XLOOKUP("mastercard|"&G$46&"|total_liabilities",'Actuals'!$K$6:$K$163,'Actuals'!$F$6:$F$163,"n.a.",0)/1000000,"n.a."),"n.a.") -> 46411
B60: Reported net revenue YoY growth | C60: ="n.a." -> n.a. | D60: =IF(AND(ISNUMBER(D50),ISNUMBER(C50),C50>0),D50/C50-1,"n.a.") -> 0.17755772 | E60: =IF(AND(ISNUMBER(E50),ISNUMBER(D50),D50>0),E50/D50-1,"n.a.") -> 0.12865944 | F60: =IF(AND(ISNUMBER(F50),ISNUMBER(E50),E50>0),F50/E50-1,"n.a.") -> 0.12228066 | G60: =IF(AND(ISNUMBER(G50),ISNUMBER(F50),F50>0),G50/F50-1,"n.a.") -> 0.16416374
B61: Reported operating income YoY growth | C61: ="n.a." -> n.a. | D61: =IF(AND(ISNUMBER(D52),ISNUMBER(C52),C52>0),D52/C52-1,"n.a.") -> 0.21642531 | E61: =IF(AND(ISNUMBER(E52),ISNUMBER(D52),D52>0),E52/D52-1,"n.a.") -> 0.14220483 | F61: =IF(AND(ISNUMBER(F52),ISNUMBER(E52),E52>0),F52/E52-1,"n.a.") -> 0.11236436 | G61: =IF(AND(ISNUMBER(G52),ISNUMBER(F52),F52>0),G52/F52-1,"n.a.") -> 0.21274548
B62: Operating margin | C62: =IF(AND(ISNUMBER(C52),ISNUMBER(C50),C50>0),C52/C50,"n.a.") -> 0.53389112 | D62: =IF(AND(ISNUMBER(D52),ISNUMBER(D50),D50>0),D52/D50,"n.a.") -> 0.55151324 | E62: =IF(AND(ISNUMBER(E52),ISNUMBER(E50),E50>0),E52/E50,"n.a.") -> 0.55813212 | F62: =IF(AND(ISNUMBER(F52),ISNUMBER(F50),F50>0),F52/F50,"n.a.") -> 0.55320055 | G62: =IF(AND(ISNUMBER(G52),ISNUMBER(G50),G50>0),G52/G50,"n.a.") -> 0.57628618
B63: Consolidated net margin | C63: =IF(AND(ISNUMBER(C53),ISNUMBER(C50),C50>0),C53/C50,"n.a.") -> 0.46001906 | D63: =IF(AND(ISNUMBER(D53),ISNUMBER(D50),D50>0),D53/D50,"n.a.") -> 0.44655304 | E63: =IF(AND(ISNUMBER(E53),ISNUMBER(E50),E50>0),E53/E50,"n.a.") -> 0.44605148 | F63: =IF(AND(ISNUMBER(F53),ISNUMBER(F50),F50>0),F53/F50,"n.a.") -> 0.45705968 | G63: =IF(AND(ISNUMBER(G53),ISNUMBER(G50),G50>0),G53/G50,"n.a.") -> 0.45646671
B64: Operating expense ratio | C64: =IF(AND(ISNUMBER(C51),ISNUMBER(C50),C50>0),C51/C50,"n.a.") -> 0.46610888 | D64: =IF(AND(ISNUMBER(D51),ISNUMBER(D50),D50>0),D51/D50,"n.a.") -> 0.44848676 | E64: =IF(AND(ISNUMBER(E51),ISNUMBER(E50),E50>0),E51/E50,"n.a.") -> 0.44186788 | F64: =IF(AND(ISNUMBER(F51),ISNUMBER(F50),F50>0),F51/F50,"n.a.") -> 0.44679945 | G64: =IF(AND(ISNUMBER(G51),ISNUMBER(G50),G50>0),G51/G50,"n.a.") -> 0.42371382
B65: OCF / consolidated net income | C65: =IF(AND(ISNUMBER(C54),ISNUMBER(C53),C53>0),C54/C53,"n.a.") -> 1.0893289 | D65: =IF(AND(ISNUMBER(D54),ISNUMBER(D53),D53>0),D54/D53,"n.a.") -> 1.1273917 | E65: =IF(AND(ISNUMBER(E54),ISNUMBER(E53),E53>0),E54/E53,"n.a.") -> 1.0701206 | F65: =IF(AND(ISNUMBER(F54),ISNUMBER(F53),F53>0),F54/F53,"n.a.") -> 1.1480503 | G65: =IF(AND(ISNUMBER(G54),ISNUMBER(G53),G53>0),G54/G53,"n.a.") -> 1.1790486
B66: Operating margin YoY change | C66: ="n.a." -> n.a. | D66: =IF(AND(ISNUMBER(D62),ISNUMBER(C62)),(D62-C62)*100,"n.a.") -> 1.7622119 | E66: =IF(AND(ISNUMBER(E62),ISNUMBER(D62)),(E62-D62)*100,"n.a.") -> 0.66188784 | F66: =IF(AND(ISNUMBER(F62),ISNUMBER(E62)),(F62-E62)*100,"n.a.") -> -0.49315682 | G66: =IF(AND(ISNUMBER(G62),ISNUMBER(F62)),(G62-F62)*100,"n.a.") -> 2.3085622
B67: Defined capital cash payments | C67: =IF(AND(ISNUMBER(IF(COUNTIFS('Actuals'!$K$6:$K$163,"mastercard|"&C$46&"|capital_payments_primary")=1,IF(AND(COUNTIFS('Actuals'!$K$6:$K$163,"mastercard|"&C$46&"|capital_payments_primary",'Actuals'!$F$6:$F$163,"<>")=1,ISNUMBER(_xlfn.XLOOKUP("mastercard|"&C$46&"|capital_payments_primary",'Actuals'!$K$6:$K$163,'Actuals'!$F$6:$F$163,"n.a.",0)),_xlfn.XLOOKUP("mastercard|"&C$46&"|capital_payments_primary",'Actuals'!$K$6:$K$163,'Actuals'!$G$6:$G$163,"n.a.",0)="USD"),_xlfn.XLOOKUP("mastercard|"&C$46&"|capital_payments_primary",'Actuals'!$K$6:$K$163,'Actuals'!$F$6:$F$163,"n.a.",0)/1000000,"n.a."),"n.a.")),ISNUMBER(IF(COUNTIFS('Actuals'!$K$6:$K$163,"mastercard|"&C$46&"|capitalized_software_payments")=1,IF(AND(COUNTIFS('Actuals'!$K$6:$K$163,"mastercard|"&C$46&"|capitalized_software_payments",'Actuals'!$F$6:$F$163,"<>")=1,ISNUMBER(_xlfn.XLOOKUP("mastercard|"&C$46&"|capitalized_software_payments",'Actuals'!$K$6:$K$163,'Actuals'!$F$6:$F$163,"n.a.",0)),_xlfn.XLOOKUP("mastercard|"&C$46&"|capitalized_software_payments",'Actuals'!$K$6:$K$163,'Actuals'!$G$6:$G$163,"n.a.",0)="USD"),_xlfn.XLOOKUP("mastercard|"&C$46&"|capitalized_software_payments",'Actuals'!$K$6:$K$163,'Actuals'!$F$6:$F$163,"n.a.",0)/1000000,"n.a."),"n.a."))),SUM(IF(COUNTIFS('Actuals'!$K$6:$K$163,"mastercard|"&C$46&"|capital_payments_primary")=1,IF(AND(COUNTIFS('Actuals'!$K$6:$K$163,"mastercard|"&C$46&"|capital_payments_primary",'Actuals'!$F$6:$F$163,"<>")=1,ISNUMBER(_xlfn.XLOOKUP("mastercard|"&C$46&"|capital_payments_primary",'Actuals'!$K$6:$K$163,'Actuals'!$F$6:$F$163,"n.a.",0)),_xlfn.XLOOKUP("mastercard|"&C$46&"|capital_payments_primary",'Actuals'!$K$6:$K$163,'Actuals'!$G$6:$G$163,"n.a.",0)="USD"),_xlfn.XLOOKUP("mastercard|"&C$46&"|capital_payments_primary",'Actuals'!$K$6:$K$163,'Actuals'!$F$6:$F$163,"n.a.",0)/1000000,"n.a."),"n.a."),IF(COUNTIFS('Actuals'!$K$6:$K$163,"mastercard|"&C$46&"|capitalized_software_payments")=1,IF(AND(COUNTIFS('Actuals'!$K$6:$K$163,"mastercard|"&C$46&"|capitalized_software_payments",'Actuals'!$F$6:$F$163,"<>")=1,ISNUMBER(_xlfn.XLOOKUP("mastercard|"&C$46&"|capitalized_software_payments",'Actuals'!$K$6:$K$163,'Actuals'!$F$6:$F$163,"n.a.",0)),_xlfn.XLOOKUP("mastercard|"&C$46&"|capitalized_software_payments",'Actuals'!$K$6:$K$163,'Actuals'!$G$6:$G$163,"n.a.",0)="USD"),_xlfn.XLOOKUP("mastercard|"&C$46&"|capitalized_software_payments",'Actuals'!$K$6:$K$163,'Actuals'!$F$6:$F$163,"n.a.",0)/1000000,"n.a."),"n.a.")),"n.a.") -> 814 | D67: =IF(AND(ISNUMBER(IF(COUNTIFS('Actuals'!$K$6:$K$163,"mastercard|"&D$46&"|capital_payments_primary")=1,IF(AND(COUNTIFS('Actuals'!$K$6:$K$163,"mastercard|"&D$46&"|capital_payments_primary",'Actuals'!$F$6:$F$163,"<>")=1,ISNUMBER(_xlfn.XLOOKUP("mastercard|"&D$46&"|capital_payments_primary",'Actuals'!$K$6:$K$163,'Actuals'!$F$6:$F$163,"n.a.",0)),_xlfn.XLOOKUP("mastercard|"&D$46&"|capital_payments_primary",'Actuals'!$K$6:$K$163,'Actuals'!$G$6:$G$163,"n.a.",0)="USD"),_xlfn.XLOOKUP("mastercard|"&D$46&"|capital_payments_primary",'Actuals'!$K$6:$K$163,'Actuals'!$F$6:$F$163,"n.a.",0)/1000000,"n.a."),"n.a.")),ISNUMBER(IF(COUNTIFS('Actuals'!$K$6:$K$163,"mastercard|"&D$46&"|capitalized_software_payments")=1,IF(AND(COUNTIFS('Actuals'!$K$6:$K$163,"mastercard|"&D$46&"|capitalized_software_payments",'Actuals'!$F$6:$F$163,"<>")=1,ISNUMBER(_xlfn.XLOOKUP("mastercard|"&D$46&"|capitalized_software_payments",'Actuals'!$K$6:$K$163,'Actuals'!$F$6:$F$163,"n.a.",0)),_xlfn.XLOOKUP("mastercard|"&D$46&"|capitalized_software_payments",'Actuals'!$K$6:$K$163,'Actuals'!$G$6:$G$163,"n.a.",0)="USD"),_xlfn.XLOOKUP("mastercard|"&D$46&"|capitalized_software_payments",'Actuals'!$K$6:$K$163,'Actuals'!$F$6:$F$163,"n.a.",0)/1000000,"n.a."),"n.a."))),SUM(IF(COUNTIFS('Actuals'!$K$6:$K$163,"mastercard|"&D$46&"|capital_payments_primary")=1,IF(AND(COUNTIFS('Actuals'!$K$6:$K$163,"mastercard|"&D$46&"|capital_payments_primary",'Actuals'!$F$6:$F$163,"<>")=1,ISNUMBER(_xlfn.XLOOKUP("mastercard|"&D$46&"|capital_payments_primary",'Actuals'!$K$6:$K$163,'Actuals'!$F$6:$F$163,"n.a.",0)),_xlfn.XLOOKUP("mastercard|"&D$46&"|capital_payments_primary",'Actuals'!$K$6:$K$163,'Actuals'!$G$6:$G$163,"n.a.",0)="USD"),_xlfn.XLOOKUP("mastercard|"&D$46&"|capital_payments_primary",'Actuals'!$K$6:$K$163,'Actuals'!$F$6:$F$163,"n.a.",0)/1000000,"n.a."),"n.a."),IF(COUNTIFS('Actuals'!$K$6:$K$163,"mastercard|"&D$46&"|capitalized_software_payments")=1,IF(AND(COUNTIFS('Actuals'!$K$6:$K$163,"mastercard|"&D$46&"|capitalized_software_payments",'Actuals'!$F$6:$F$163,"<>")=1,ISNUMBER(_xlfn.XLOOKUP("mastercard|"&D$46&"|capitalized_software_payments",'Actuals'!$K$6:$K$163,'Actuals'!$F$6:$F$163,"n.a.",0)),_xlfn.XLOOKUP("mastercard|"&D$46&"|capitalized_software_payments",'Actuals'!$K$6:$K$163,'Actuals'!$G$6:$G$163,"n.a.",0)="USD"),_xlfn.XLOOKUP("mastercard|"&D$46&"|capitalized_software_payments",'Actuals'!$K$6:$K$163,'Actuals'!$F$6:$F$163,"n.a.",0)/1000000,"n.a."),"n.a.")),"n.a.") -> 1097 | E67: =IF(AND(ISNUMBER(IF(COUNTIFS('Actuals'!$K$6:$K$163,"mastercard|"&E$46&"|capital_payments_primary")=1,IF(AND(COUNTIFS('Actuals'!$K$6:$K$163,"mastercard|"&E$46&"|capital_payments_primary",'Actuals'!$F$6:$F$163,"<>")=1,ISNUMBER(_xlfn.XLOOKUP("mastercard|"&E$46&"|capital_payments_primary",'Actuals'!$K$6:$K$163,'Actuals'!$F$6:$F$163,"n.a.",0)),_xlfn.XLOOKUP("mastercard|"&E$46&"|capital_payments_primary",'Actuals'!$K$6:$K$163,'Actuals'!$G$6:$G$163,"n.a.",0)="USD"),_xlfn.XLOOKUP("mastercard|"&E$46&"|capital_payments_primary",'Actuals'!$K$6:$K$163,'Actuals'!$F$6:$F$163,"n.a.",0)/1000000,"n.a."),"n.a.")),ISNUMBER(IF(COUNTIFS('Actuals'!$K$6:$K$163,"mastercard|"&E$46&"|capitalized_software_payments")=1,IF(AND(COUNTIFS('Actuals'!$K$6:$K$163,"mastercard|"&E$46&"|capitalized_software_payments",'Actuals'!$F$6:$F$163,"<>")=1,ISNUMBER(_xlfn.XLOOKUP("mastercard|"&E$46&"|capitalized_software_payments",'Actuals'!$K$6:$K$163,'Actuals'!$F$6:$F$163,"n.a.",0)),_xlfn.XLOOKUP("mastercard|"&E$46&"|capitalized_software_payments",'Actuals'!$K$6:$K$163,'Actuals'!$G$6:$G$163,"n.a.",0)="USD"),_xlfn.XLOOKUP("mastercard|"&E$46&"|capitalized_software_payments",'Actuals'!$K$6:$K$163,'Actuals'!$F$6:$F$163,"n.a.",0)/1000000,"n.a."),"n.a."))),SUM(IF(COUNTIFS('Actuals'!$K$6:$K$163,"mastercard|"&E$46&"|capital_payments_primary")=1,IF(AND(COUNTIFS('Actuals'!$K$6:$K$163,"mastercard|"&E$46&"|capital_payments_primary",'Actuals'!$F$6:$F$163,"<>")=1,ISNUMBER(_xlfn.XLOOKUP("mastercard|"&E$46&"|capital_payments_primary",'Actuals'!$K$6:$K$163,'Actuals'!$F$6:$F$163,"n.a.",0)),_xlfn.XLOOKUP("mastercard|"&E$46&"|capital_payments_primary",'Actuals'!$K$6:$K$163,'Actuals'!$G$6:$G$163,"n.a.",0)="USD"),_xlfn.XLOOKUP("mastercard|"&E$46&"|capital_payments_primary",'Actuals'!$K$6:$K$163,'Actuals'!$F$6:$F$163,"n.a.",0)/1000000,"n.a."),"n.a."),IF(COUNTIFS('Actuals'!$K$6:$K$163,"mastercard|"&E$46&"|capitalized_software_payments")=1,IF(AND(COUNTIFS('Actuals'!$K$6:$K$163,"mastercard|"&E$46&"|capitalized_software_payments",'Actuals'!$F$6:$F$163,"<>")=1,ISNUMBER(_xlfn.XLOOKUP("mastercard|"&E$46&"|capitalized_software_payments",'Actuals'!$K$6:$K$163,'Actuals'!$F$6:$F$163,"n.a.",0)),_xlfn.XLOOKUP("mastercard|"&E$46&"|capitalized_software_payments",'Actuals'!$K$6:$K$163,'Actuals'!$G$6:$G$163,"n.a.",0)="USD"),_xlfn.XLOOKUP("mastercard|"&E$46&"|capitalized_software_payments",'Actuals'!$K$6:$K$163,'Actuals'!$F$6:$F$163,"n.a.",0)/1000000,"n.a."),"n.a.")),"n.a.") -> 1088 | F67: =IF(AND(ISNUMBER(IF(COUNTIFS('Actuals'!$K$6:$K$163,"mastercard|"&F$46&"|capital_payments_primary")=1,IF(AND(COUNTIFS('Actuals'!$K$6:$K$163,"mastercard|"&F$46&"|capital_payments_primary",'Actuals'!$F$6:$F$163,"<>")=1,ISNUMBER(_xlfn.XLOOKUP("mastercard|"&F$46&"|capital_payments_primary",'Actuals'!$K$6:$K$163,'Actuals'!$F$6:$F$163,"n.a.",0)),_xlfn.XLOOKUP("mastercard|"&F$46&"|capital_payments_primary",'Actuals'!$K$6:$K$163,'Actuals'!$G$6:$G$163,"n.a.",0)="USD"),_xlfn.XLOOKUP("mastercard|"&F$46&"|capital_payments_primary",'Actuals'!$K$6:$K$163,'Actuals'!$F$6:$F$163,"n.a.",0)/1000000,"n.a."),"n.a.")),ISNUMBER(IF(COUNTIFS('Actuals'!$K$6:$K$163,"mastercard|"&F$46&"|capitalized_software_payments")=1,IF(AND(COUNTIFS('Actuals'!$K$6:$K$163,"mastercard|"&F$46&"|capitalized_software_payments",'Actuals'!$F$6:$F$163,"<>")=1,ISNUMBER(_xlfn.XLOOKUP("mastercard|"&F$46&"|capitalized_software_payments",'Actuals'!$K$6:$K$163,'Actuals'!$F$6:$F$163,"n.a.",0)),_xlfn.XLOOKUP("mastercard|"&F$46&"|capitalized_software_payments",'Actuals'!$K$6:$K$163,'Actuals'!$G$6:$G$163,"n.a.",0)="USD"),_xlfn.XLOOKUP("mastercard|"&F$46&"|capitalized_software_payments",'Actuals'!$K$6:$K$163,'Actuals'!$F$6:$F$163,"n.a.",0)/1000000,"n.a."),"n.a."))),SUM(IF(COUNTIFS('Actuals'!$K$6:$K$163,"mastercard|"&F$46&"|capital_payments_primary")=1,IF(AND(COUNTIFS('Actuals'!$K$6:$K$163,"mastercard|"&F$46&"|capital_payments_primary",'Actuals'!$F$6:$F$163,"<>")=1,ISNUMBER(_xlfn.XLOOKUP("mastercard|"&F$46&"|capital_payments_primary",'Actuals'!$K$6:$K$163,'Actuals'!$F$6:$F$163,"n.a.",0)),_xlfn.XLOOKUP("mastercard|"&F$46&"|capital_payments_primary",'Actuals'!$K$6:$K$163,'Actuals'!$G$6:$G$163,"n.a.",0)="USD"),_xlfn.XLOOKUP("mastercard|"&F$46&"|capital_payments_primary",'Actuals'!$K$6:$K$163,'Actuals'!$F$6:$F$163,"n.a.",0)/1000000,"n.a."),"n.a."),IF(COUNTIFS('Actuals'!$K$6:$K$163,"mastercard|"&F$46&"|capitalized_software_payments")=1,IF(AND(COUNTIFS('Actuals'!$K$6:$K$163,"mastercard|"&F$46&"|capitalized_software_payments",'Actuals'!$F$6:$F$163,"<>")=1,ISNUMBER(_xlfn.XLOOKUP("mastercard|"&F$46&"|capitalized_software_payments",'Actuals'!$K$6:$K$163,'Actuals'!$F$6:$F$163,"n.a.",0)),_xlfn.XLOOKUP("mastercard|"&F$46&"|capitalized_software_payments",'Actuals'!$K$6:$K$163,'Actuals'!$G$6:$G$163,"n.a.",0)="USD"),_xlfn.XLOOKUP("mastercard|"&F$46&"|capitalized_software_payments",'Actuals'!$K$6:$K$163,'Actuals'!$F$6:$F$163,"n.a.",0)/1000000,"n.a."),"n.a.")),"n.a.") -> 1194 | G67: =IF(AND(ISNUMBER(IF(COUNTIFS('Actuals'!$K$6:$K$163,"mastercard|"&G$46&"|capital_payments_primary")=1,IF(AND(COUNTIFS('Actuals'!$K$6:$K$163,"mastercard|"&G$46&"|capital_payments_primary",'Actuals'!$F$6:$F$163,"<>")=1,ISNUMBER(_xlfn.XLOOKUP("mastercard|"&G$46&"|capital_payments_primary",'Actuals'!$K$6:$K$163,'Actuals'!$F$6:$F$163,"n.a.",0)),_xlfn.XLOOKUP("mastercard|"&G$46&"|capital_payments_primary",'Actuals'!$K$6:$K$163,'Actuals'!$G$6:$G$163,"n.a.",0)="USD"),_xlfn.XLOOKUP("mastercard|"&G$46&"|capital_payments_primary",'Actuals'!$K$6:$K$163,'Actuals'!$F$6:$F$163,"n.a.",0)/1000000,"n.a."),"n.a.")),ISNUMBER(IF(COUNTIFS('Actuals'!$K$6:$K$163,"mastercard|"&G$46&"|capitalized_software_payments")=1,IF(AND(COUNTIFS('Actuals'!$K$6:$K$163,"mastercard|"&G$46&"|capitalized_software_payments",'Actuals'!$F$6:$F$163,"<>")=1,ISNUMBER(_xlfn.XLOOKUP("mastercard|"&G$46&"|capitalized_software_payments",'Actuals'!$K$6:$K$163,'Actuals'!$F$6:$F$163,"n.a.",0)),_xlfn.XLOOKUP("mastercard|"&G$46&"|capitalized_software_payments",'Actuals'!$K$6:$K$163,'Actuals'!$G$6:$G$163,"n.a.",0)="USD"),_xlfn.XLOOKUP("mastercard|"&G$46&"|capitalized_software_payments",'Actuals'!$K$6:$K$163,'Actuals'!$F$6:$F$163,"n.a.",0)/1000000,"n.a."),"n.a."))),SUM(IF(COUNTIFS('Actuals'!$K$6:$K$163,"mastercard|"&G$46&"|capital_payments_primary")=1,IF(AND(COUNTIFS('Actuals'!$K$6:$K$163,"mastercard|"&G$46&"|capital_payments_primary",'Actuals'!$F$6:$F$163,"<>")=1,ISNUMBER(_xlfn.XLOOKUP("mastercard|"&G$46&"|capital_payments_primary",'Actuals'!$K$6:$K$163,'Actuals'!$F$6:$F$163,"n.a.",0)),_xlfn.XLOOKUP("mastercard|"&G$46&"|capital_payments_primary",'Actuals'!$K$6:$K$163,'Actuals'!$G$6:$G$163,"n.a.",0)="USD"),_xlfn.XLOOKUP("mastercard|"&G$46&"|capital_payments_primary",'Actuals'!$K$6:$K$163,'Actuals'!$F$6:$F$163,"n.a.",0)/1000000,"n.a."),"n.a."),IF(COUNTIFS('Actuals'!$K$6:$K$163,"mastercard|"&G$46&"|capitalized_software_payments")=1,IF(AND(COUNTIFS('Actuals'!$K$6:$K$163,"mastercard|"&G$46&"|capitalized_software_payments",'Actuals'!$F$6:$F$163,"<>")=1,ISNUMBER(_xlfn.XLOOKUP("mastercard|"&G$46&"|capitalized_software_payments",'Actuals'!$K$6:$K$163,'Actuals'!$F$6:$F$163,"n.a.",0)),_xlfn.XLOOKUP("mastercard|"&G$46&"|capitalized_software_payments",'Actuals'!$K$6:$K$163,'Actuals'!$G$6:$G$163,"n.a.",0)="USD"),_xlfn.XLOOKUP("mastercard|"&G$46&"|capitalized_software_payments",'Actuals'!$K$6:$K$163,'Actuals'!$F$6:$F$163,"n.a.",0)/1000000,"n.a."),"n.a.")),"n.a.") -> 1215
B68: OCF less defined capital payments | C68: =IF(AND(ISNUMBER(C54),ISNUMBER(C67)),C54-C67,"n.a.") -> 8649 | D68: =IF(AND(ISNUMBER(D54),ISNUMBER(D67)),D54-D67,"n.a.") -> 10098 | E68: =IF(AND(ISNUMBER(E54),ISNUMBER(E67)),E54-E67,"n.a.") -> 10892 | F68: =IF(AND(ISNUMBER(F54),ISNUMBER(F67)),F54-F67,"n.a.") -> 13586 | G68: =IF(AND(ISNUMBER(G54),ISNUMBER(G67)),G54-G67,"n.a.") -> 16433
B69: FCF proxy / net revenue | C69: =IF(AND(ISNUMBER(C68),ISNUMBER(C50),C50>0),C68/C50,"n.a.") -> 0.45800678 | D69: =IF(AND(ISNUMBER(D68),ISNUMBER(D50),D50>0),D68/D50,"n.a.") -> 0.45410802 | E69: =IF(AND(ISNUMBER(E68),ISNUMBER(E50),E50>0),E68/E50,"n.a.") -> 0.4339788 | F69: =IF(AND(ISNUMBER(F68),ISNUMBER(F50),F50>0),F68/F50,"n.a.") -> 0.48233749 | G69: =IF(AND(ISNUMBER(G68),ISNUMBER(G50),G50>0),G68/G50,"n.a.") -> 0.50114361
B70: Selected debt carrying total | C70: =IF(AND(ISNUMBER(C56),ISNUMBER(C57)),SUM(C56,C57),"n.a.") -> 13901 | D70: =IF(AND(ISNUMBER(D56),ISNUMBER(D57)),SUM(D56,D57),"n.a.") -> 14023 | E70: =IF(AND(ISNUMBER(E56),ISNUMBER(E57)),SUM(E56,E57),"n.a.") -> 15681 | F70: =IF(AND(ISNUMBER(F56),ISNUMBER(F57)),SUM(F56,F57),"n.a.") -> 18226 | G70: =IF(AND(ISNUMBER(G56),ISNUMBER(G57)),SUM(G56,G57),"n.a.") -> 19000
B71: Selected debt less cash proxy | C71: =IF(AND(ISNUMBER(C70),ISNUMBER(C55)),C70-C55,"n.a.") -> 6480 | D71: =IF(AND(ISNUMBER(D70),ISNUMBER(D55)),D70-D55,"n.a.") -> 7015 | E71: =IF(AND(ISNUMBER(E70),ISNUMBER(E55)),E70-E55,"n.a.") -> 7093 | F71: =IF(AND(ISNUMBER(F70),ISNUMBER(F55)),F70-F55,"n.a.") -> 9784 | G71: =IF(AND(ISNUMBER(G70),ISNUMBER(G55)),G70-G55,"n.a.") -> 8434
B72: Selected debt / total assets | C72: =IF(AND(ISNUMBER(C70),ISNUMBER(C58),C58>0),C70/C58,"n.a.") -> 0.36903024 | D72: =IF(AND(ISNUMBER(D70),ISNUMBER(D58),D58>0),D70/D58,"n.a.") -> 0.36212685 | E72: =IF(AND(ISNUMBER(E70),ISNUMBER(E58),E58>0),E70/E58,"n.a.") -> 0.3694167 | F72: =IF(AND(ISNUMBER(F70),ISNUMBER(F58),F58>0),F70/F58,"n.a.") -> 0.37906865 | G72: =IF(AND(ISNUMBER(G70),ISNUMBER(G58),G58>0),G70/G58,"n.a.") -> 0.35083184
B73: Total liabilities / total assets | C73: =IF(AND(ISNUMBER(C59),ISNUMBER(C58),C58>0),C59/C58,"n.a.") -> 0.80323343 | D73: =IF(AND(ISNUMBER(D59),ISNUMBER(D58),D58>0),D59/D58,"n.a.") -> 0.83532176 | E73: =IF(AND(ISNUMBER(E59),ISNUMBER(E58),E58>0),E59/E58,"n.a.") -> 0.83516302 | F73: =IF(AND(ISNUMBER(F59),ISNUMBER(F58),F58>0),F59/F58,"n.a.") -> 0.86449949 | G73: =IF(AND(ISNUMBER(G59),ISNUMBER(G58),G58>0),G59/G58,"n.a.") -> 0.8569714
B74: Cash equivalents / selected debt | C74: =IF(AND(ISNUMBER(C55),ISNUMBER(C70),C70>0),C55/C70,"n.a.") -> 0.53384649 | D74: =IF(AND(ISNUMBER(D55),ISNUMBER(D70),D70>0),D55/D70,"n.a.") -> 0.49975041 | E74: =IF(AND(ISNUMBER(E55),ISNUMBER(E70),E70>0),E55/E70,"n.a.") -> 0.54766915 | F74: =IF(AND(ISNUMBER(F55),ISNUMBER(F70),F70>0),F55/F70,"n.a.") -> 0.46318446 | G74: =IF(AND(ISNUMBER(G55),ISNUMBER(G70),G70>0),G55/G70,"n.a.") -> 0.55610526
B76: FCF proxy: OCF less defined capital payments.
B77: Visa: equipment/technology; Mastercard: PPE plus software.
B79: Cash/debt uses selected carrying debt; not maturity coverage.
B81: Industry: 30 verified values in the Industry sheet. Six FY2021 changes have no verified FY2020 base.
B83: Reported margins include disclosed legal/tax effects; no normalization.

Sheet Actuals
A1: Reviewed statement inputs
A2: Amounts in original USD. Source reporting units were normalized before this workbook.
A3: Frozen FY2021–2025 evidence. Edit only the amber assumptions on Scenario.
A5: Company | B5: Fiscal year | C5: Item | D5: Period start | E5: Period end | F5: Amount (USD) | G5: Unit | H5: IR PDF page | I5: Filing accession | J5: Original source | K5: Lookup key | M5: Original PDF URL
A6: visa | B6: 2021 | C6: net_revenue | D6: 2020-10-01T00:00:00.000Z | E6: 2021-09-30T00:00:00.000Z | F6: 24105000000 | G6: USD | H6: 67 | I6: 0001403161-23-000099 | J6: Visa FY2023 annual report, PDF p67 | K6: =A6&"|"&B6&"|"&C6 -> visa|2021|net_revenue | M6: =_xlfn.XLOOKUP(I6,$I$169:$I$174,$M$169:$M$174,"n.a.",0) -> https://s29.q4cdn.com/385744025/files/doc_downloads/2023/Visa-Inc-Fiscal-2023-Annual-Report.pdf
A7: visa | B7: 2021 | C7: operating_expenses | D7: 2020-10-01T00:00:00.000Z | E7: 2021-09-30T00:00:00.000Z | F7: 8301000000 | G7: USD | H7: 67 | I7: 0001403161-23-000099 | J7: Visa FY2023 annual report, PDF p67 | K7: =A7&"|"&B7&"|"&C7 -> visa|2021|operating_expenses | M7: =_xlfn.XLOOKUP(I7,$I$169:$I$174,$M$169:$M$174,"n.a.",0) -> https://s29.q4cdn.com/385744025/files/doc_downloads/2023/Visa-Inc-Fiscal-2023-Annual-Report.pdf
A8: visa | B8: 2021 | C8: operating_income | D8: 2020-10-01T00:00:00.000Z | E8: 2021-09-30T00:00:00.000Z | F8: 15804000000 | G8: USD | H8: 67 | I8: 0001403161-23-000099 | J8: Visa FY2023 annual report, PDF p67 | K8: =A8&"|"&B8&"|"&C8 -> visa|2021|operating_income | M8: =_xlfn.XLOOKUP(I8,$I$169:$I$174,$M$169:$M$174,"n.a.",0) -> https://s29.q4cdn.com/385744025/files/doc_downloads/2023/Visa-Inc-Fiscal-2023-Annual-Report.pdf
A9: visa | B9: 2021 | C9: pretax_income | D9: 2020-10-01T00:00:00.000Z | E9: 2021-09-30T00:00:00.000Z | F9: 16063000000 | G9: USD | H9: 67 | I9: 0001403161-23-000099 | J9: Visa FY2023 annual report, PDF p67 | K9: =A9&"|"&B9&"|"&C9 -> visa|2021|pretax_income | M9: =_xlfn.XLOOKUP(I9,$I$169:$I$174,$M$169:$M$174,"n.a.",0) -> https://s29.q4cdn.com/385744025/files/doc_downloads/2023/Visa-Inc-Fiscal-2023-Annual-Report.pdf
A10: visa | B10: 2021 | C10: income_tax | D10: 2020-10-01T00:00:00.000Z | E10: 2021-09-30T00:00:00.000Z | F10: 3752000000 | G10: USD | H10: 67 | I10: 0001403161-23-000099 | J10: Visa FY2023 annual report, PDF p67 | K10: =A10&"|"&B10&"|"&C10 -> visa|2021|income_tax | M10: =_xlfn.XLOOKUP(I10,$I$169:$I$174,$M$169:$M$174,"n.a.",0) -> https://s29.q4cdn.com/385744025/files/doc_downloads/2023/Visa-Inc-Fiscal-2023-Annual-Report.pdf
A11: visa | B11: 2021 | C11: net_income | D11: 2020-10-01T00:00:00.000Z | E11: 2021-09-30T00:00:00.000Z | F11: 12311000000 | G11: USD | H11: 67 | I11: 0001403161-23-000099 | J11: Visa FY2023 annual report, PDF p67 | K11: =A11&"|"&B11&"|"&C11 -> visa|2021|net_income | M11: =_xlfn.XLOOKUP(I11,$I$169:$I$174,$M$169:$M$174,"n.a.",0) -> https://s29.q4cdn.com/385744025/files/doc_downloads/2023/Visa-Inc-Fiscal-2023-Annual-Report.pdf
A12: visa | B12: 2021 | C12: operating_cash_flow | D12: 2020-10-01T00:00:00.000Z | E12: 2021-09-30T00:00:00.000Z | F12: 15227000000 | G12: USD | H12: 72 | I12: 0001403161-23-000099 | J12: Visa FY2023 annual report, PDF p72 | K12: =A12&"|"&B12&"|"&C12 -> visa|2021|operating_cash_flow | M12: =_xlfn.XLOOKUP(I12,$I$169:$I$174,$M$169:$M$174,"n.a.",0) -> https://s29.q4cdn.com/385744025/files/doc_downloads/2023/Visa-Inc-Fiscal-2023-Annual-Report.pdf
A13: visa | B13: 2021 | C13: capital_payments_primary | D13: 2020-10-01T00:00:00.000Z | E13: 2021-09-30T00:00:00.000Z | F13: 705000000 | G13: USD | H13: 72 | I13: 0001403161-23-000099 | J13: Visa FY2023 annual report, PDF p72 | K13: =A13&"|"&B13&"|"&C13 -> visa|2021|capital_payments_primary | M13: =_xlfn.XLOOKUP(I13,$I$169:$I$174,$M$169:$M$174,"n.a.",0) -> https://s29.q4cdn.com/385744025/files/doc_downloads/2023/Visa-Inc-Fiscal-2023-Annual-Report.pdf
A14: visa | B14: 2021 | C14: cash_and_cash_equivalents | E14: 2021-09-30T00:00:00.000Z | F14: 16487000000 | G14: USD | H14: 66 | I14: 0001403161-21-000060 | J14: Visa FY2021 annual report, PDF p66 | K14: =A14&"|"&B14&"|"&C14 -> visa|2021|cash_and_cash_equivalents | M14: =_xlfn.XLOOKUP(I14,$I$169:$I$174,$M$169:$M$174,"n.a.",0) -> https://s29.q4cdn.com/385744025/files/doc_downloads/Visa-Inc_-Fiscal-2021-Annual-Report.pdf
A15: visa | B15: 2021 | C15: current_debt | E15: 2021-09-30T00:00:00.000Z | F15: 999000000 | G15: USD | H15: 66 | I15: 0001403161-21-000060 | J15: Visa FY2021 annual report, PDF p66 | K15: =A15&"|"&B15&"|"&C15 -> visa|2021|current_debt | M15: =_xlfn.XLOOKUP(I15,$I$169:$I$174,$M$169:$M$174,"n.a.",0) -> https://s29.q4cdn.com/385744025/files/doc_downloads/Visa-Inc_-Fiscal-2021-Annual-Report.pdf
A16: visa | B16: 2021 | C16: noncurrent_debt | E16: 2021-09-30T00:00:00.000Z | F16: 19978000000 | G16: USD | H16: 66 | I16: 0001403161-21-000060 | J16: Visa FY2021 annual report, PDF p66 | K16: =A16&"|"&B16&"|"&C16 -> visa|2021|noncurrent_debt | M16: =_xlfn.XLOOKUP(I16,$I$169:$I$174,$M$169:$M$174,"n.a.",0) -> https://s29.q4cdn.com/385744025/files/doc_downloads/Visa-Inc_-Fiscal-2021-Annual-Report.pdf
A17: visa | B17: 2021 | C17: total_assets | E17: 2021-09-30T00:00:00.000Z | F17: 82896000000 | G17: USD | H17: 66 | I17: 0001403161-21-000060 | J17: Visa FY2021 annual report, PDF p66 | K17: =A17&"|"&B17&"|"&C17 -> visa|2021|total_assets | M17: =_xlfn.XLOOKUP(I17,$I$169:$I$174,$M$169:$M$174,"n.a.",0) -> https://s29.q4cdn.com/385744025/files/doc_downloads/Visa-Inc_-Fiscal-2021-Annual-Report.pdf
A18: visa | B18: 2021 | C18: total_liabilities | E18: 2021-09-30T00:00:00.000Z | F18: 45307000000 | G18: USD | H18: 66 | I18: 0001403161-21-000060 | J18: Visa FY2021 annual report, PDF p66 | K18: =A18&"|"&B18&"|"&C18 -> visa|2021|total_liabilities | M18: =_xlfn.XLOOKUP(I18,$I$169:$I$174,$M$169:$M$174,"n.a.",0) -> https://s29.q4cdn.com/385744025/files/doc_downloads/Visa-Inc_-Fiscal-2021-Annual-Report.pdf
A19: visa | B19: 2021 | C19: total_equity | E19: 2021-09-30T00:00:00.000Z | F19: 37589000000 | G19: USD | H19: 66 | I19: 0001403161-21-000060 | J19: Visa FY2021 annual report, PDF p66 | K19: =A19&"|"&B19&"|"&C19 -> visa|2021|total_equity | M19: =_xlfn.XLOOKUP(I19,$I$169:$I$174,$M$169:$M$174,"n.a.",0) -> https://s29.q4cdn.com/385744025/files/doc_downloads/Visa-Inc_-Fiscal-2021-Annual-Report.pdf
A20: visa | B20: 2021 | C20: cash_flow_total_end | E20: 2021-09-30T00:00:00.000Z | F20: 19799000000 | G20: USD | H20: 72 | I20: 0001403161-23-000099 | J20: Visa FY2023 annual report, PDF p72 | K20: =A20&"|"&B20&"|"&C20 -> visa|2021|cash_flow_total_end | M20: =_xlfn.XLOOKUP(I20,$I$169:$I$174,$M$169:$M$174,"n.a.",0) -> https://s29.q4cdn.com/385744025/files/doc_downloads/2023/Visa-Inc-Fiscal-2023-Annual-Report.pdf
A21: visa | B21: 2022 | C21: net_revenue | D21: 2021-10-01T00:00:00.000Z | E21: 2022-09-30T00:00:00.000Z | F21: 29310000000 | G21: USD | H21: 67 | I21: 0001403161-23-000099 | J21: Visa FY2023 annual report, PDF p67 | K21: =A21&"|"&B21&"|"&C21 -> visa|2022|net_revenue | M21: =_xlfn.XLOOKUP(I21,$I$169:$I$174,$M$169:$M$174,"n.a.",0) -> https://s29.q4cdn.com/385744025/files/doc_downloads/2023/Visa-Inc-Fiscal-2023-Annual-Report.pdf
A22: visa | B22: 2022 | C22: operating_expenses | D22: 2021-10-01T00:00:00.000Z | E22: 2022-09-30T00:00:00.000Z | F22: 10497000000 | G22: USD | H22: 67 | I22: 0001403161-23-000099 | J22: Visa FY2023 annual report, PDF p67 | K22: =A22&"|"&B22&"|"&C22 -> visa|2022|operating_expenses | M22: =_xlfn.XLOOKUP(I22,$I$169:$I$174,$M$169:$M$174,"n.a.",0) -> https://s29.q4cdn.com/385744025/files/doc_downloads/2023/Visa-Inc-Fiscal-2023-Annual-Report.pdf
A23: visa | B23: 2022 | C23: operating_income | D23: 2021-10-01T00:00:00.000Z | E23: 2022-09-30T00:00:00.000Z | F23: 18813000000 | G23: USD | H23: 67 | I23: 0001403161-23-000099 | J23: Visa FY2023 annual report, PDF p67 | K23: =A23&"|"&B23&"|"&C23 -> visa|2022|operating_income | M23: =_xlfn.XLOOKUP(I23,$I$169:$I$174,$M$169:$M$174,"n.a.",0) -> https://s29.q4cdn.com/385744025/files/doc_downloads/2023/Visa-Inc-Fiscal-2023-Annual-Report.pdf
A24: visa | B24: 2022 | C24: pretax_income | D24: 2021-10-01T00:00:00.000Z | E24: 2022-09-30T00:00:00.000Z | F24: 18136000000 | G24: USD | H24: 67 | I24: 0001403161-23-000099 | J24: Visa FY2023 annual report, PDF p67 | K24: =A24&"|"&B24&"|"&C24 -> visa|2022|pretax_income | M24: =_xlfn.XLOOKUP(I24,$I$169:$I$174,$M$169:$M$174,"n.a.",0) -> https://s29.q4cdn.com/385744025/files/doc_downloads/2023/Visa-Inc-Fiscal-2023-Annual-Report.pdf
A25: visa | B25: 2022 | C25: income_tax | D25: 2021-10-01T00:00:00.000Z | E25: 2022-09-30T00:00:00.000Z | F25: 3179000000 | G25: USD | H25: 67 | I25: 0001403161-23-000099 | J25: Visa FY2023 annual report, PDF p67 | K25: =A25&"|"&B25&"|"&C25 -> visa|2022|income_tax | M25: =_xlfn.XLOOKUP(I25,$I$169:$I$174,$M$169:$M$174,"n.a.",0) -> https://s29.q4cdn.com/385744025/files/doc_downloads/2023/Visa-Inc-Fiscal-2023-Annual-Report.pdf
A26: visa | B26: 2022 | C26: net_income | D26: 2021-10-01T00:00:00.000Z | E26: 2022-09-30T00:00:00.000Z | F26: 14957000000 | G26: USD | H26: 67 | I26: 0001403161-23-000099 | J26: Visa FY2023 annual report, PDF p67 | K26: =A26&"|"&B26&"|"&C26 -> visa|2022|net_income | M26: =_xlfn.XLOOKUP(I26,$I$169:$I$174,$M$169:$M$174,"n.a.",0) -> https://s29.q4cdn.com/385744025/files/doc_downloads/2023/Visa-Inc-Fiscal-2023-Annual-Report.pdf
A27: visa | B27: 2022 | C27: operating_cash_flow | D27: 2021-10-01T00:00:00.000Z | E27: 2022-09-30T00:00:00.000Z | F27: 18849000000 | G27: USD | H27: 72 | I27: 0001403161-23-000099 | J27: Visa FY2023 annual report, PDF p72 | K27: =A27&"|"&B27&"|"&C27 -> visa|2022|operating_cash_flow | M27: =_xlfn.XLOOKUP(I27,$I$169:$I$174,$M$169:$M$174,"n.a.",0) -> https://s29.q4cdn.com/385744025/files/doc_downloads/2023/Visa-Inc-Fiscal-2023-Annual-Report.pdf
A28: visa | B28: 2022 | C28: capital_payments_primary | D28: 2021-10-01T00:00:00.000Z | E28: 2022-09-30T00:00:00.000Z | F28: 970000000 | G28: USD | H28: 72 | I28: 0001403161-23-000099 | J28: Visa FY2023 annual report, PDF p72 | K28: =A28&"|"&B28&"|"&C28 -> visa|2022|capital_payments_primary | M28: =_xlfn.XLOOKUP(I28,$I$169:$I$174,$M$169:$M$174,"n.a.",0) -> https://s29.q4cdn.com/385744025/files/doc_downloads/2023/Visa-Inc-Fiscal-2023-Annual-Report.pdf
A29: visa | B29: 2022 | C29: cash_and_cash_equivalents | E29: 2022-09-30T00:00:00.000Z | F29: 15689000000 | G29: USD | H29: 66 | I29: 0001403161-23-000099 | J29: Visa FY2023 annual report, PDF p66 | K29: =A29&"|"&B29&"|"&C29 -> visa|2022|cash_and_cash_equivalents | M29: =_xlfn.XLOOKUP(I29,$I$169:$I$174,$M$169:$M$174,"n.a.",0) -> https://s29.q4cdn.com/385744025/files/doc_downloads/2023/Visa-Inc-Fiscal-2023-Annual-Report.pdf
A30: visa | B30: 2022 | C30: current_debt | E30: 2022-09-30T00:00:00.000Z | F30: 2250000000 | G30: USD | H30: 66 | I30: 0001403161-23-000099 | J30: Visa FY2023 annual report, PDF p66 | K30: =A30&"|"&B30&"|"&C30 -> visa|2022|current_debt | M30: =_xlfn.XLOOKUP(I30,$I$169:$I$174,$M$169:$M$174,"n.a.",0) -> https://s29.q4cdn.com/385744025/files/doc_downloads/2023/Visa-Inc-Fiscal-2023-Annual-Report.pdf
A31: visa | B31: 2022 | C31: noncurrent_debt | E31: 2022-09-30T00:00:00.000Z | F31: 20200000000 | G31: USD | H31: 66 | I31: 0001403161-23-000099 | J31: Visa FY2023 annual report, PDF p66 | K31: =A31&"|"&B31&"|"&C31 -> visa|2022|noncurrent_debt | M31: =_xlfn.XLOOKUP(I31,$I$169:$I$174,$M$169:$M$174,"n.a.",0) -> https://s29.q4cdn.com/385744025/files/doc_downloads/2023/Visa-Inc-Fiscal-2023-Annual-Report.pdf
A32: visa | B32: 2022 | C32: total_assets | E32: 2022-09-30T00:00:00.000Z | F32: 85501000000 | G32: USD | H32: 66 | I32: 0001403161-23-000099 | J32: Visa FY2023 annual report, PDF p66 | K32: =A32&"|"&B32&"|"&C32 -> visa|2022|total_assets | M32: =_xlfn.XLOOKUP(I32,$I$169:$I$174,$M$169:$M$174,"n.a.",0) -> https://s29.q4cdn.com/385744025/files/doc_downloads/2023/Visa-Inc-Fiscal-2023-Annual-Report.pdf
A33: visa | B33: 2022 | C33: total_liabilities | E33: 2022-09-30T00:00:00.000Z | F33: 49920000000 | G33: USD | H33: 66 | I33: 0001403161-23-000099 | J33: Visa FY2023 annual report, PDF p66 | K33: =A33&"|"&B33&"|"&C33 -> visa|2022|total_liabilities | M33: =_xlfn.XLOOKUP(I33,$I$169:$I$174,$M$169:$M$174,"n.a.",0) -> https://s29.q4cdn.com/385744025/files/doc_downloads/2023/Visa-Inc-Fiscal-2023-Annual-Report.pdf
A34: visa | B34: 2022 | C34: total_equity | E34: 2022-09-30T00:00:00.000Z | F34: 35581000000 | G34: USD | H34: 66 | I34: 0001403161-23-000099 | J34: Visa FY2023 annual report, PDF p66 | K34: =A34&"|"&B34&"|"&C34 -> visa|2022|total_equity | M34: =_xlfn.XLOOKUP(I34,$I$169:$I$174,$M$169:$M$174,"n.a.",0) -> https://s29.q4cdn.com/385744025/files/doc_downloads/2023/Visa-Inc-Fiscal-2023-Annual-Report.pdf
A35: visa | B35: 2022 | C35: cash_flow_total_end | E35: 2022-09-30T00:00:00.000Z | F35: 20377000000 | G35: USD | H35: 72 | I35: 0001403161-23-000099 | J35: Visa FY2023 annual report, PDF p72 | K35: =A35&"|"&B35&"|"&C35 -> visa|2022|cash_flow_total_end | M35: =_xlfn.XLOOKUP(I35,$I$169:$I$174,$M$169:$M$174,"n.a.",0) -> https://s29.q4cdn.com/385744025/files/doc_downloads/2023/Visa-Inc-Fiscal-2023-Annual-Report.pdf
A36: visa | B36: 2023 | C36: net_revenue | D36: 2022-10-01T00:00:00.000Z | E36: 2023-09-30T00:00:00.000Z | F36: 32653000000 | G36: USD | H36: 75 | I36: 0001403161-25-000089 | J36: Visa FY2025 annual report, PDF p75 | K36: =A36&"|"&B36&"|"&C36 -> visa|2023|net_revenue | M36: =_xlfn.XLOOKUP(I36,$I$169:$I$174,$M$169:$M$174,"n.a.",0) -> https://s29.q4cdn.com/385744025/files/doc_downloads/2025/Visa-Fiscal-2025-Annual-Report.pdf
A37: visa | B37: 2023 | C37: operating_expenses | D37: 2022-10-01T00:00:00.000Z | E37: 2023-09-30T00:00:00.000Z | F37: 11653000000 | G37: USD | H37: 75 | I37: 0001403161-25-000089 | J37: Visa FY2025 annual report, PDF p75 | K37: =A37&"|"&B37&"|"&C37 -> visa|2023|operating_expenses | M37: =_xlfn.XLOOKUP(I37,$I$169:$I$174,$M$169:$M$174,"n.a.",0) -> https://s29.q4cdn.com/385744025/files/doc_downloads/2025/Visa-Fiscal-2025-Annual-Report.pdf
A38: visa | B38: 2023 | C38: operating_income | D38: 2022-10-01T00:00:00.000Z | E38: 2023-09-30T00:00:00.000Z | F38: 21000000000 | G38: USD | H38: 75 | I38: 0001403161-25-000089 | J38: Visa FY2025 annual report, PDF p75 | K38: =A38&"|"&B38&"|"&C38 -> visa|2023|operating_income | M38: =_xlfn.XLOOKUP(I38,$I$169:$I$174,$M$169:$M$174,"n.a.",0) -> https://s29.q4cdn.com/385744025/files/doc_downloads/2025/Visa-Fiscal-2025-Annual-Report.pdf
A39: visa | B39: 2023 | C39: pretax_income | D39: 2022-10-01T00:00:00.000Z | E39: 2023-09-30T00:00:00.000Z | F39: 21037000000 | G39: USD | H39: 75 | I39: 0001403161-25-000089 | J39: Visa FY2025 annual report, PDF p75 | K39: =A39&"|"&B39&"|"&C39 -> visa|2023|pretax_income | M39: =_xlfn.XLOOKUP(I39,$I$169:$I$174,$M$169:$M$174,"n.a.",0) -> https://s29.q4cdn.com/385744025/files/doc_downloads/2025/Visa-Fiscal-2025-Annual-Report.pdf
A40: visa | B40: 2023 | C40: income_tax | D40: 2022-10-01T00:00:00.000Z | E40: 2023-09-30T00:00:00.000Z | F40: 3764000000 | G40: USD | H40: 75 | I40: 0001403161-25-000089 | J40: Visa FY2025 annual report, PDF p75 | K40: =A40&"|"&B40&"|"&C40 -> visa|2023|income_tax | M40: =_xlfn.XLOOKUP(I40,$I$169:$I$174,$M$169:$M$174,"n.a.",0) -> https://s29.q4cdn.com/385744025/files/doc_downloads/2025/Visa-Fiscal-2025-Annual-Report.pdf
A41: visa | B41: 2023 | C41: net_income | D41: 2022-10-01T00:00:00.000Z | E41: 2023-09-30T00:00:00.000Z | F41: 17273000000 | G41: USD | H41: 75 | I41: 0001403161-25-000089 | J41: Visa FY2025 annual report, PDF p75 | K41: =A41&"|"&B41&"|"&C41 -> visa|2023|net_income | M41: =_xlfn.XLOOKUP(I41,$I$169:$I$174,$M$169:$M$174,"n.a.",0) -> https://s29.q4cdn.com/385744025/files/doc_downloads/2025/Visa-Fiscal-2025-Annual-Report.pdf
A42: visa | B42: 2023 | C42: operating_cash_flow | D42: 2022-10-01T00:00:00.000Z | E42: 2023-09-30T00:00:00.000Z | F42: 20755000000 | G42: USD | H42: 80 | I42: 0001403161-25-000089 | J42: Visa FY2025 annual report, PDF p80 | K42: =A42&"|"&B42&"|"&C42 -> visa|2023|operating_cash_flow | M42: =_xlfn.XLOOKUP(I42,$I$169:$I$174,$M$169:$M$174,"n.a.",0) -> https://s29.q4cdn.com/385744025/files/doc_downloads/2025/Visa-Fiscal-2025-Annual-Report.pdf
A43: visa | B43: 2023 | C43: capital_payments_primary | D43: 2022-10-01T00:00:00.000Z | E43: 2023-09-30T00:00:00.000Z | F43: 1059000000 | G43: USD | H43: 80 | I43: 0001403161-25-000089 | J43: Visa FY2025 annual report, PDF p80 | K43: =A43&"|"&B43&"|"&C43 -> visa|2023|capital_payments_primary | M43: =_xlfn.XLOOKUP(I43,$I$169:$I$174,$M$169:$M$174,"n.a.",0) -> https://s29.q4cdn.com/385744025/files/doc_downloads/2025/Visa-Fiscal-2025-Annual-Report.pdf
A44: visa | B44: 2023 | C44: cash_and_cash_equivalents | E44: 2023-09-30T00:00:00.000Z | F44: 16286000000 | G44: USD | H44: 66 | I44: 0001403161-23-000099 | J44: Visa FY2023 annual report, PDF p66 | K44: =A44&"|"&B44&"|"&C44 -> visa|2023|cash_and_cash_equivalents | M44: =_xlfn.XLOOKUP(I44,$I$169:$I$174,$M$169:$M$174,"n.a.",0) -> https://s29.q4cdn.com/385744025/files/doc_downloads/2023/Visa-Inc-Fiscal-2023-Annual-Report.pdf
A45: visa | B45: 2023 | C45: current_debt | E45: 2023-09-30T00:00:00.000Z | F45: 0 | G45: USD | H45: 66 | I45: 0001403161-23-000099 | J45: Visa FY2023 annual report, PDF p66 | K45: =A45&"|"&B45&"|"&C45 -> visa|2023|current_debt | M45: =_xlfn.XLOOKUP(I45,$I$169:$I$174,$M$169:$M$174,"n.a.",0) -> https://s29.q4cdn.com/385744025/files/doc_downloads/2023/Visa-Inc-Fiscal-2023-Annual-Report.pdf
A46: visa | B46: 2023 | C46: noncurrent_debt | E46: 2023-09-30T00:00:00.000Z | F46: 20463000000 | G46: USD | H46: 66 | I46: 0001403161-23-000099 | J46: Visa FY2023 annual report, PDF p66 | K46: =A46&"|"&B46&"|"&C46 -> visa|2023|noncurrent_debt | M46: =_xlfn.XLOOKUP(I46,$I$169:$I$174,$M$169:$M$174,"n.a.",0) -> https://s29.q4cdn.com/385744025/files/doc_downloads/2023/Visa-Inc-Fiscal-2023-Annual-Report.pdf
A47: visa | B47: 2023 | C47: total_assets | E47: 2023-09-30T00:00:00.000Z | F47: 90499000000 | G47: USD | H47: 66 | I47: 0001403161-23-000099 | J47: Visa FY2023 annual report, PDF p66 | K47: =A47&"|"&B47&"|"&C47 -> visa|2023|total_assets | M47: =_xlfn.XLOOKUP(I47,$I$169:$I$174,$M$169:$M$174,"n.a.",0) -> https://s29.q4cdn.com/385744025/files/doc_downloads/2023/Visa-Inc-Fiscal-2023-Annual-Report.pdf
A48: visa | B48: 2023 | C48: total_liabilities | E48: 2023-09-30T00:00:00.000Z | F48: 51766000000 | G48: USD | H48: 66 | I48: 0001403161-23-000099 | J48: Visa FY2023 annual report, PDF p66 | K48: =A48&"|"&B48&"|"&C48 -> visa|2023|total_liabilities | M48: =_xlfn.XLOOKUP(I48,$I$169:$I$174,$M$169:$M$174,"n.a.",0) -> https://s29.q4cdn.com/385744025/files/doc_downloads/2023/Visa-Inc-Fiscal-2023-Annual-Report.pdf
A49: visa | B49: 2023 | C49: total_equity | E49: 2023-09-30T00:00:00.000Z | F49: 38733000000 | G49: USD | H49: 66 | I49: 0001403161-23-000099 | J49: Visa FY2023 annual report, PDF p66 | K49: =A49&"|"&B49&"|"&C49 -> visa|2023|total_equity | M49: =_xlfn.XLOOKUP(I49,$I$169:$I$174,$M$169:$M$174,"n.a.",0) -> https://s29.q4cdn.com/385744025/files/doc_downloads/2023/Visa-Inc-Fiscal-2023-Annual-Report.pdf
A50: visa | B50: 2023 | C50: cash_flow_total_end | E50: 2023-09-30T00:00:00.000Z | F50: 21990000000 | G50: USD | H50: 80 | I50: 0001403161-25-000089 | J50: Visa FY2025 annual report, PDF p80 | K50: =A50&"|"&B50&"|"&C50 -> visa|2023|cash_flow_total_end | M50: =_xlfn.XLOOKUP(I50,$I$169:$I$174,$M$169:$M$174,"n.a.",0) -> https://s29.q4cdn.com/385744025/files/doc_downloads/2025/Visa-Fiscal-2025-Annual-Report.pdf
A51: visa | B51: 2024 | C51: net_revenue | D51: 2023-10-01T00:00:00.000Z | E51: 2024-09-30T00:00:00.000Z | F51: 35926000000 | G51: USD | H51: 75 | I51: 0001403161-25-000089 | J51: Visa FY2025 annual report, PDF p75 | K51: =A51&"|"&B51&"|"&C51 -> visa|2024|net_revenue | M51: =_xlfn.XLOOKUP(I51,$I$169:$I$174,$M$169:$M$174,"n.a.",0) -> https://s29.q4cdn.com/385744025/files/doc_downloads/2025/Visa-Fiscal-2025-Annual-Report.pdf
A52: visa | B52: 2024 | C52: operating_expenses | D52: 2023-10-01T00:00:00.000Z | E52: 2024-09-30T00:00:00.000Z | F52: 12331000000 | G52: USD | H52: 75 | I52: 0001403161-25-000089 | J52: Visa FY2025 annual report, PDF p75 | K52: =A52&"|"&B52&"|"&C52 -> visa|2024|operating_expenses | M52: =_xlfn.XLOOKUP(I52,$I$169:$I$174,$M$169:$M$174,"n.a.",0) -> https://s29.q4cdn.com/385744025/files/doc_downloads/2025/Visa-Fiscal-2025-Annual-Report.pdf
A53: visa | B53: 2024 | C53: operating_income | D53: 2023-10-01T00:00:00.000Z | E53: 2024-09-30T00:00:00.000Z | F53: 23595000000 | G53: USD | H53: 75 | I53: 0001403161-25-000089 | J53: Visa FY2025 annual report, PDF p75 | K53: =A53&"|"&B53&"|"&C53 -> visa|2024|operating_income | M53: =_xlfn.XLOOKUP(I53,$I$169:$I$174,$M$169:$M$174,"n.a.",0) -> https://s29.q4cdn.com/385744025/files/doc_downloads/2025/Visa-Fiscal-2025-Annual-Report.pdf
A54: visa | B54: 2024 | C54: pretax_income | D54: 2023-10-01T00:00:00.000Z | E54: 2024-09-30T00:00:00.000Z | F54: 23916000000 | G54: USD | H54: 75 | I54: 0001403161-25-000089 | J54: Visa FY2025 annual report, PDF p75 | K54: =A54&"|"&B54&"|"&C54 -> visa|2024|pretax_income | M54: =_xlfn.XLOOKUP(I54,$I$169:$I$174,$M$169:$M$174,"n.a.",0) -> https://s29.q4cdn.com/385744025/files/doc_downloads/2025/Visa-Fiscal-2025-Annual-Report.pdf
A55: visa | B55: 2024 | C55: income_tax | D55: 2023-10-01T00:00:00.000Z | E55: 2024-09-30T00:00:00.000Z | F55: 4173000000 | G55: USD | H55: 75 | I55: 0001403161-25-000089 | J55: Visa FY2025 annual report, PDF p75 | K55: =A55&"|"&B55&"|"&C55 -> visa|2024|income_tax | M55: =_xlfn.XLOOKUP(I55,$I$169:$I$174,$M$169:$M$174,"n.a.",0) -> https://s29.q4cdn.com/385744025/files/doc_downloads/2025/Visa-Fiscal-2025-Annual-Report.pdf
A56: visa | B56: 2024 | C56: net_income | D56: 2023-10-01T00:00:00.000Z | E56: 2024-09-30T00:00:00.000Z | F56: 19743000000 | G56: USD | H56: 75 | I56: 0001403161-25-000089 | J56: Visa FY2025 annual report, PDF p75 | K56: =A56&"|"&B56&"|"&C56 -> visa|2024|net_income | M56: =_xlfn.XLOOKUP(I56,$I$169:$I$174,$M$169:$M$174,"n.a.",0) -> https://s29.q4cdn.com/385744025/files/doc_downloads/2025/Visa-Fiscal-2025-Annual-Report.pdf
A57: visa | B57: 2024 | C57: operating_cash_flow | D57: 2023-10-01T00:00:00.000Z | E57: 2024-09-30T00:00:00.000Z | F57: 19950000000 | G57: USD | H57: 80 | I57: 0001403161-25-000089 | J57: Visa FY2025 annual report, PDF p80 | K57: =A57&"|"&B57&"|"&C57 -> visa|2024|operating_cash_flow | M57: =_xlfn.XLOOKUP(I57,$I$169:$I$174,$M$169:$M$174,"n.a.",0) -> https://s29.q4cdn.com/385744025/files/doc_downloads/2025/Visa-Fiscal-2025-Annual-Report.pdf
A58: visa | B58: 2024 | C58: capital_payments_primary | D58: 2023-10-01T00:00:00.000Z | E58: 2024-09-30T00:00:00.000Z | F58: 1257000000 | G58: USD | H58: 80 | I58: 0001403161-25-000089 | J58: Visa FY2025 annual report, PDF p80 | K58: =A58&"|"&B58&"|"&C58 -> visa|2024|capital_payments_primary | M58: =_xlfn.XLOOKUP(I58,$I$169:$I$174,$M$169:$M$174,"n.a.",0) -> https://s29.q4cdn.com/385744025/files/doc_downloads/2025/Visa-Fiscal-2025-Annual-Report.pdf
A59: visa | B59: 2024 | C59: cash_and_cash_equivalents | E59: 2024-09-30T00:00:00.000Z | F59: 11975000000 | G59: USD | H59: 74 | I59: 0001403161-25-000089 | J59: Visa FY2025 annual report, PDF p74 | K59: =A59&"|"&B59&"|"&C59 -> visa|2024|cash_and_cash_equivalents | M59: =_xlfn.XLOOKUP(I59,$I$169:$I$174,$M$169:$M$174,"n.a.",0) -> https://s29.q4cdn.com/385744025/files/doc_downloads/2025/Visa-Fiscal-2025-Annual-Report.pdf
A60: visa | B60: 2024 | C60: current_debt | E60: 2024-09-30T00:00:00.000Z | F60: 0 | G60: USD | H60: 74 | I60: 0001403161-25-000089 | J60: Visa FY2025 annual report, PDF p74 | K60: =A60&"|"&B60&"|"&C60 -> visa|2024|current_debt | M60: =_xlfn.XLOOKUP(I60,$I$169:$I$174,$M$169:$M$174,"n.a.",0) -> https://s29.q4cdn.com/385744025/files/doc_downloads/2025/Visa-Fiscal-2025-Annual-Report.pdf
A61: visa | B61: 2024 | C61: noncurrent_debt | E61: 2024-09-30T00:00:00.000Z | F61: 20836000000 | G61: USD | H61: 74 | I61: 0001403161-25-000089 | J61: Visa FY2025 annual report, PDF p74 | K61: =A61&"|"&B61&"|"&C61 -> visa|2024|noncurrent_debt | M61: =_xlfn.XLOOKUP(I61,$I$169:$I$174,$M$169:$M$174,"n.a.",0) -> https://s29.q4cdn.com/385744025/files/doc_downloads/2025/Visa-Fiscal-2025-Annual-Report.pdf
A62: visa | B62: 2024 | C62: total_assets | E62: 2024-09-30T00:00:00.000Z | F62: 94511000000 | G62: USD | H62: 74 | I62: 0001403161-25-000089 | J62: Visa FY2025 annual report, PDF p74 | K62: =A62&"|"&B62&"|"&C62 -> visa|2024|total_assets | M62: =_xlfn.XLOOKUP(I62,$I$169:$I$174,$M$169:$M$174,"n.a.",0) -> https://s29.q4cdn.com/385744025/files/doc_downloads/2025/Visa-Fiscal-2025-Annual-Report.pdf
A63: visa | B63: 2024 | C63: total_liabilities | E63: 2024-09-30T00:00:00.000Z | F63: 55374000000 | G63: USD | H63: 74 | I63: 0001403161-25-000089 | J63: Visa FY2025 annual report, PDF p74 | K63: =A63&"|"&B63&"|"&C63 -> visa|2024|total_liabilities | M63: =_xlfn.XLOOKUP(I63,$I$169:$I$174,$M$169:$M$174,"n.a.",0) -> https://s29.q4cdn.com/385744025/files/doc_downloads/2025/Visa-Fiscal-2025-Annual-Report.pdf
A64: visa | B64: 2024 | C64: total_equity | E64: 2024-09-30T00:00:00.000Z | F64: 39137000000 | G64: USD | H64: 74 | I64: 0001403161-25-000089 | J64: Visa FY2025 annual report, PDF p74 | K64: =A64&"|"&B64&"|"&C64 -> visa|2024|total_equity | M64: =_xlfn.XLOOKUP(I64,$I$169:$I$174,$M$169:$M$174,"n.a.",0) -> https://s29.q4cdn.com/385744025/files/doc_downloads/2025/Visa-Fiscal-2025-Annual-Report.pdf
A65: visa | B65: 2024 | C65: cash_flow_total_end | E65: 2024-09-30T00:00:00.000Z | F65: 19763000000 | G65: USD | H65: 80 | I65: 0001403161-25-000089 | J65: Visa FY2025 annual report, PDF p80 | K65: =A65&"|"&B65&"|"&C65 -> visa|2024|cash_flow_total_end | M65: =_xlfn.XLOOKUP(I65,$I$169:$I$174,$M$169:$M$174,"n.a.",0) -> https://s29.q4cdn.com/385744025/files/doc_downloads/2025/Visa-Fiscal-2025-Annual-Report.pdf
A66: visa | B66: 2025 | C66: net_revenue | D66: 2024-10-01T00:00:00.000Z | E66: 2025-09-30T00:00:00.000Z | F66: 40000000000 | G66: USD | H66: 75 | I66: 0001403161-25-000089 | J66: Visa FY2025 annual report, PDF p75 | K66: =A66&"|"&B66&"|"&C66 -> visa|2025|net_revenue | M66: =_xlfn.XLOOKUP(I66,$I$169:$I$174,$M$169:$M$174,"n.a.",0) -> https://s29.q4cdn.com/385744025/files/doc_downloads/2025/Visa-Fiscal-2025-Annual-Report.pdf
A67: visa | B67: 2025 | C67: operating_expenses | D67: 2024-10-01T00:00:00.000Z | E67: 2025-09-30T00:00:00.000Z | F67: 16006000000 | G67: USD | H67: 75 | I67: 0001403161-25-000089 | J67: Visa FY2025 annual report, PDF p75 | K67: =A67&"|"&B67&"|"&C67 -> visa|2025|operating_expenses | M67: =_xlfn.XLOOKUP(I67,$I$169:$I$174,$M$169:$M$174,"n.a.",0) -> https://s29.q4cdn.com/385744025/files/doc_downloads/2025/Visa-Fiscal-2025-Annual-Report.pdf
A68: visa | B68: 2025 | C68: operating_income | D68: 2024-10-01T00:00:00.000Z | E68: 2025-09-30T00:00:00.000Z | F68: 23994000000 | G68: USD | H68: 75 | I68: 0001403161-25-000089 | J68: Visa FY2025 annual report, PDF p75 | K68: =A68&"|"&B68&"|"&C68 -> visa|2025|operating_income | M68: =_xlfn.XLOOKUP(I68,$I$169:$I$174,$M$169:$M$174,"n.a.",0) -> https://s29.q4cdn.com/385744025/files/doc_downloads/2025/Visa-Fiscal-2025-Annual-Report.pdf
A69: visa | B69: 2025 | C69: pretax_income | D69: 2024-10-01T00:00:00.000Z | E69: 2025-09-30T00:00:00.000Z | F69: 24194000000 | G69: USD | H69: 75 | I69: 0001403161-25-000089 | J69: Visa FY2025 annual report, PDF p75 | K69: =A69&"|"&B69&"|"&C69 -> visa|2025|pretax_income | M69: =_xlfn.XLOOKUP(I69,$I$169:$I$174,$M$169:$M$174,"n.a.",0) -> https://s29.q4cdn.com/385744025/files/doc_downloads/2025/Visa-Fiscal-2025-Annual-Report.pdf
A70: visa | B70: 2025 | C70: income_tax | D70: 2024-10-01T00:00:00.000Z | E70: 2025-09-30T00:00:00.000Z | F70: 4136000000 | G70: USD | H70: 75 | I70: 0001403161-25-000089 | J70: Visa FY2025 annual report, PDF p75 | K70: =A70&"|"&B70&"|"&C70 -> visa|2025|income_tax | M70: =_xlfn.XLOOKUP(I70,$I$169:$I$174,$M$169:$M$174,"n.a.",0) -> https://s29.q4cdn.com/385744025/files/doc_downloads/2025/Visa-Fiscal-2025-Annual-Report.pdf
A71: visa | B71: 2025 | C71: net_income | D71: 2024-10-01T00:00:00.000Z | E71: 2025-09-30T00:00:00.000Z | F71: 20058000000 | G71: USD | H71: 75 | I71: 0001403161-25-000089 | J71: Visa FY2025 annual report, PDF p75 | K71: =A71&"|"&B71&"|"&C71 -> visa|2025|net_income | M71: =_xlfn.XLOOKUP(I71,$I$169:$I$174,$M$169:$M$174,"n.a.",0) -> https://s29.q4cdn.com/385744025/files/doc_downloads/2025/Visa-Fiscal-2025-Annual-Report.pdf
A72: visa | B72: 2025 | C72: operating_cash_flow | D72: 2024-10-01T00:00:00.000Z | E72: 2025-09-30T00:00:00.000Z | F72: 23059000000 | G72: USD | H72: 80 | I72: 0001403161-25-000089 | J72: Visa FY2025 annual report, PDF p80 | K72: =A72&"|"&B72&"|"&C72 -> visa|2025|operating_cash_flow | M72: =_xlfn.XLOOKUP(I72,$I$169:$I$174,$M$169:$M$174,"n.a.",0) -> https://s29.q4cdn.com/385744025/files/doc_downloads/2025/Visa-Fiscal-2025-Annual-Report.pdf
A73: visa | B73: 2025 | C73: capital_payments_primary | D73: 2024-10-01T00:00:00.000Z | E73: 2025-09-30T00:00:00.000Z | F73: 1482000000 | G73: USD | H73: 80 | I73: 0001403161-25-000089 | J73: Visa FY2025 annual report, PDF p80 | K73: =A73&"|"&B73&"|"&C73 -> visa|2025|capital_payments_primary | M73: =_xlfn.XLOOKUP(I73,$I$169:$I$174,$M$169:$M$174,"n.a.",0) -> https://s29.q4cdn.com/385744025/files/doc_downloads/2025/Visa-Fiscal-2025-Annual-Report.pdf
A74: visa | B74: 2025 | C74: cash_and_cash_equivalents | E74: 2025-09-30T00:00:00.000Z | F74: 17164000000 | G74: USD | H74: 74 | I74: 0001403161-25-000089 | J74: Visa FY2025 annual report, PDF p74 | K74: =A74&"|"&B74&"|"&C74 -> visa|2025|cash_and_cash_equivalents | M74: =_xlfn.XLOOKUP(I74,$I$169:$I$174,$M$169:$M$174,"n.a.",0) -> https://s29.q4cdn.com/385744025/files/doc_downloads/2025/Visa-Fiscal-2025-Annual-Report.pdf
A75: visa | B75: 2025 | C75: current_debt | E75: 2025-09-30T00:00:00.000Z | F75: 5569000000 | G75: USD | H75: 74 | I75: 0001403161-25-000089 | J75: Visa FY2025 annual report, PDF p74 | K75: =A75&"|"&B75&"|"&C75 -> visa|2025|current_debt | M75: =_xlfn.XLOOKUP(I75,$I$169:$I$174,$M$169:$M$174,"n.a.",0) -> https://s29.q4cdn.com/385744025/files/doc_downloads/2025/Visa-Fiscal-2025-Annual-Report.pdf
A76: visa | B76: 2025 | C76: noncurrent_debt | E76: 2025-09-30T00:00:00.000Z | F76: 19602000000 | G76: USD | H76: 74 | I76: 0001403161-25-000089 | J76: Visa FY2025 annual report, PDF p74 | K76: =A76&"|"&B76&"|"&C76 -> visa|2025|noncurrent_debt | M76: =_xlfn.XLOOKUP(I76,$I$169:$I$174,$M$169:$M$174,"n.a.",0) -> https://s29.q4cdn.com/385744025/files/doc_downloads/2025/Visa-Fiscal-2025-Annual-Report.pdf
A77: visa | B77: 2025 | C77: total_assets | E77: 2025-09-30T00:00:00.000Z | F77: 99627000000 | G77: USD | H77: 74 | I77: 0001403161-25-000089 | J77: Visa FY2025 annual report, PDF p74 | K77: =A77&"|"&B77&"|"&C77 -> visa|2025|total_assets | M77: =_xlfn.XLOOKUP(I77,$I$169:$I$174,$M$169:$M$174,"n.a.",0) -> https://s29.q4cdn.com/385744025/files/doc_downloads/2025/Visa-Fiscal-2025-Annual-Report.pdf
A78: visa | B78: 2025 | C78: total_liabilities | E78: 2025-09-30T00:00:00.000Z | F78: 61718000000 | G78: USD | H78: 74 | I78: 0001403161-25-000089 | J78: Visa FY2025 annual report, PDF p74 | K78: =A78&"|"&B78&"|"&C78 -> visa|2025|total_liabilities | M78: =_xlfn.XLOOKUP(I78,$I$169:$I$174,$M$169:$M$174,"n.a.",0) -> https://s29.q4cdn.com/385744025/files/doc_downloads/2025/Visa-Fiscal-2025-Annual-Report.pdf
A79: visa | B79: 2025 | C79: total_equity | E79: 2025-09-30T00:00:00.000Z | F79: 37909000000 | G79: USD | H79: 74 | I79: 0001403161-25-000089 | J79: Visa FY2025 annual report, PDF p74 | K79: =A79&"|"&B79&"|"&C79 -> visa|2025|total_equity | M79: =_xlfn.XLOOKUP(I79,$I$169:$I$174,$M$169:$M$174,"n.a.",0) -> https://s29.q4cdn.com/385744025/files/doc_downloads/2025/Visa-Fiscal-2025-Annual-Report.pdf
A80: visa | B80: 2025 | C80: cash_flow_total_end | E80: 2025-09-30T00:00:00.000Z | F80: 24987000000 | G80: USD | H80: 80 | I80: 0001403161-25-000089 | J80: Visa FY2025 annual report, PDF p80 | K80: =A80&"|"&B80&"|"&C80 -> visa|2025|cash_flow_total_end | M80: =_xlfn.XLOOKUP(I80,$I$169:$I$174,$M$169:$M$174,"n.a.",0) -> https://s29.q4cdn.com/385744025/files/doc_downloads/2025/Visa-Fiscal-2025-Annual-Report.pdf
A81: mastercard | B81: 2021 | C81: net_revenue | D81: 2021-01-01T00:00:00.000Z | E81: 2021-12-31T00:00:00.000Z | F81: 18884000000 | G81: USD | H81: 69 | I81: 0001141391-24-000022 | J81: Mastercard FY2023 annual report, PDF p69 | K81: =A81&"|"&B81&"|"&C81 -> mastercard|2021|net_revenue | M81: =_xlfn.XLOOKUP(I81,$I$169:$I$174,$M$169:$M$174,"n.a.",0) -> https://s25.q4cdn.com/479285134/files/doc_financials/2023/AR/2023-annual-report.pdf
A82: mastercard | B82: 2021 | C82: operating_expenses | D82: 2021-01-01T00:00:00.000Z | E82: 2021-12-31T00:00:00.000Z | F82: 8802000000 | G82: USD | H82: 69 | I82: 0001141391-24-000022 | J82: Mastercard FY2023 annual report, PDF p69 | K82: =A82&"|"&B82&"|"&C82 -> mastercard|2021|operating_expenses | M82: =_xlfn.XLOOKUP(I82,$I$169:$I$174,$M$169:$M$174,"n.a.",0) -> https://s25.q4cdn.com/479285134/files/doc_financials/2023/AR/2023-annual-report.pdf
A83: mastercard | B83: 2021 | C83: operating_income | D83: 2021-01-01T00:00:00.000Z | E83: 2021-12-31T00:00:00.000Z | F83: 10082000000 | G83: USD | H83: 69 | I83: 0001141391-24-000022 | J83: Mastercard FY2023 annual report, PDF p69 | K83: =A83&"|"&B83&"|"&C83 -> mastercard|2021|operating_income | M83: =_xlfn.XLOOKUP(I83,$I$169:$I$174,$M$169:$M$174,"n.a.",0) -> https://s25.q4cdn.com/479285134/files/doc_financials/2023/AR/2023-annual-report.pdf
A84: mastercard | B84: 2021 | C84: pretax_income | D84: 2021-01-01T00:00:00.000Z | E84: 2021-12-31T00:00:00.000Z | F84: 10307000000 | G84: USD | H84: 69 | I84: 0001141391-24-000022 | J84: Mastercard FY2023 annual report, PDF p69 | K84: =A84&"|"&B84&"|"&C84 -> mastercard|2021|pretax_income | M84: =_xlfn.XLOOKUP(I84,$I$169:$I$174,$M$169:$M$174,"n.a.",0) -> https://s25.q4cdn.com/479285134/files/doc_financials/2023/AR/2023-annual-report.pdf
A85: mastercard | B85: 2021 | C85: income_tax | D85: 2021-01-01T00:00:00.000Z | E85: 2021-12-31T00:00:00.000Z | F85: 1620000000 | G85: USD | H85: 69 | I85: 0001141391-24-000022 | J85: Mastercard FY2023 annual report, PDF p69 | K85: =A85&"|"&B85&"|"&C85 -> mastercard|2021|income_tax | M85: =_xlfn.XLOOKUP(I85,$I$169:$I$174,$M$169:$M$174,"n.a.",0) -> https://s25.q4cdn.com/479285134/files/doc_financials/2023/AR/2023-annual-report.pdf
A86: mastercard | B86: 2021 | C86: net_income | D86: 2021-01-01T00:00:00.000Z | E86: 2021-12-31T00:00:00.000Z | F86: 8687000000 | G86: USD | H86: 69 | I86: 0001141391-24-000022 | J86: Mastercard FY2023 annual report, PDF p69 | K86: =A86&"|"&B86&"|"&C86 -> mastercard|2021|net_income | M86: =_xlfn.XLOOKUP(I86,$I$169:$I$174,$M$169:$M$174,"n.a.",0) -> https://s25.q4cdn.com/479285134/files/doc_financials/2023/AR/2023-annual-report.pdf
A87: mastercard | B87: 2021 | C87: operating_cash_flow | D87: 2021-01-01T00:00:00.000Z | E87: 2021-12-31T00:00:00.000Z | F87: 9463000000 | G87: USD | H87: 74 | I87: 0001141391-24-000022 | J87: Mastercard FY2023 annual report, PDF p74 | K87: =A87&"|"&B87&"|"&C87 -> mastercard|2021|operating_cash_flow | M87: =_xlfn.XLOOKUP(I87,$I$169:$I$174,$M$169:$M$174,"n.a.",0) -> https://s25.q4cdn.com/479285134/files/doc_financials/2023/AR/2023-annual-report.pdf
A88: mastercard | B88: 2021 | C88: capital_payments_primary | D88: 2021-01-01T00:00:00.000Z | E88: 2021-12-31T00:00:00.000Z | F88: 407000000 | G88: USD | H88: 74 | I88: 0001141391-24-000022 | J88: Mastercard FY2023 annual report, PDF p74 | K88: =A88&"|"&B88&"|"&C88 -> mastercard|2021|capital_payments_primary | M88: =_xlfn.XLOOKUP(I88,$I$169:$I$174,$M$169:$M$174,"n.a.",0) -> https://s25.q4cdn.com/479285134/files/doc_financials/2023/AR/2023-annual-report.pdf
A89: mastercard | B89: 2021 | C89: cash_and_cash_equivalents | E89: 2021-12-31T00:00:00.000Z | F89: 7421000000 | G89: USD | H89: 65 | I89: 0001141391-22-000023 | J89: Mastercard FY2021 annual report, PDF p65 | K89: =A89&"|"&B89&"|"&C89 -> mastercard|2021|cash_and_cash_equivalents | M89: =_xlfn.XLOOKUP(I89,$I$169:$I$174,$M$169:$M$174,"n.a.",0) -> https://s25.q4cdn.com/479285134/files/doc_financials/2021/q4/MA.12.31.2021-10-K-as-filed-Exhibits.pdf
A90: mastercard | B90: 2021 | C90: current_debt | E90: 2021-12-31T00:00:00.000Z | F90: 792000000 | G90: USD | H90: 65 | I90: 0001141391-22-000023 | J90: Mastercard FY2021 annual report, PDF p65 | K90: =A90&"|"&B90&"|"&C90 -> mastercard|2021|current_debt | M90: =_xlfn.XLOOKUP(I90,$I$169:$I$174,$M$169:$M$174,"n.a.",0) -> https://s25.q4cdn.com/479285134/files/doc_financials/2021/q4/MA.12.31.2021-10-K-as-filed-Exhibits.pdf
A91: mastercard | B91: 2021 | C91: noncurrent_debt | E91: 2021-12-31T00:00:00.000Z | F91: 13109000000 | G91: USD | H91: 65 | I91: 0001141391-22-000023 | J91: Mastercard FY2021 annual report, PDF p65 | K91: =A91&"|"&B91&"|"&C91 -> mastercard|2021|noncurrent_debt | M91: =_xlfn.XLOOKUP(I91,$I$169:$I$174,$M$169:$M$174,"n.a.",0) -> https://s25.q4cdn.com/479285134/files/doc_financials/2021/q4/MA.12.31.2021-10-K-as-filed-Exhibits.pdf
A92: mastercard | B92: 2021 | C92: total_assets | E92: 2021-12-31T00:00:00.000Z | F92: 37669000000 | G92: USD | H92: 65 | I92: 0001141391-22-000023 | J92: Mastercard FY2021 annual report, PDF p65 | K92: =A92&"|"&B92&"|"&C92 -> mastercard|2021|total_assets | M92: =_xlfn.XLOOKUP(I92,$I$169:$I$174,$M$169:$M$174,"n.a.",0) -> https://s25.q4cdn.com/479285134/files/doc_financials/2021/q4/MA.12.31.2021-10-K-as-filed-Exhibits.pdf
A93: mastercard | B93: 2021 | C93: total_liabilities | E93: 2021-12-31T00:00:00.000Z | F93: 30257000000 | G93: USD | H93: 65 | I93: 0001141391-22-000023 | J93: Mastercard FY2021 annual report, PDF p65 | K93: =A93&"|"&B93&"|"&C93 -> mastercard|2021|total_liabilities | M93: =_xlfn.XLOOKUP(I93,$I$169:$I$174,$M$169:$M$174,"n.a.",0) -> https://s25.q4cdn.com/479285134/files/doc_financials/2021/q4/MA.12.31.2021-10-K-as-filed-Exhibits.pdf
A94: mastercard | B94: 2021 | C94: total_equity | E94: 2021-12-31T00:00:00.000Z | F94: 7383000000 | G94: USD | H94: 65 | I94: 0001141391-22-000023 | J94: Mastercard FY2021 annual report, PDF p65 | K94: =A94&"|"&B94&"|"&C94 -> mastercard|2021|total_equity | M94: =_xlfn.XLOOKUP(I94,$I$169:$I$174,$M$169:$M$174,"n.a.",0) -> https://s25.q4cdn.com/479285134/files/doc_financials/2021/q4/MA.12.31.2021-10-K-as-filed-Exhibits.pdf
A95: mastercard | B95: 2021 | C95: cash_flow_total_end | E95: 2021-12-31T00:00:00.000Z | F95: 9902000000 | G95: USD | H95: 74 | I95: 0001141391-24-000022 | J95: Mastercard FY2023 annual report, PDF p74 | K95: =A95&"|"&B95&"|"&C95 -> mastercard|2021|cash_flow_total_end | M95: =_xlfn.XLOOKUP(I95,$I$169:$I$174,$M$169:$M$174,"n.a.",0) -> https://s25.q4cdn.com/479285134/files/doc_financials/2023/AR/2023-annual-report.pdf
A96: mastercard | B96: 2021 | C96: capitalized_software_payments | D96: 2021-01-01T00:00:00.000Z | E96: 2021-12-31T00:00:00.000Z | F96: 407000000 | G96: USD | H96: 74 | I96: 0001141391-24-000022 | J96: Mastercard FY2023 annual report, PDF p74 | K96: =A96&"|"&B96&"|"&C96 -> mastercard|2021|capitalized_software_payments | M96: =_xlfn.XLOOKUP(I96,$I$169:$I$174,$M$169:$M$174,"n.a.",0) -> https://s25.q4cdn.com/479285134/files/doc_financials/2023/AR/2023-annual-report.pdf
A97: mastercard | B97: 2021 | C97: redeemable_noncontrolling_interests | E97: 2021-12-31T00:00:00.000Z | F97: 29000000 | G97: USD | H97: 65 | I97: 0001141391-22-000023 | J97: Mastercard FY2021 annual report, PDF p65 | K97: =A97&"|"&B97&"|"&C97 -> mastercard|2021|redeemable_noncontrolling_interests | M97: =_xlfn.XLOOKUP(I97,$I$169:$I$174,$M$169:$M$174,"n.a.",0) -> https://s25.q4cdn.com/479285134/files/doc_financials/2021/q4/MA.12.31.2021-10-K-as-filed-Exhibits.pdf
A98: mastercard | B98: 2022 | C98: net_revenue | D98: 2022-01-01T00:00:00.000Z | E98: 2022-12-31T00:00:00.000Z | F98: 22237000000 | G98: USD | H98: 69 | I98: 0001141391-24-000022 | J98: Mastercard FY2023 annual report, PDF p69 | K98: =A98&"|"&B98&"|"&C98 -> mastercard|2022|net_revenue | M98: =_xlfn.XLOOKUP(I98,$I$169:$I$174,$M$169:$M$174,"n.a.",0) -> https://s25.q4cdn.com/479285134/files/doc_financials/2023/AR/2023-annual-report.pdf
A99: mastercard | B99: 2022 | C99: operating_expenses | D99: 2022-01-01T00:00:00.000Z | E99: 2022-12-31T00:00:00.000Z | F99: 9973000000 | G99: USD | H99: 69 | I99: 0001141391-24-000022 | J99: Mastercard FY2023 annual report, PDF p69 | K99: =A99&"|"&B99&"|"&C99 -> mastercard|2022|operating_expenses | M99: =_xlfn.XLOOKUP(I99,$I$169:$I$174,$M$169:$M$174,"n.a.",0) -> https://s25.q4cdn.com/479285134/files/doc_financials/2023/AR/2023-annual-report.pdf
A100: mastercard | B100: 2022 | C100: operating_income | D100: 2022-01-01T00:00:00.000Z | E100: 2022-12-31T00:00:00.000Z | F100: 12264000000 | G100: USD | H100: 69 | I100: 0001141391-24-000022 | J100: Mastercard FY2023 annual report, PDF p69 | K100: =A100&"|"&B100&"|"&C100 -> mastercard|2022|operating_income | M100: =_xlfn.XLOOKUP(I100,$I$169:$I$174,$M$169:$M$174,"n.a.",0) -> https://s25.q4cdn.com/479285134/files/doc_financials/2023/AR/2023-annual-report.pdf
A101: mastercard | B101: 2022 | C101: pretax_income | D101: 2022-01-01T00:00:00.000Z | E101: 2022-12-31T00:00:00.000Z | F101: 11732000000 | G101: USD | H101: 69 | I101: 0001141391-24-000022 | J101: Mastercard FY2023 annual report, PDF p69 | K101: =A101&"|"&B101&"|"&C101 -> mastercard|2022|pretax_income | M101: =_xlfn.XLOOKUP(I101,$I$169:$I$174,$M$169:$M$174,"n.a.",0) -> https://s25.q4cdn.com/479285134/files/doc_financials/2023/AR/2023-annual-report.pdf
...

Sheet Industry
A2: Payment network operating metrics
A3: Fiscal years retain issuer dates. USD amounts are nominal. Transaction scopes differ.
A5: Issuer | B5: FY | C5: Year end | D5: Purchases USD bn | E5: Network tx m | F5: Deductions USD m | G5: Purchase YoY | H5: Tx YoY | I5: Deduction YoY
A6: Visa | B6: 2021 | C6: 2021-09-30T12:00:00.000Z | D6: 10401 | E6: 164734 | F6: 8367
A7: Visa | B7: 2022 | C7: 2022-09-30T12:00:00.000Z | D7: 11614 | E7: 192530 | F7: 10295 | G7: =D7/D6-1 -> 0.1166234 | H7: =E7/E6-1 -> 0.16873262 | I7: =F7/F6-1 -> 0.23042907
A8: Visa | B8: 2023 | C8: 2023-09-30T12:00:00.000Z | D8: 12338 | E8: 212579 | F8: 12297 | G8: =D8/D7-1 -> 0.062338557 | H8: =E8/E7-1 -> 0.10413442 | I8: =F8/F7-1 -> 0.19446333
A9: Visa | B9: 2024 | C9: 2024-09-30T12:00:00.000Z | D9: 13193 | E9: 233758 | F9: 13764 | G9: =D9/D8-1 -> 0.069298103 | H9: =E9/E8-1 -> 0.099628844 | I9: =F9/F8-1 -> 0.11929739
A10: Visa | B10: 2025 | C10: 2025-09-30T12:00:00.000Z | D10: 14217 | E10: 257545 | F10: 15751 | G10: =D10/D9-1 -> 0.077616918 | H10: =E10/E9-1 -> 0.10175908 | I10: =F10/F9-1 -> 0.1443621
A11: Mastercard | B11: 2021 | C11: 2021-12-31T12:00:00.000Z | D11: 5959 | E11: 112090 | F11: 10476
A12: Mastercard | B12: 2022 | C12: 2022-12-31T12:00:00.000Z | D12: 6571 | E12: 125680 | F12: 12445 | G12: =D12/D11-1 -> 0.1027018 | H12: =E12/E11-1 -> 0.12124186 | I12: =F12/F11-1 -> 0.18795342
A13: Mastercard | B13: 2023 | C13: 2023-12-31T12:00:00.000Z | D13: 7345 | E13: 143196 | F13: 15181 | G13: =D13/D12-1 -> 0.11779029 | H13: =E13/E12-1 -> 0.13936983 | I13: =F13/F12-1 -> 0.21984733
A14: Mastercard | B14: 2024 | C14: 2024-12-31T12:00:00.000Z | D14: 8003 | E14: 159424 | F14: 17629 | G14: =D14/D13-1 -> 0.089584752 | H14: =E14/E13-1 -> 0.11332719 | I14: =F14/F13-1 -> 0.1612542
A15: Mastercard | B15: 2025 | C15: 2025-12-31T12:00:00.000Z | D15: 8799 | E15: 175464 | F15: 20522 | G15: =D15/D14-1 -> 0.099462701 | H15: =E15/E14-1 -> 0.1006122 | I15: =F15/F14-1 -> 0.1641046
A17: Visa: processed transactions; reported consolidated client incentives.
A18: Mastercard: switched transactions; deductions derived from reclassified payment-network assessments less network net revenue.
A19: FY2023 Mastercard: derived 15,181m; narrative 15,182m. The 1m residual reflects rounded published components.
A20: Incentives are revenue deductions, not cash paid. No common take-rate or average ticket is calculated.
A21: Visa FY2021 transactions use the FY2023 comparative (164,734m), versus 164,733m in FY2021. Source editions are retained.
A23: Issuer | B23: FY | C23: Metric | D23: Value in source units | E23: Scale | F23: Basis | G23: PDF page(s) | H23: Source file | I23: Source URL | J23: Scope
A24: visa | B24: 2021 | C24: payment_volume | D24: 10401 | E24: 1000000000 | F24: reported_nominal_USD | G24: 3 | H24: data/raw/industry_supplements/visa_2021_supplement.pdf | I24: https://investor.visa.com/files/doc_financials/2021/q4/Visa-Inc.-Fourth-Quarter-and-Full-Year-2021-Operational-Performance-Data.pdf | J24: Worldwide Visa credit and debit payments, excluding cash
A25: visa | B25: 2021 | C25: network_transactions | D25: 164734 | E25: 1000000 | F25: reported | G25: 53 | H25: data/raw/issuer_reports/visa/FY2023_annual_report.pdf | I25: https://s29.q4cdn.com/385744025/files/doc_downloads/2023/Visa-Inc-Fiscal-2023-Annual-Report.pdf | J25: Transactions processed on Visa networks, including payment and cash
A26: visa | B26: 2022 | C26: payment_volume | D26: 11614 | E26: 1000000000 | F26: reported_nominal_USD | G26: 3 | H26: data/raw/industry_supplements/visa_2023_supplement.pdf | I26: https://s1.q4cdn.com/050606653/files/doc_financials/2023/q4/Q4FY23-Visa-Operational-Performance-Data.pdf | J26: Worldwide Visa credit and debit payments, excluding cash
A27: visa | B27: 2022 | C27: network_transactions | D27: 192530 | E27: 1000000 | F27: reported | G27: 53 | H27: data/raw/issuer_reports/visa/FY2023_annual_report.pdf | I27: https://s29.q4cdn.com/385744025/files/doc_downloads/2023/Visa-Inc-Fiscal-2023-Annual-Report.pdf | J27: Transactions processed on Visa networks, including payment and cash
A28: visa | B28: 2023 | C28: payment_volume | D28: 12338 | E28: 1000000000 | F28: reported_nominal_USD | G28: 3 | H28: data/raw/industry_supplements/visa_2023_supplement.pdf | I28: https://s1.q4cdn.com/050606653/files/doc_financials/2023/q4/Q4FY23-Visa-Operational-Performance-Data.pdf | J28: Worldwide Visa credit and debit payments, excluding cash
A29: visa | B29: 2023 | C29: network_transactions | D29: 212579 | E29: 1000000 | F29: reported | G29: 53 | H29: data/raw/issuer_reports/visa/FY2023_annual_report.pdf | I29: https://s29.q4cdn.com/385744025/files/doc_downloads/2023/Visa-Inc-Fiscal-2023-Annual-Report.pdf | J29: Transactions processed on Visa networks, including payment and cash
A30: visa | B30: 2024 | C30: payment_volume | D30: 13193 | E30: 1000000000 | F30: reported_nominal_USD | G30: 3 | H30: data/raw/industry_supplements/visa_2025_supplement.pdf | I30: https://s1.q4cdn.com/050606653/files/doc_financials/2025/q4/Q4FY25-Visa-Operational-Performance-Data.pdf | J30: Worldwide Visa credit and debit payments, excluding cash
A31: visa | B31: 2024 | C31: network_transactions | D31: 233758 | E31: 1000000 | F31: reported | G31: 60 | H31: data/raw/issuer_reports/visa/FY2025_annual_report.pdf | I31: https://s29.q4cdn.com/385744025/files/doc_downloads/2025/Visa-Fiscal-2025-Annual-Report.pdf | J31: Transactions processed on Visa networks, including payment and cash
A32: visa | B32: 2025 | C32: payment_volume | D32: 14217 | E32: 1000000000 | F32: reported_nominal_USD | G32: 3 | H32: data/raw/industry_supplements/visa_2025_supplement.pdf | I32: https://s1.q4cdn.com/050606653/files/doc_financials/2025/q4/Q4FY25-Visa-Operational-Performance-Data.pdf | J32: Worldwide Visa credit and debit payments, excluding cash
A33: visa | B33: 2025 | C33: network_transactions | D33: 257545 | E33: 1000000 | F33: reported | G33: 60 | H33: data/raw/issuer_reports/visa/FY2025_annual_report.pdf | I33: https://s29.q4cdn.com/385744025/files/doc_downloads/2025/Visa-Fiscal-2025-Annual-Report.pdf | J33: Transactions processed on Visa networks, including payment and cash
A34: mastercard | B34: 2021 | C34: payment_volume | D34: 5959 | E34: 1000000000 | F34: reported_nominal_USD | G34: 2 | H34: data/raw/industry_supplements/mastercard_2021_supplement.pdf | I34: https://investor.mastercard.com/files/doc_financials/2021/q4/4Q21-Mastercard-Supplemental-Operational-Performance-Data.pdf | J34: Worldwide Mastercard credit, charge, debit and prepaid purchases, excluding cash, Maestro and Cirrus
A35: mastercard | B35: 2021 | C35: network_transactions | D35: 112090 | E35: 1000000 | F35: reported | G35: 8 | H35: data/raw/industry_supplements/mastercard_2021_supplement.pdf | I35: https://investor.mastercard.com/files/doc_financials/2021/q4/4Q21-Mastercard-Supplemental-Operational-Performance-Data.pdf | J35: Transactions initiated and switched through Mastercard network
... A53: mastercard | B53: 2025 | C53: customer_incentives | D53: 20522 | E53: 1000000 | F53: derived_assessments_less_network_net_revenue | G53: 56, 57 | H53: data/raw/issuer_reports/mastercard/FY2025_annual_report.pdf | I53: https://s25.q4cdn.com/479285134/files/doc_financials/2025/q4/MA-12-31-2025-10-K-as-filed-with-standard-exhibits.pdf | J53: Mastercard payment-network revenue deductions; excludes value-added services and solutions
